Workbook

Sheet Cover Page
D2: THE ANUP ENGINEERING LIMITED
B7: Integrated Financial Model • Forecasts & Equity Valuation
B10: ABOUT THE COMPANY
B11: The Anup Engineering Limited, part of the Lalbhai Group, is an Indian heavy-engineering company specializing in the design and fabrication of critical process equipment — including heat exchangers, reactors, pressure vessels and other custom-built equipment — for the oil & gas, refining, petrochemical, fertilizer and power sectors.
B16: TABLE OF CONTENTS
B17: 01 Income Statement | F17: 07 DCF Model
B18: 02 Balance Sheet | F18: 08 Peer Comparison
B19: 03 Cash Flow Statement | F19: 09 Peer Data
B20: 04 Revenue Segments | F20: 10 Beta
B21: 05 Graphical Representation | F21: 11 Risk Data
B22: 06 Estimate Sheet | F22: 12 Guidance
B24: COLOR KEY
C25: Hardcoded data / Actuals
C26: Formula / Cell links
C27: Assumptions / Drivers
B29: AUTHOR & MODEL INFORMATION
B30: Author | D30: Niranjan Desai
B31: Date | D31: 5 June 2026
B32: Purpose | D32: This forecasting financial model is prepared for academic and competition purposes.
B33: Description | D33: This model comprises proprietary formulas, logical structures and analytical frameworks created by the author for The Anup Engineering Limited (standalone entity).
B35: Acknowledgements | D35: Bloomberg (financial data); NMIMS (academic resources); and The Anup Engineering Limited annual reports & investor presentations.
B37: Contact | D37: +91 97699 87893
B38: Email (Personal) | D38: mr.niranjandesai@gmail.com
B39: Email (Academic) | D39: niranjan.desai553@nmims.in
B41: All figures in INR Crores (₹ Cr) unless stated. Disclaimer: This model is prepared for illustrative and educational purposes only and does not constitute investment advice or a recommendation to buy or sell any security.

Sheet Income Statement
B1: Anup Engineering Limited
B2: Fiscal year ending 31st Mar, 2026 | C2: H1 | D2: H2 | E2: FY | F2: H1 | G2: H2 | H2: FY | I2: H1 | J2: H2 | K2: FY | L2: H1 | M2: H2 | N2: FY | O2: H1 | P2: H2 | Q2: FY | R2: H1 | S2: H2 | T2: FY | U2: H1 | V2: H2 | W2: FY | X2: H1 | Y2: H2 | Z2: FY | AA2: H1 | AB2: H2 | AC2: FY | AD2: H1 | AE2: H2 | AF2: FY | AG2: H1 | AH2: H2 | AI2: FY
B3: All amounts in ₹ crores except per share data | C3: 2021 | D3: 2021 | E3: 2021 | F3: 2022 | G3: 2022 | H3: 2022 | I3: 2023 | J3: 2023 | K3: 2023 | L3: 2024 | M3: 2024 | N3: 2024 | O3: 2025 | P3: 2025 | Q3: 2025 | R3: 2026 | S3: 2026 | T3: 2026 | U3: 2027 E | V3: 2027 E | W3: 2027 E | X3: 2028 E | Y3: 2028 E | Z3: 2028 E | AA3: 2029 E | AB3: 2029 E | AC3: 2029 E | AD3: 2030 E | AE3: 2030 E | AF3: 2030 E | AG3: 2031 E | AH3: 2031 E | AI3: 2031 E
B5: INCOME STATEMENT
B7: Income
B8: Revenue from operations | C8: 116.8959 | D8: =E8-C8 | E8: 279.1296 | F8: 141.0507 | G8: =H8-F8 | H8: 288.2416 | I8: 152.7418 | J8: =K8-I8 | K8: 411.3381 | L8: 265.0608 | M8: =N8-L8 | N8: 550.3845 | O8: 339.1337 | P8: =Q8-O8 | Q8: 732.786 | R8: 407.5122 | S8: =T8-R8 | T8: 822.2877 | U8: ='Revenue Segments'!U69 | V8: ='Revenue Segments'!V69 | W8: ='Revenue Segments'!W69 | X8: ='Revenue Segments'!X69 | Y8: ='Revenue Segments'!Y69 | Z8: ='Revenue Segments'!Z69 | AA8: ='Revenue Segments'!AA69 | AB8: ='Revenue Segments'!AB69 | ... AI8: ='Revenue Segments'!AI69
B9: Growth % | F9: =(F8-C8)/C8 | G9: =(G8-D8)/D8 | H9: =(H8-E8)/E8 | I9: =(I8-F8)/F8 | J9: =(J8-G8)/G8 | K9: =(K8-H8)/H8 | L9: =(L8-I8)/I8 | M9: =(M8-J8)/J8 | ... AI9: =(AI8-AF8)/AF8
B12: Cost of materials consumed | C12: 53.5332 | D12: =E12-C12 | E12: 140.3952 | F12: 69.5237 | G12: =H12-F12 | H12: 162.7251 | I12: 103.0964 | J12: =K12-I12 | K12: 233.208 | L12: 118.2643 | M12: =N12-L12 | N12: 271.6647 | O12: 201.7059 | P12: =Q12-O12 | Q12: 409.9813 | R12: 186.8596 | S12: =T12-R12 | T12: 374.8979
B13: Changes in inventories | C13: 11.7919 | D13: =E13-C13 | E13: 7.6665 | F13: -2.8458 | G13: =H13-F13 | H13: -22.5585 | I13: -19.8119 | J13: =K13-I13 | K13: -11.3768 | L13: 21.0177 | M13: =N13-L13 | N13: 13.3156 | O13: -14.7911 | P13: =Q13-O13 | Q13: -12.3133 | R13: 4.9015 | S13: =T13-R13 | T13: 18.4005
B14: Cost of Goods Sold | C14: =C12+C13 | D14: =D12+D13 | E14: =E12+E13 | F14: =F12+F13 | G14: =G12+G13 | H14: =H12+H13 | I14: =I12+I13 | J14: =J12+J13 | ... T14: =T12+T13 | U14: =U8*U15 | V14: =V8*V15 | W14: =U14+V14 | X14: =X8*X15 | Y14: =Y8*Y15 | Z14: =X14+Y14 | AA14: =AA8*AA15 | AB14: =AB8*AB15 | AC14: =AA14+AB14 | AD14: =AD8*AD15 | AE14: =AE8*AE15 | AF14: =AD14+AE14 | AG14: =AG8*AG15 | AH14: =AH8*AH15 | AI14: =AG14+AH14
B15: As % of Sales | C15: =C14/C8 | D15: =D14/D8 | E15: =E14/E8 | F15: =F14/F8 | G15: =G14/G8 | H15: =H14/H8 | I15: =I14/I8 | J15: =J14/J8 | ... T15: =T14/T8 | U15: 0.48 | V15: =U15 | W15: =W14/W8 | X15: 0.48 | Y15: =X15 | Z15: =Z14/Z8 | AA15: 0.48 | AB15: =AA15 | AC15: =AC14/AC8 | AD15: =AB15-0.5% | AE15: =AD15 | AF15: =AF14/AF8 | AG15: =AE15-0.5% | AH15: =AG15 | AI15: =AI14/AI8
B17: Gross Profit | C17: =C8-C14 | D17: =D8-D14 | E17: =E8-E14 | F17: =F8-F14 | G17: =G8-G14 | H17: =H8-H14 | I17: =I8-I14 | J17: =J8-J14 | ... AI17: =AI8-AI14
B18: Gross Margin | C18: =C17/C8 | D18: =D17/D8 | E18: =E17/E8 | F18: =F17/F8 | G18: =G17/G8 | H18: =H17/H8 | I18: =I17/I8 | J18: =J17/J8 | ... AI18: =AI17/AI8
B20: Employee benefits expense | C20: 8.4449 | D20: =E20-C20 | E20: 17.3837 | F20: 11.1719 | G20: =H20-F20 | H20: 20.3548 | I20: 9.4939 | J20: =K20-I20 | K20: 20.9578 | L20: 15.5905 | M20: =N20-L20 | N20: 30.9611 | O20: 19.5635 | P20: =Q20-O20 | Q20: 41.8524 | R20: 25.2866 | S20: =T20-R20 | T20: 51.2752 | U20: =U8*U21 | V20: =V8*V21 | W20: =U20+V20 | X20: =X8*X21 | Y20: =Y8*Y21 | Z20: =X20+Y20 | AA20: =AA8*AA21 | AB20: =AB8*AB21 | AC20: =AA20+AB20 | AD20: =AD8*AD21 | AE20: =AE8*AE21 | AF20: =AD20+AE20 | AG20: =AG8*AG21 | AH20: =AH8*AH21 | AI20: =AG20+AH20
B21: As % of Sales | C21: =C20/C8 | D21: =D20/D8 | E21: =E20/E8 | F21: =F20/F8 | G21: =G20/G8 | H21: =H20/H8 | I21: =I20/I8 | J21: =J20/J8 | ... T21: =T20/T8 | U21: 0.058 | V21: =U21 | W21: =W20/W8 | X21: =V21 | Y21: =X21 | Z21: =Z20/Z8 | AA21: =Y21 | AB21: =AA21 | AC21: =AC20/AC8 | AD21: =AB21 | AE21: =AD21 | AF21: =AF20/AF8 | AG21: =AE21 | AH21: =AG21 | AI21: =AI20/AI8
B22: Other expenses | C22: 16.6056 | D22: =E22-C22 | E22: 44.9232 | F22: 28.0228 | G22: =H22-F22 | H22: 57.742 | I22: 30.0765 | J22: =K22-I22 | K22: 85.8442 | L22: 50.8185 | M22: =N22-L22 | N22: 107.6925 | O22: 56.3075 | P22: =Q22-O22 | Q22: 128.0416 | R22: 98.6367 | S22: =T22-R22 | T22: 203.5519 | U22: =U8*'Income Statement'!U58 | V22: =V8*'Income Statement'!V58 | W22: =U22+V22 | X22: =X8*'Income Statement'!X58 | Y22: =Y8*'Income Statement'!Y58 | Z22: =X22+Y22 | AA22: =AA8*'Income Statement'!AA58 | AB22: =AB8*'Income Statement'!AB58 | AC22: =AA22+AB22 | AD22: =AD8*'Income Statement'!AD58 | AE22: =AE8*'Income Statement'!AE58 | AF22: =AD22+AE22 | AG22: =AG8*'Income Statement'!AG58 | AH22: =AH8*'Income Statement'!AH58 | AI22: =AG22+AH22
B23: EBITDA | C23: =C17-SUM(C20,C22) | D23: =D17-SUM(D20,D22) | E23: =E17-SUM(E20,E22) | F23: =F17-SUM(F20,F22) | G23: =G17-SUM(G20,G22) | H23: =H17-SUM(H20,H22) | I23: =I17-SUM(I20,I22) | J23: =J17-SUM(J20,J22) | ... AI23: =AI17-SUM(AI20,AI22)
B24: EBITDA Margin | C24: =C23/C8 | D24: =D23/D8 | E24: =E23/E8 | F24: =F23/F8 | G24: =G23/G8 | H24: =H23/H8 | I24: =I23/I8 | J24: =J23/J8 | ... AI24: =AI23/AI8
B26: D&A Expenses | C26: 4.5149 | D26: =E26-C26 | E26: 10.5059 | F26: 5.7862 | G26: =H26-F26 | H26: 11.5922 | I26: 5.8629 | J26: =K26-I26 | K26: 12.5405 | L26: 7.0289 | M26: =N26-L26 | N26: 17.464 | O26: 11.3557 | P26: =Q26-O26 | Q26: 23.819 | R26: 13.2423 | S26: =T26-R26 | T26: 27.841 | U26: ='Balance Sheet'!U63 | V26: ='Balance Sheet'!V63 | W26: =U26+V26 | X26: ='Balance Sheet'!X63 | Y26: ='Balance Sheet'!Y63 | Z26: =X26+Y26 | AA26: ='Balance Sheet'!AA63 | AB26: ='Balance Sheet'!AB63 | AC26: =AA26+AB26 | AD26: ='Balance Sheet'!AD63 | AE26: ='Balance Sheet'!AE63 | AF26: =AD26+AE26 | AG26: ='Balance Sheet'!AG63 | AH26: ='Balance Sheet'!AH63 | AI26: =AG26+AH26
B27: EBIT/Operating Income | C27: =C23-C26 | D27: =D23-D26 | E27: =E23-E26 | F27: =F23-F26 | G27: =G23-G26 | H27: =H23-H26 | I27: =I23-I26 | J27: =J23-J26 | ... AI27: =AI23-AI26
B28: EBIT Margin | C28: =C27/C8 | D28: =D27/D8 | E28: =E27/E8 | F28: =F27/F8 | G28: =G27/G8 | H28: =H27/H8 | I28: =I27/I8 | J28: =J27/J8 | ... AI28: =AI27/AI8
B30: Other Income | C30: 1.5638 | D30: =E30-C30 | E30: 3.5543 | F30: 0.9833 | G30: =H30-F30 | H30: 3.7677 | I30: 0.6182 | J30: =K30-I30 | K30: 1.2421 | L30: 2.0524 | M30: =N30-L30 | N30: 9.0637 | O30: 3.9853 | P30: =Q30-O30 | Q30: 5.1341 | R30: 2.6912 | S30: =T30-R30 | T30: 1.6776 | U30: =T30 | V30: =U30 | W30: =U30+V30 | X30: =V30 | Y30: =X30 | Z30: =X30+Y30 | AA30: =Y30 | AB30: =AA30 | AC30: =AA30+AB30 | AD30: =AB30 | AE30: =AD30 | AF30: =AD30+AE30 | AG30: =AE30 | AH30: =AG30 | AI30: =AG30+AH30
B31: Finance Cost | C31: 0.2708 | D31: =E31-C31 | E31: 0.3444 | F31: 0.2223 | G31: =H31-F31 | H31: 1.0315 | I31: 0.5961 | J31: =K31-I31 | K31: 1.4083 | L31: 0.2067 | M31: =N31-L31 | N31: 2.1744 | O31: 1.9606 | P31: =Q31-O31 | Q31: 3.3389 | R31: 2.9776 | S31: =T31-R31 | T31: 8.6983 | U31: ='Income Statement'!U61 | V31: ='Income Statement'!V61 | W31: =U31+V31 | X31: ='Income Statement'!X61 | Y31: ='Income Statement'!Y61 | Z31: =X31+Y31 | AA31: ='Income Statement'!AA61 | AB31: ='Income Statement'!AB61 | AC31: =AA31+AB31 | AD31: ='Income Statement'!AD61 | AE31: ='Income Statement'!AE61 | AF31: =AD31+AE31 | AG31: ='Income Statement'!AG61 | AH31: ='Income Statement'!AH61 | AI31: =AG31+AH31
B32: PBT | C32: =C27+C30-C31 | D32: =D27+D30-D31 | E32: =E27+E30-E31 | F32: =F27+F30-F31 | G32: =G27+G30-G31 | H32: =H27+H30-H31 | I32: =I27+I30-I31 | J32: =J27+J30-J31 | ... AI32: =AI27+AI30-AI31
B33: PBT Margin | C33: =C32/C8 | D33: =D32/D8 | E33: =E32/E8 | F33: =F32/F8 | G33: =G32/G8 | H33: =H32/H8 | I33: =I32/I8 | J33: =J32/J8 | ... AI33: =AI32/AI8
B34: check | C34: 23.2984 | E34: 61.465 | F34: 30.1529 | H34: 61.1222 | I34: 24.0461 | K34: 69.9982 | L34: 54.1866 | N34: 116.1759 | O34: 67.0169 | Q34: 143.2002 | R34: 78.2991 | T34: 139.3005
B35: difference | C35: =C32-C34 | E35: =E32-E34 | F35: =F32-F34 | H35: =H32-H34 | I35: =I32-I34 | K35: =K32-K34 | L35: =L32-L34 | N35: =N32-N34 | O35: =O32-O34 | Q35: =Q32-Q34 | R35: =R32-R34 | T35: =T32-T34
B37: Tax Expense
B38: Current Tax | C38: 6.72 | D38: =E38-C38 | E38: 15.15 | F38: 7.13 | G38: =H38-F38 | H38: 15.45 | I38: 6.13 | J38: =K38-I38 | K38: 18.15 | L38: 14.04 | M38: =N38-L38 | N38: 26.5 | O38: 12.5596 | P38: =Q38-O38 | Q38: 30.0692 | R38: 20.4941 | S38: =T38-R38 | T38: 34.6886
B39: Earlier Years tax | C39: 0 | D39: =E39-C39 | E39: -6.916 | F39: 0 | G39: =H39-F39 | H39: -15.5737 | I39: 0 | J39: =K39-I39 | K39: 0 | L39: 0 | M39: =N39-L39 | N39: -14.5115 | O39: 0 | P39: =Q39-O39 | Q39: -3.4566 | R39: 0 | S39: =T39-R39 | T39: -5.3208
B40: Deferred Tax Charge/(Credit) | C40: -0.2848 | D40: =E40-C40 | E40: -0.2922 | F40: -0.6155 | G40: =H40-F40 | H40: -0.8085 | I40: -0.1702 | J40: =K40-I40 | K40: 0.4182 | L40: -0.1333 | M40: =N40-L40 | N40: 0.7124 | O40: -2.0961 | P40: =Q40-O40 | Q40: -1.7151 | R40: -0.5089 | S40: =T40-R40 | T40: -0.4597
B41: Total Tax Expense | C41: =SUM(C38:C40) | D41: =SUM(D38:D40) | E41: =SUM(E38:E40) | F41: =SUM(F38:F40) | G41: =SUM(G38:G40) | H41: =SUM(H38:H40) | I41: =SUM(I38:I40) | J41: =SUM(J38:J40) | ... T41: =SUM(T38:T40) | U41: =U32*U62 | V41: =V32*V62 | W41: =U41+V41 | X41: =X32*X62 | Y41: =Y32*Y62 | Z41: =X41+Y41 | AA41: =AA32*AA62 | AB41: =AB32*AB62 | AC41: =AA41+AB41 | AD41: =AD32*AD62 | AE41: =AE32*AE62 | AF41: =AD41+AE41 | AG41: =AG32*AG62 | AH41: =AH32*AH62 | AI41: =AG41+AH41
B43: PAT | C43: =C32-C41 | D43: =D32-D41 | E43: =E32-E41 | F43: =F32-F41 | G43: =G32-G41 | H43: =H32-H41 | I43: =I32-I41 | J43: =J32-J41 | ... AI43: =AI32-AI41
B44: check | C44: 16.8632 | E44: 53.5232 | F44: 23.6384 | H44: 62.0544 | I44: 18.0863 | K44: 51.43 | L44: 40.2799 | N44: 103.475 | O44: 56.5534 | Q44: 118.3027 | R44: 58.3139 | T44: 110.3924
B45: difference | C45: =C43-C44 | E45: =E43-E44 | F45: =F43-F44 | H45: =H43-H44 | I45: =I43-I44 | K45: =K43-K44 | L45: =L43-L44 | N45: =N43-N44 | O45: =O43-O44 | Q45: =Q43-Q44 | R45: =R43-R44 | T45: =T43-T44
B46: PAT Margin | C46: =C43/C8 | D46: =D43/D8 | E46: =E43/E8 | F46: =F43/F8 | G46: =G43/G8 | H46: =H43/H8 | I46: =I43/I8 | J46: =J43/J8 | ... AI46: =AI43/AI8
B48: Outstanding Shares (in crores) | C48: 2.00025 | D48: 2.00025 | E48: 2.00025 | F48: 2.00025 | G48: 2.00025 | H48: 2.00025 | I48: 2.00025 | J48: 2.00025 | K48: 2.00025 | L48: 2.00025 | M48: 2.00025 | N48: 2.00025 | O48: 2.00025 | P48: 2.00265 | Q48: 2.00265 | R48: 2.00265 | S48: 2.00315 | T48: 2.00315 | U48: =T48 | V48: =U48 | W48: =V48 | X48: =W48 | Y48: =X48 | Z48: =Y48 | AA48: =Z48 | AB48: =AA48 | ... AI48: =AH48
B49: EPS | C49: =C43/C48 | D49: =D43/D48 | E49: =E43/E48 | F49: =F43/F48 | G49: =G43/G48 | H49: =H43/H48 | I49: =I43/I48 | J49: =J43/J48 | ... AI49: =AI43/AI48
B50: MPS | C50: 275.15 | D50: 331.9 | E50: 331.9 | F50: 505.85 | G50: 400.45 | H50: 400.45 | I50: 424.93 | J50: 699.45 | K50: 699.45 | L50: 1196.93 | M50: 1949.25 | N50: 1949.25 | O50: 3148.85 | P50: 2991.2 | Q50: 2991.2 | R50: 2447.3 | S50: 1840.1 | T50: 1840.1
B51: Market Cap | C51: =C48*C50 | D51: =D48*D50 | E51: =E48*E50 | F51: =F48*F50 | G51: =G48*G50 | H51: =H48*H50 | I51: =I48*I50 | J51: =J48*J50 | ... T51: =T48*T50
B52: Results Date | C52: 31/10/2020 | D52: =E52 | E52: 14/05/2021 | F52: 26/10/2021 | G52: =H52 | H52: 17/05/2022 | I52: 17/10/2022 | J52: =K52 | K52: 17/05/2023 | L52: 30/10/2023 | M52: =N52 | N52: 45387 | O52: 26/10/2024 | P52: =Q52 | Q52: 13/05/2025 | R52: 45941 | S52: =T52 | T52: 28/05/2026
B53: Dividend per Share | C53: 7 | E53: 7 | F53: 7 | H53: 7 | I53: 8 | K53: 8 | L53: 15 | N53: 15 | O53: 15 | Q53: 15 | R53: 17 | T53: =SUM(R53:S53) | U53: =U56/U48 | W53: =W49*W55 | X53: =X56/X48 | Z53: =Z49*Z55 | AA53: =AA56/AA48 | AC53: =AC49*AC55 | AD53: =AD56/AD48 | AF53: =AF49*AF55 | AG53: =AG56/AG48 | AI53: =AI49*AI55
B54: Dividend Yield | C54: =C53/C50 | E54: =E53/E50 | F54: =F53/F50 | H54: =H53/H50 | I54: =I53/I50 | K54: =K53/K50 | L54: =L53/L50 | N54: =N53/N50 | O54: =O53/O50 | Q54: =Q53/Q50 | R54: =R53/R50 | T54: =T53/T50
B55: Dividend payout ratio | E55: =E53/E49 | H55: =H53/H49 | K55: =K53/K49 | L55: =L53/L49 | N55: =N53/N49 | Q55: =Q53/Q49 | R55: =R53/R49 | T55: =T53/T49 | W55: 0.4 | Z55: =W55+5% | AC55: =Z55+5% | AF55: =AC55+5% | AI55: =AF55+5%
B56: Dividend Paid | C56: 0.0006 | D56: =E56-C56 | E56: 7.0228 | F56: 6.7938 | G56: =H56-F56 | H56: 6.7964 | I56: 7.8133 | J56: =K56-I56 | K56: 7.81 | L56: 14.6934 | M56: =N56-L56 | N56: 14.6675 | O56: 39.2369 | Q56: =SUM(O56:P56) | R56: 33.5658 | T56: =SUM(R56:S56) | U56: =W56 | V56: =V53*V48 | W56: =W53*W48 | X56: =Z56 | Y56: =Y53*Y48 | Z56: =Z53*Z48 | AA56: =AC56 | AB56: =AB53*AB48 | AC56: =AC53*AC48 | AD56: =AF56 | AE56: =AE53*AE48 | AF56: =AF53*AF48 | AG56: =AI56 | AH56: =AH53*AH48 | AI56: =AI53*AI48
B58: Other Expenses as % of Revenue | E58: =E22/E8 | F58: =F22/F8 | G58: =G22/G8 | H58: =H22/H8 | I58: =I22/I8 | J58: =J22/J8 | K58: =K22/K8 | L58: =L22/L8 | ... T58: =T22/T8 | U58: 0.25 | V58: =U58 | W58: =W22/W8 | X58: =W58 | Y58: =X58 | Z58: =Z22/Z8 | AA58: =Z58 | AB58: =AA58 | AC58: =AC22/AC8 | AD58: =AC58 | AE58: =AD58 | AF58: =AF22/AF8 | AG58: =AF58 | AH58: =AG58 | AI58: =AI22/AI8
B59: Average Debt | C59: =SUM('Balance Sheet'!C13,'Balance Sheet'!C19,'Balance Sheet'!B13,'Balance Sheet'!B19)/2 | D59: =SUM('Balance Sheet'!D13,'Balance Sheet'!D19,'Balance Sheet'!C13,'Balance Sheet'!C19)/2 | E59: =SUM('Balance Sheet'!E13,'Balance Sheet'!E19,'Balance Sheet'!D13,'Balance Sheet'!D19)/2 | F59: =SUM('Balance Sheet'!F13,'Balance Sheet'!F19,'Balance Sheet'!E13,'Balance Sheet'!E19)/2 | G59: =SUM('Balance Sheet'!G13,'Balance Sheet'!G19,'Balance Sheet'!F13,'Balance Sheet'!F19)/2 | H59: =SUM('Balance Sheet'!H13,'Balance Sheet'!H19,'Balance Sheet'!G13,'Balance Sheet'!G19)/2 | I59: =SUM('Balance Sheet'!I13,'Balance Sheet'!I19,'Balance Sheet'!H13,'Balance Sheet'!H19)/2 | J59: =SUM('Balance Sheet'!J13,'Balance Sheet'!J19,'Balance Sheet'!I13,'Balance Sheet'!I19)/2 | ... V59: =SUM('Balance Sheet'!V13,'Balance Sheet'!V19,'Balance Sheet'!U13,'Balance Sheet'!U19)/2 | W59: =SUM('Balance Sheet'!W13,'Balance Sheet'!W19,'Balance Sheet'!T13,'Balance Sheet'!T19)/2 | X59: =SUM('Balance Sheet'!X13,'Balance Sheet'!X19,'Balance Sheet'!W13,'Balance Sheet'!W19)/2 | Y59: =SUM('Balance Sheet'!Y13,'Balance Sheet'!Y19,'Balance Sheet'!X13,'Balance Sheet'!X19)/2 | Z59: =SUM('Balance Sheet'!Z13,'Balance Sheet'!Z19,'Balance Sheet'!W13,'Balance Sheet'!W19)/2 | AA59: =SUM('Balance Sheet'!AA13,'Balance Sheet'!AA19,'Balance Sheet'!Z13,'Balance Sheet'!Z19)/2 | AB59: =SUM('Balance Sheet'!AB13,'Balance Sheet'!AB19,'Balance Sheet'!AA13,'Balance Sheet'!AA19)/2 | AC59: =SUM('Balance Sheet'!AC13,'Balance Sheet'!AC19,'Balance Sheet'!Z13,'Balance Sheet'!Z19)/2 | AD59: =SUM('Balance Sheet'!AD13,'Balance Sheet'!AD19,'Balance Sheet'!AC13,'Balance Sheet'!AC19)/2 | AE59: =SUM('Balance Sheet'!AE13,'Balance Sheet'!AE19,'Balance Sheet'!AD13,'Balance Sheet'!AD19)/2 | AF59: =SUM('Balance Sheet'!AF13,'Balance Sheet'!AF19,'Balance Sheet'!AC13,'Balance Sheet'!AC19)/2 | AG59: =SUM('Balance Sheet'!AG13,'Balance Sheet'!AG19,'Balance Sheet'!AF13,'Balance Sheet'!AF19)/2 | AH59: =SUM('Balance Sheet'!AH13,'Balance Sheet'!AH19,'Balance Sheet'!AG13,'Balance Sheet'!AG19)/2 | AI59: =SUM('Balance Sheet'!AI13,'Balance Sheet'!AI19,'Balance Sheet'!AF13,'Balance Sheet'!AF19)/2
B60: Interest Rate | J60: =J61*2/J59 | K60: =K61/K59 | L60: =L61*2/L59 | M60: =M61*2/M59 | N60: =N61/N59 | O60: =O61*2/O59 | P60: =P61*2/P59 | Q60: =Q61/Q59 | R60: =R61*2/R59 | S60: =S61*2/S59 | T60: =T61/T59 | U60: =S60 | V60: =U60 | W60: =W61/W59 | X60: =V60 | Y60: =X60 | Z60: =Z61/Z59 | AA60: =Y60 | AB60: =AA60 | AC60: =AC61/AC59 | AD60: =AB60 | AE60: =AD60 | AF60: =AF61/AF59 | AG60: =AE60 | AH60: =AG60 | AI60: =AI61/AI59
B61: Finance Cost | C61: ='Income Statement'!C31 | D61: ='Income Statement'!D31 | E61: ='Income Statement'!E31 | F61: ='Income Statement'!F31 | G61: ='Income Statement'!G31 | H61: ='Income Statement'!H31 | I61: ='Income Statement'!I31 | J61: ='Income Statement'!J31 | ... T61: ='Income Statement'!T31 | U61: =U59*U60/2 | V61: =V59*V60/2 | W61: =U61+V61 | X61: =X59*X60/2 | Y61: =Y59*Y60/2 | Z61: =X61+Y61 | AA61: =AA59*AA60/2 | AB61: =AB59*AB60/2 | AC61: =AA61+AB61 | AD61: =AD59*AD60/2 | AE61: =AE59*AE60/2 | AF61: =AD61+AE61 | AG61: =AG59*AG60/2 | AH61: =AH59*AH60/2 | AI61: =AG61+AH61
B62: Effective Tax Rate | C62: ='Income Statement'!C41/'Income Statement'!C32 | D62: ='Income Statement'!D41/'Income Statement'!D32 | E62: ='Income Statement'!E41/'Income Statement'!E32 | F62: ='Income Statement'!F41/'Income Statement'!F32 | G62: ='Income Statement'!G41/'Income Statement'!G32 | H62: ='Income Statement'!H41/'Income Statement'!H32 | I62: ='Income Statement'!I41/'Income Statement'!I32 | J62: ='Income Statement'!J41/'Income Statement'!J32 | ... T62: ='Income Statement'!T41/'Income Statement'!T32 | U62: =Guidance!D19 | V62: =U62 | W62: ='Income Statement'!W41/'Income Statement'!W32 | X62: =V62 | Y62: =V62 | Z62: ='Income Statement'!Z41/'Income Statement'!Z32 | AA62: =Y62 | AB62: =Y62 | AC62: ='Income Statement'!AC41/'Income Statement'!AC32 | AD62: =AB62 | AE62: =AB62 | AF62: ='Income Statement'!AF41/'Income Statement'!AF32 | AG62: =AE62 | AH62: =AE62 | AI62: ='Income Statement'!AI41/'Income Statement'!AI32
B64: Ratio Analysis
B65: Interest Coverage Ratio | C65: ='Income Statement'!C23/'Income Statement'!C31 | D65: ='Income Statement'!D23/'Income Statement'!D31 | E65: ='Income Statement'!E23/'Income Statement'!E31 | F65: ='Income Statement'!F23/'Income Statement'!F31 | G65: ='Income Statement'!G23/'Income Statement'!G31 | H65: ='Income Statement'!H23/'Income Statement'!H31 | I65: ='Income Statement'!I23/'Income Statement'!I31 | J65: ='Income Statement'!J23/'Income Statement'!J31 | ... AI65: ='Income Statement'!AI23/'Income Statement'!AI31
B66: Gross Margin Ratio | C66: ='Income Statement'!C17/'Income Statement'!C8 | D66: ='Income Statement'!D17/'Income Statement'!D8 | E66: ='Income Statement'!E17/'Income Statement'!E8 | F66: ='Income Statement'!F17/'Income Statement'!F8 | G66: ='Income Statement'!G17/'Income Statement'!G8 | H66: ='Income Statement'!H17/'Income Statement'!H8 | I66: ='Income Statement'!I17/'Income Statement'!I8 | J66: ='Income Statement'!J17/'Income Statement'!J8 | ... AI66: ='Income Statement'!AI17/'Income Statement'!AI8
B67: EBITDA Margin | C67: ='Income Statement'!C23/'Income Statement'!C8 | D67: ='Income Statement'!D23/'Income Statement'!D8 | E67: ='Income Statement'!E23/'Income Statement'!E8 | F67: ='Income Statement'!F23/'Income Statement'!F8 | G67: ='Income Statement'!G23/'Income Statement'!G8 | H67: ='Income Statement'!H23/'Income Statement'!H8 | I67: ='Income Statement'!I23/'Income Statement'!I8 | J67: ='Income Statement'!J23/'Income Statement'!J8 | ... AI67: ='Income Statement'!AI23/'Income Statement'!AI8
B68: EBIT Margin | C68: ='Income Statement'!C27/'Income Statement'!C8 | D68: ='Income Statement'!D27/'Income Statement'!D8 | E68: ='Income Statement'!E27/'Income Statement'!E8 | F68: ='Income Statement'!F27/'Income Statement'!F8 | G68: ='Income Statement'!G27/'Income Statement'!G8 | H68: ='Income Statement'!H27/'Income Statement'!H8 | I68: ='Income Statement'!I27/'Income Statement'!I8 | J68: ='Income Statement'!J27/'Income Statement'!J8 | ... AI68: ='Income Statement'!AI27/'Income Statement'!AI8
B69: PAT Margin Ratio | C69: ='Income Statement'!C43/'Income Statement'!C8 | D69: ='Income Statement'!D43/'Income Statement'!D8 | E69: ='Income Statement'!E43/'Income Statement'!E8 | F69: ='Income Statement'!F43/'Income Statement'!F8 | G69: ='Income Statement'!G43/'Income Statement'!G8 | H69: ='Income Statement'!H43/'Income Statement'!H8 | I69: ='Income Statement'!I43/'Income Statement'!I8 | J69: ='Income Statement'!J43/'Income Statement'!J8 | ... AI69: ='Income Statement'!AI43/'Income Statement'!AI8
B70: Return on Assets | C70: ='Income Statement'!C43/'Balance Sheet'!C55 | D70: ='Income Statement'!D43/'Balance Sheet'!D55 | E70: ='Income Statement'!E43/'Balance Sheet'!E55 | F70: ='Income Statement'!F43/'Balance Sheet'!F55 | G70: ='Income Statement'!G43/'Balance Sheet'!G55 | H70: ='Income Statement'!H43/'Balance Sheet'!H55 | I70: ='Income Statement'!I43/'Balance Sheet'!I55 | J70: ='Income Statement'!J43/'Balance Sheet'!J55 | ... AI70: ='Income Statement'!AI43/'Balance Sheet'!AI55
B71: Return on Equity | C71: ='Income Statement'!C43/'Balance Sheet'!C11 | D71: ='Income Statement'!D43/'Balance Sheet'!D11 | E71: ='Income Statement'!E43/'Balance Sheet'!E11 | F71: ='Income Statement'!F43/'Balance Sheet'!F11 | G71: ='Income Statement'!G43/'Balance Sheet'!G11 | H71: ='Income Statement'!H43/'Balance Sheet'!H11 | I71: ='Income Statement'!I43/'Balance Sheet'!I11 | J71: ='Income Statement'!J43/'Balance Sheet'!J11 | ... AI71: ='Income Statement'!AI43/'Balance Sheet'!AI11
B72: Return on Capital Employed | C72: ='Income Statement'!C27/('Balance Sheet'!C55-'Balance Sheet'!C28) | D72: ='Income Statement'!D27/('Balance Sheet'!D55-'Balance Sheet'!D28) | E72: ='Income Statement'!E27/('Balance Sheet'!E55-'Balance Sheet'!E28) | F72: ='Income Statement'!F27/('Balance Sheet'!F55-'Balance Sheet'!F28) | G72: ='Income Statement'!G27/('Balance Sheet'!G55-'Balance Sheet'!G28) | H72: ='Income Statement'!H27/('Balance Sheet'!H55-'Balance Sheet'!H28) | I72: ='Income Statement'!I27/('Balance Sheet'!I55-'Balance Sheet'!I28) | J72: ='Income Statement'!J27/('Balance Sheet'!J55-'Balance Sheet'!J28) | ... AI72: ='Income Statement'!AI27/('Balance Sheet'!AI55-'Balance Sheet'!AI28)
B74: Times Interest Earned Ratio | C74: ='Income Statement'!C27/'Income Statement'!C31 | D74: ='Income Statement'!D27/'Income Statement'!D31 | E74: ='Income Statement'!E27/'Income Statement'!E31 | F74: ='Income Statement'!F27/'Income Statement'!F31 | G74: ='Income Statement'!G27/'Income Statement'!G31 | H74: ='Income Statement'!H27/'Income Statement'!H31 | I74: ='Income Statement'!I27/'Income Statement'!I31 | J74: ='Income Statement'!J27/'Income Statement'!J31 | ... AI74: ='Income Statement'!AI27/'Income Statement'!AI31
B75: Price/Sales Ratio | C75: ='Income Statement'!C51/('Income Statement'!C8*2) | D75: ='Income Statement'!D51/('Income Statement'!D8*2) | E75: ='Income Statement'!E51/'Income Statement'!E8 | F75: ='Income Statement'!F51/('Income Statement'!F8*2) | G75: ='Income Statement'!G51/('Income Statement'!G8*2) | H75: ='Income Statement'!H51/'Income Statement'!H8 | I75: ='Income Statement'!I51/('Income Statement'!I8*2) | J75: ='Income Statement'!J51/('Income Statement'!J8*2) | K75: ='Income Statement'!K51/'Income Statement'!K8 | L75: ='Income Statement'!L51/('Income Statement'!L8*2) | M75: ='Income Statement'!M51/('Income Statement'!M8*2) | N75: ='Income Statement'!N51/'Income Statement'!N8 | O75: ='Income Statement'!O51/('Income Statement'!O8*2) | P75: ='Income Statement'!P51/('Income Statement'!P8*2) | Q75: ='Income Statement'!Q51/'Income Statement'!Q8 | R75: ='Income Statement'!R51/('Income Statement'!R8*2) | S75: ='Income Statement'!S51/('Income Statement'!S8*2) | T75: ='Income Statement'!T51/'Income Statement'!T8 | U75: ='Income Statement'!U51/('Income Statement'!U8*2) | V75: ='Income Statement'!V51/('Income Statement'!V8*2) | W75: ='Income Statement'!W51/('Income Statement'!W8*2) | X75: ='Income Statement'!X51/('Income Statement'!X8*2) | Y75: ='Income Statement'!Y51/('Income Statement'!Y8*2) | Z75: ='Income Statement'!Z51/('Income Statement'!Z8*2) | AA75: ='Income Statement'!AA51/('Income Statement'!AA8*2) | AB75: ='Income Statement'!AB51/('Income Statement'!AB8*2) | ... AI75: ='Income Statement'!AI51/('Income Statement'!AI8*2)
B76: P/E Ratio | C76: ='Income Statement'!C50/'Income Statement'!C49 | D76: ='Income Statement'!D50/'Income Statement'!D49 | E76: ='Income Statement'!E50/'Income Statement'!E49 | F76: ='Income Statement'!F50/'Income Statement'!F49 | G76: ='Income Statement'!G50/'Income Statement'!G49 | H76: ='Income Statement'!H50/'Income Statement'!H49 | I76: ='Income Statement'!I50/'Income Statement'!I49 | J76: ='Income Statement'!J50/'Income Statement'!J49 | ... AI76: ='Income Statement'!AI50/'Income Statement'!AI49
B77: EV/EBITDA | C77: =('Income Statement'!C51+SUM('Balance Sheet'!C19,'Balance Sheet'!C20,'Balance Sheet'!C13,'Balance Sheet'!C14)-'Balance Sheet'!C49)/'Income Statement'!C23 | D77: =('Income Statement'!D51+SUM('Balance Sheet'!D19,'Balance Sheet'!D20,'Balance Sheet'!D13,'Balance Sheet'!D14)-'Balance Sheet'!D49)/'Income Statement'!D23 | E77: =('Income Statement'!E51+SUM('Balance Sheet'!E19,'Balance Sheet'!E20,'Balance Sheet'!E13,'Balance Sheet'!E14)-'Balance Sheet'!E49)/'Income Statement'!E23 | F77: =('Income Statement'!F51+SUM('Balance Sheet'!F19,'Balance Sheet'!F20,'Balance Sheet'!F13,'Balance Sheet'!F14)-'Balance Sheet'!F49)/'Income Statement'!F23 | G77: =('Income Statement'!G51+SUM('Balance Sheet'!G19,'Balance Sheet'!G20,'Balance Sheet'!G13,'Balance Sheet'!G14)-'Balance Sheet'!G49)/'Income Statement'!G23 | H77: =('Income Statement'!H51+SUM('Balance Sheet'!H19,'Balance Sheet'!H20,'Balance Sheet'!H13,'Balance Sheet'!H14)-'Balance Sheet'!H49)/'Income Statement'!H23 | I77: =('Income Statement'!I51+SUM('Balance Sheet'!I19,'Balance Sheet'!I20,'Balance Sheet'!I13,'Balance Sheet'!I14)-'Balance Sheet'!I49)/'Income Statement'!I23 | J77: =('Income Statement'!J51+SUM('Balance Sheet'!J19,'Balance Sheet'!J20,'Balance Sheet'!J13,'Balance Sheet'!J14)-'Balance Sheet'!J49)/'Income Statement'!J23 | ... AI77: =('Income Statement'!AI51+SUM('Balance Sheet'!AI19,'Balance Sheet'!AI20,'Balance Sheet'!AI13,'Balance Sheet'!AI14)-'Balance Sheet'!AI49)/'Income Statement'!AI23

Sheet Balance Sheet
B1: Anup Engineering Limited
B2: Fiscal year ending 31st Mar, 2026 | C2: H1 | D2: H2 | E2: FY | F2: H1 | G2: H2 | H2: FY | I2: H1 | J2: H2 | K2: FY | L2: H1 | M2: H2 | N2: FY | O2: H1 | P2: H2 | Q2: FY | R2: H1 | S2: H2 | T2: FY | U2: H1 | V2: H2 | W2: FY | X2: H1 | Y2: H2 | Z2: FY | AA2: H1 | AB2: H2 | AC2: FY | AD2: H1 | AE2: H2 | AF2: FY | AG2: H1 | AH2: H2 | AI2: FY
B3: All amounts in ₹ crores except per share data | C3: 2021 | D3: 2021 | E3: 2021 | F3: 2022 | G3: 2022 | H3: 2022 | I3: 2023 | J3: 2023 | K3: 2023 | L3: 2024 | M3: 2024 | N3: 2024 | O3: 2025 | P3: 2025 | Q3: 2025 | R3: 2026 | S3: 2026 | T3: 2026 | U3: 2027 E | V3: 2027 E | W3: 2027 E | X3: 2028 E | Y3: 2028 E | Z3: 2028 E | AA3: 2029 E | AB3: 2029 E | AC3: 2029 E | AD3: 2030 E | AE3: 2030 E | AF3: 2030 E | AG3: 2031 E | AH3: 2031 E | AI3: 2031 E
B5: BALANCE SHEET
B7: EQUITY AND LIABILITIES
B9: Equity Share Capital | C9: 10.2082 | D9: =E9 | E9: 9.8312 | F9: 9.8812 | G9: =H9 | H9: 9.8812 | I9: 9.8812 | J9: =K9 | K9: 9.8962 | L9: 9.9112 | M9: =N9 | N9: 9.9505 | O9: 20.0025 | P9: =Q9 | Q9: 20.0265 | R9: 20.0265 | S9: =T9 | T9: 20.0315 | U9: =T9 | V9: =U9 | W9: =V9 | X9: =W9 | Y9: =X9 | Z9: =Y9 | AA9: =Z9 | AB9: =AA9 | ... AI9: =AH9
B10: Other Equity | C10: 322.8136 | D10: =E10 | E10: 327.3179 | F10: 344.8998 | G10: =H10 | H10: 383.5297 | I10: 393.916 | J10: =K10 | K10: 427.7846 | L10: 454.2219 | M10: =N10 | N10: 518.4959 | O10: 528.4494 | P10: =Q10 | Q10: 591.9316 | R10: 616.2312 | S10: =T10 | T10: 670.975 | U10: =T10+'Income Statement'!U43-'Income Statement'!U56 | V10: =U10+'Income Statement'!V43-'Income Statement'!V56 | W10: =V10 | X10: =W10+'Income Statement'!X43-'Income Statement'!X56 | Y10: =X10+'Income Statement'!Y43-'Income Statement'!Y56 | Z10: =Y10 | AA10: =Z10+'Income Statement'!AA43-'Income Statement'!AA56 | AB10: =AA10+'Income Statement'!AB43-'Income Statement'!AB56 | AC10: =AB10 | AD10: =AC10+'Income Statement'!AD43-'Income Statement'!AD56 | AE10: =AD10+'Income Statement'!AE43-'Income Statement'!AE56 | AF10: =AE10 | AG10: =AF10+'Income Statement'!AG43-'Income Statement'!AG56 | AH10: =AG10+'Income Statement'!AH43-'Income Statement'!AH56 | AI10: =AH10
B11: Total Equity | C11: =SUM(C9:C10) | D11: =SUM(D9:D10) | E11: =SUM(E9:E10) | F11: =SUM(F9:F10) | G11: =SUM(G9:G10) | H11: =SUM(H9:H10) | I11: =SUM(I9:I10) | J11: =SUM(J9:J10) | ... AI11: =SUM(AI9:AI10)
B13: Borrowings | D13: =E13 | E13: 0 | F13: 0 | G13: =H13 | H13: 0 | I13: 0 | J13: =K13 | K13: 30.0254 | L13: 33.5767 | M13: =N13 | N13: 13.79 | O13: 12.2239 | P13: =Q13 | Q13: 8.239 | R13: 5.5299 | S13: =T13 | T13: 33.9215 | U13: =T13 | V13: =U13 | W13: =V13 | X13: =W13 | Y13: =X13 | Z13: =Y13 | AA13: =Z13 | AB13: =AA13 | ... AI13: =AH13
B14: Lease Liabilities | D14: =E14 | E14: 0 | F14: 0 | G14: =H14 | H14: 0 | I14: 0 | J14: =K14 | K14: 0 | L14: 0 | M14: =N14 | N14: 0.8413 | O14: 0.7468 | P14: =Q14 | Q14: 2.6527 | R14: 2.4898 | S14: =T14 | T14: 1.8778 | U14: =T14 | V14: =U14+3 | W14: =V14 | X14: =W14 | Y14: =X14 | Z14: =Y14 | AA14: =Z14 | AB14: =AA14 | AC14: =AB14 | AD14: =AC14 | ... AI14: =AH14
B15: Long-Term Provisions | D15: =E15 | E15: 0.0853 | F15: 0.0853 | G15: =H15 | H15: 0.3343 | I15: 0.3343 | J15: =K15 | K15: 0 | L15: 0 | M15: =N15 | N15: 2.3987 | O15: 10.7958 | P15: =Q15 | Q15: 5.7768 | R15: 6.7926 | S15: =T15 | T15: 5.9837 | U15: =T15 | V15: =U15 | W15: =V15 | X15: =W15 | Y15: =X15 | Z15: =Y15 | AA15: =Z15 | AB15: =AA15 | ... AI15: =AH15
B16: Deferred Tax Liabilities (Net) | C16: 14.779 | D16: =E16 | E16: 12.4736 | F16: 11.8548 | G16: =H16 | H16: 11.6506 | I16: 11.4732 | J16: =K16 | K16: 12.0978 | L16: 11.9616 | M16: =N16 | N16: 12.4492 | O16: 4.4934 | P16: =Q16 | Q16: 10.9749 | R16: 9.8801 | S16: =T16 | T16: 9.6979 | U16: =T16 | V16: =U16 | W16: =V16 | X16: =W16 | Y16: =X16 | Z16: =Y16 | AA16: =Z16 | AB16: =AA16 | ... AI16: =AH16
B17: Total Non-Current Liabilities | C17: =SUM(C13:C16) | D17: =SUM(D13:D16) | E17: =SUM(E13:E16) | F17: =SUM(F13:F16) | G17: =SUM(G13:G16) | H17: =SUM(H13:H16) | I17: =SUM(I13:I16) | J17: =SUM(J13:J16) | ... AI17: =SUM(AI13:AI16)
B19: Borrowings | D19: =E19 | E19: 0 | F19: 0 | G19: =H19 | H19: 0 | I19: 0 | J19: =K19 | K19: 4.3151 | L19: 11.2523 | M19: =N19 | N19: 5.4836 | O19: 5.6648 | P19: =Q19 | Q19: 21.2021 | R19: 149.3251 | S19: =T19 | T19: 73.88 | U19: =T19 | V19: 70 | W19: =V19 | X19: 65 | Y19: 60 | Z19: =Y19 | AA19: 55 | AB19: 50 | AC19: =AB19 | AD19: 45 | AE19: 40 | AF19: =AE19 | AG19: 35 | AH19: =AI19 | AI19: 30
B20: Lease Liabilities | D20: =E20 | E20: 0 | F20: 0 | G20: =H20 | H20: 0 | I20: 0 | J20: =K20 | K20: 0 | L20: 0 | M20: =N20 | N20: 0.1648 | O20: 0.182 | P20: =Q20 | Q20: 0.3237 | R20: 0.3322 | S20: =T20 | T20: 0.2082 | U20: =T20 | V20: =U20 | W20: =V20 | X20: =W20 | Y20: =X20 | Z20: =Y20 | AA20: =Z20 | AB20: =AA20 | ... AI20: =AH20
B21: Total O/S Dues Of Micro & Small Enterprises | D21: =E21 | E21: 0 | F21: 0 | G21: =H21 | H21: 0.3085 | I21: 0.0212 | J21: =K21 | K21: 0.6245 | L21: 3.0258 | M21: =N21 | N21: 13.2798 | O21: 15.4792 | P21: =Q21 | Q21: 29.6007 | R21: 31.8155 | S21: =T21 | T21: 29.9151 | W21: =V21 | Z21: =Y21 | AC21: =AB21 | AF21: =AE21 | AI21: =AH21
B22: Total O/S Dues Of Creditors Other Than Micro & Small Enterprises | C22: 28.3611 | D22: =E22 | E22: 26.9466 | F22: 30.8222 | G22: =H22 | H22: 42.9866 | I22: 40.7457 | J22: =K22 | K22: 65.2005 | L22: 38.0974 | M22: =N22 | N22: 49.6379 | O22: 66.4714 | P22: =Q22 | Q22: 58.8133 | R22: 48.9036 | S22: =T22 | T22: 55.0838 | W22: =V22 | Z22: =Y22 | AC22: =AB22 | AF22: =AE22 | AI22: =AH22
B23: Total Trade Payables | C23: =SUM(C21:C22) | D23: =SUM(D21:D22) | E23: =SUM(E21:E22) | F23: =SUM(F21:F22) | G23: =SUM(G21:G22) | H23: =SUM(H21:H22) | I23: =SUM(I21:I22) | J23: =SUM(J21:J22) | ... T23: =SUM(T21:T22) | U23: ='Balance Sheet'!U71/365*('Income Statement'!U14+'Income Statement'!S14) | V23: ='Balance Sheet'!V71/365*('Income Statement'!V14+'Income Statement'!U14) | W23: =V23 | X23: ='Balance Sheet'!X71/365*('Income Statement'!X14+'Income Statement'!V14) | Y23: ='Balance Sheet'!Y71/365*('Income Statement'!Y14+'Income Statement'!X14) | Z23: =Y23 | AA23: ='Balance Sheet'!AA71/365*('Income Statement'!AA14+'Income Statement'!Y14) | AB23: ='Balance Sheet'!AB71/365*('Income Statement'!AB14+'Income Statement'!AA14) | AC23: =AB23 | AD23: ='Balance Sheet'!AD71/365*('Income Statement'!AD14+'Income Statement'!AB14) | AE23: ='Balance Sheet'!AE71/365*('Income Statement'!AE14+'Income Statement'!AD14) | AF23: =AE23 | AG23: ='Balance Sheet'!AG71/365*('Income Statement'!AG14+'Income Statement'!AE14) | AH23: ='Balance Sheet'!AH71/365*('Income Statement'!AH14+'Income Statement'!AG14) | AI23: =AH23
B24: Other Financial Liabilities | C24: 8.0253 | D24: =E24 | E24: 2.494 | F24: 2.7014 | G24: =H24 | H24: 2.6483 | I24: 5.5005 | J24: =K24 | K24: 3.8477 | L24: 3.3442 | M24: =N24 | N24: 8.6134 | O24: 8.0072 | P24: =Q24 | Q24: 11.3576 | R24: 14.9178 | S24: =T24 | T24: 23.0812 | U24: =U72*('Income Statement'!U8+'Income Statement'!S8) | V24: =V72*('Income Statement'!V8+'Income Statement'!U8) | W24: =V24 | X24: =X72*('Income Statement'!X8+'Income Statement'!V8) | Y24: =Y72*('Income Statement'!Y8+'Income Statement'!X8) | Z24: =Y24 | AA24: =AA72*('Income Statement'!AA8+'Income Statement'!Y8) | AB24: =AB72*('Income Statement'!AB8+'Income Statement'!AA8) | AC24: =AB24 | AD24: =AD72*('Income Statement'!AD8+'Income Statement'!AB8) | AE24: =AE72*('Income Statement'!AE8+'Income Statement'!AD8) | AF24: =AE24 | AG24: =AG72*('Income Statement'!AG8+'Income Statement'!AE8) | AH24: =AH72*('Income Statement'!AH8+'Income Statement'!AG8) | AI24: =AH24
B25: Short-Term Provisions | C25: 1.126 | D25: =E25 | E25: 0.6224 | F25: 0.7514 | G25: =H25 | H25: 0.6365 | I25: 0.9358 | J25: =K25 | K25: 0.7389 | L25: 0.8229 | M25: =N25 | N25: 1.4338 | O25: 3.249 | P25: =Q25 | Q25: 2.5333 | R25: 3.1648 | S25: =T25 | T25: 3.8807 | U25: =U74*('Income Statement'!U8+'Income Statement'!S8) | V25: =V74*('Income Statement'!V8+'Income Statement'!U8) | W25: =V25 | X25: =X74*('Income Statement'!X8+'Income Statement'!V8) | Y25: =Y74*('Income Statement'!Y8+'Income Statement'!X8) | Z25: =Y25 | AA25: =AA74*('Income Statement'!AA8+'Income Statement'!Y8) | AB25: =AB74*('Income Statement'!AB8+'Income Statement'!AA8) | AC25: =AB25 | AD25: =AD74*('Income Statement'!AD8+'Income Statement'!AB8) | AE25: =AE74*('Income Statement'!AE8+'Income Statement'!AD8) | AF25: =AE25 | AG25: =AG74*('Income Statement'!AG8+'Income Statement'!AE8) | AH25: =AH74*('Income Statement'!AH8+'Income Statement'!AG8) | AI25: =AH25
B26: Other Current Liabilities | C26: 77.0848 | D26: =E26 | E26: 50.9509 | F26: 56.3176 | G26: =H26 | H26: 62.9655 | I26: 64.8595 | J26: =K26 | K26: 72.974 | L26: 101.3735 | M26: =N26 | N26: 154.5197 | O26: 177.7682 | P26: =Q26 | Q26: 144.0976 | R26: 62.1181 | S26: =T26 | T26: 24.8001 | U26: ='Balance Sheet'!U73*('Income Statement'!U8+'Income Statement'!S8) | V26: ='Balance Sheet'!V73*('Income Statement'!V$8+'Income Statement'!U$8) | W26: =V26 | X26: ='Balance Sheet'!X73*('Income Statement'!X8+'Income Statement'!V8) | Y26: ='Balance Sheet'!Y73*('Income Statement'!Y$8+'Income Statement'!X$8) | Z26: =Y26 | AA26: ='Balance Sheet'!AA73*('Income Statement'!AA8+'Income Statement'!Y8) | AB26: ='Balance Sheet'!AB73*('Income Statement'!AB$8+'Income Statement'!AA$8) | AC26: =AB26 | AD26: ='Balance Sheet'!AD73*('Income Statement'!AD8+'Income Statement'!AB8) | AE26: ='Balance Sheet'!AE73*('Income Statement'!AE$8+'Income Statement'!AD$8) | AF26: =AE26 | AG26: ='Balance Sheet'!AG73*('Income Statement'!AG8+'Income Statement'!AE8) | AH26: ='Balance Sheet'!AH73*('Income Statement'!AH$8+'Income Statement'!AG$8) | AI26: =AH26
B27: Current Tax Liabilities (Net) | D27: =E27 | E27: 0 | F27: 0 | G27: =H27 | H27: 10.3724 | I27: 10.3307 | J27: =K27 | K27: 15.4099 | L27: 20.5059 | M27: =N27 | N27: 17.3722 | O27: 18.4707 | P27: =Q27 | Q27: 18.6254 | R27: 25.352 | S27: =T27 | T27: 17.3227 | U27: =T27 | V27: =U27 | W27: =V27 | X27: =W27 | Y27: =X27 | Z27: =Y27 | AA27: =Z27 | AB27: =AA27 | ... AI27: =AH27
B28: Total Current Liabilities | C28: =SUM(C19:C20,C23:C27) | D28: =SUM(D19:D20,D23:D27) | E28: =SUM(E19:E20,E23:E27) | F28: =SUM(F19:F20,F23:F27) | G28: =SUM(G19:G20,G23:G27) | H28: =SUM(H19:H20,H23:H27) | I28: =SUM(I19:I20,I23:I27) | J28: =SUM(J19:J20,J23:J27) | ... AI28: =SUM(AI19:AI20,AI23:AI27)
B29: TOTAL EQUITY AND LIABILITIES | C29: =C11+C17+C28 | D29: =D11+D17+D28 | E29: =E11+E17+E28 | F29: =F11+F17+F28 | G29: =G11+G17+G28 | H29: =H11+H17+H28 | I29: =I11+I17+I28 | J29: =J11+J17+J28 | ... AI29: =AI11+AI17+AI28
B30: Check | C30: 462.398 | E30: 430.7219 | F30: 457.3137 | H30: 525.3136 | I30: 537.9981 | K30: 642.9146 | L30: 688.0934 | N30: 808.4308 | O30: 872.0043 | Q30: 926.1552 | R30: 996.8792 | T30: 970.6592
B31: Difference | C31: =C29-C30 | E31: =E29-E30 | F31: =F29-F30 | H31: =H29-H30 | I31: =I29-I30 | K31: =K29-K30 | L31: =L29-L30 | N31: =N29-N30 | O31: =O29-O30 | Q31: =Q29-Q30 | R31: =R29-R30 | T31: =T29-T30
B33: ASSETS
B35: Property, Plant And Equipment | C35: 181.3986 | D35: =E35 | E35: 188.0553 | F35: 185.1124 | G35: =H35 | H35: 182.9107 | I35: 193.3338 | J35: =K35 | K35: 200.6862 | L35: 294.2455 | M35: =N35 | N35: 299.5435 | O35: 322.9711 | P35: =Q35 | Q35: 288.0958 | R35: 314.2222 | S35: =T35 | T35: 328.3049 | U35: ='Balance Sheet'!U65 | V35: ='Balance Sheet'!V65 | W35: =V35 | X35: ='Balance Sheet'!X65 | Y35: ='Balance Sheet'!Y65 | Z35: =Y35 | AA35: ='Balance Sheet'!AA65 | AB35: ='Balance Sheet'!AB65 | AC35: =AB35 | AD35: ='Balance Sheet'!AD65 | AE35: ='Balance Sheet'!AE65 | AF35: =AE35 | AG35: ='Balance Sheet'!AG65 | AH35: ='Balance Sheet'!AH65 | AI35: =AH35
B36: Capital Work In Progress | C36: 7.61 | D36: =E36 | E36: 1.5337 | F36: 3.0925 | G36: =H36 | H36: 30.662 | I36: 59.2635 | J36: =K36 | K36: 87.0256 | L36: 7.9168 | M36: =N36 | N36: 15.5042 | O36: 14.5616 | P36: =Q36 | Q36: 9.9153 | R36: 14.598 | S36: =T36 | T36: 1.5728 | U36: 5 | V36: =U36 | W36: =V36 | X36: =W36 | Y36: =X36 | Z36: =Y36 | AA36: =Z36 | AB36: =AA36 | AC36: =AB36 | ... AI36: =AH36
B37: Goodwill On Consolidation | C37: 0 | D37: =E37 | E37: 0 | F37: 0 | G37: =H37 | H37: 0 | I37: 0 | J37: =K37 | K37: 0 | L37: 0 | M37: =N37 | N37: 0 | O37: 13.0164 | P37: =Q37 | Q37: 12.6164 | R37: 12.6164 | S37: =T37 | T37: 12.6164 | U37: =T37 | V37: =U37 | W37: =V37 | X37: =W37 | Y37: =X37 | Z37: =Y37 | AA37: =Z37 | AB37: =AA37 | ... AI37: =AH37
B38: Intangible Assets | C38: 25.3759 | D38: =E38 | E38: 23.72 | F38: 21.9603 | G38: =H38 | H38: 20.2005 | I38: 18.5722 | J38: =K38 | K38: 16.7009 | L38: 15.2288 | M38: =N38 | N38: 13.6719 | O38: 12.2365 | P38: =Q38 | Q38: 10.4086 | R38: 8.6507 | S38: =T38 | T38: 7.0597 | U38: =T38 | V38: =U38 | W38: =V38 | X38: =W38 | Y38: =X38 | Z38: =Y38 | AA38: =Z38 | AB38: =AA38 | ... AI38: =AH38
B39: Intangible Assets Under Development | C39: 0 | D39: =E39 | E39: 0 | F39: 0 | G39: =H39 | H39: 0 | I39: 0 | J39: =K39 | K39: 0 | L39: 0 | M39: =N39 | N39: 0.054 | O39: 0 | P39: =Q39 | Q39: 0 | R39: 0.1251 | S39: =T39 | T39: 0 | U39: =T39 | V39: =U39 | W39: =V39 | X39: =W39 | Y39: =X39 | Z39: =Y39 | AA39: =Z39 | AB39: =AA39 | ... AI39: =AH39
B40: Right Of Use Assets | C40: 0 | D40: =E40 | E40: 0 | F40: 0 | G40: =H40 | H40: 0 | I40: 0 | J40: =K40 | K40: 0 | L40: 0 | M40: =N40 | N40: 0 | O40: 0 | P40: =Q40 | Q40: 51.6565 | R40: 51.3151 | S40: =T40 | T40: 50.4817 | U40: =T40 | V40: =U40+(V14-U14) | W40: =V40 | X40: =W40 | Y40: =X40 | Z40: =Y40 | AA40: =Z40 | AB40: =AA40 | AC40: =AB40 | AD40: =AC40 | ... AI40: =AH40
B41: Other Financial Assets | C41: 0.7028 | D41: =E41 | E41: 0.733 | F41: 0.7572 | G41: =H41 | H41: 2.1833 | I41: 0.9294 | J41: =K41 | K41: 2.6321 | L41: 1.3199 | M41: =N41 | N41: 11.0554 | O41: 2.3295 | P41: =Q41 | Q41: 3.8095 | R41: 0.7194 | S41: =T41 | T41: 4.8304 | U41: =T41 | V41: =U41 | W41: =V41 | X41: =W41 | Y41: =X41 | Z41: =Y41 | AA41: =Z41 | AB41: =AA41 | ... AI41: =AH41
B42: Other Non-Current Assets | C42: 0.5876 | D42: =E42 | E42: 0.474 | F42: 0.4061 | G42: =H42 | H42: 9.8352 | I42: 4.623 | J42: =K42 | K42: 1.686 | L42: 1.1577 | M42: =N42 | N42: 3.827 | O42: 2.2817 | P42: =Q42 | Q42: 4.353 | R42: 0.6808 | S42: =T42 | T42: 1.3223 | U42: =T42 | V42: =U42 | W42: =V42 | X42: =W42 | Y42: =X42 | Z42: =Y42 | AA42: =Z42 | AB42: =AA42 | ... AI42: =AH42
B43: Total Non-Current Assets | C43: =SUM(C35:C42) | D43: =SUM(D35:D42) | E43: =SUM(E35:E42) | F43: =SUM(F35:F42) | G43: =SUM(G35:G42) | H43: =SUM(H35:H42) | I43: =SUM(I35:I42) | J43: =SUM(J35:J42) | ... AI43: =SUM(AI35:AI42)
B45: Inventories | C45: 85.1764 | D45: =E45 | E45: 66.7802 | F45: 64.4496 | G45: =H45 | H45: 90.1969 | I45: 115.8315 | J45: =K45 | K45: 126.9184 | L45: 118.9629 | M45: =N45 | N45: 165.2845 | O45: 179.6863 | P45: =Q45 | Q45: 147.2944 | R45: 148.3081 | S45: =T45 | T45: 100.7499 | U45: =('Income Statement'!U14+'Income Statement'!S14)/'Balance Sheet'!U76 | V45: =('Income Statement'!V14+'Income Statement'!U14)/'Balance Sheet'!V76 | W45: =V45 | X45: =('Income Statement'!X14+'Income Statement'!V14)/'Balance Sheet'!X76 | Y45: =('Income Statement'!Y14+'Income Statement'!X14)/'Balance Sheet'!Y76 | Z45: =Y45 | AA45: =('Income Statement'!AA14+'Income Statement'!Y14)/'Balance Sheet'!AA76 | AB45: =('Income Statement'!AB14+'Income Statement'!AA14)/'Balance Sheet'!AB76 | AC45: =AB45 | AD45: =('Income Statement'!AD14+'Income Statement'!AB14)/'Balance Sheet'!AD76 | AE45: =('Income Statement'!AE14+'Income Statement'!AD14)/'Balance Sheet'!AE76 | AF45: =AE45 | AG45: =('Income Statement'!AG14+'Income Statement'!AE14)/'Balance Sheet'!AG76 | AH45: =('Income Statement'!AH14+'Income Statement'!AG14)/'Balance Sheet'!AH76 | AI45: =AH45
B46: Financial Assets
B47: Investments | L47: 89.0044 | M47: =N47 | N47: 103.8624 | O47: 23.0281 | P47: =Q47 | Q47: 10.6319 | S47: =T47
B48: Trade Receivables | C48: 75.4486 | D48: =E48 | E48: 110.1157 | F48: 112.2841 | G48: =H48 | H48: 124.7955 | I48: 77.367 | J48: =K48 | K48: 148.5622 | L48: 127.2452 | M48: =N48 | N48: 127.2406 | O48: 228.9854 | P48: =Q48 | Q48: 283.6497 | R48: 350.4321 | S48: =T48 | T48: 415.9389 | U48: =('Income Statement'!U8+'Income Statement'!S8)/'Balance Sheet'!U78 | V48: =('Income Statement'!V8+'Income Statement'!U8)/'Balance Sheet'!V78 | W48: =V48 | X48: =('Income Statement'!X8+'Income Statement'!V8)/'Balance Sheet'!X78 | Y48: =('Income Statement'!Y8+'Income Statement'!X8)/'Balance Sheet'!Y78 | Z48: =Y48 | AA48: =('Income Statement'!AA8+'Income Statement'!Y8)/'Balance Sheet'!AA78 | AB48: =('Income Statement'!AB8+'Income Statement'!AA8)/'Balance Sheet'!AB78 | AC48: =AB48 | AD48: =('Income Statement'!AD8+'Income Statement'!AB8)/'Balance Sheet'!AD78 | AE48: =('Income Statement'!AE8+'Income Statement'!AD8)/'Balance Sheet'!AE78 | AF48: =AE48 | AG48: =('Income Statement'!AG8+'Income Statement'!AE8)/'Balance Sheet'!AG78 | AH48: =('Income Statement'!AH8+'Income Statement'!AG8)/'Balance Sheet'!AH78 | AI48: =AH48
B49: Cash And Cash Equivalents | C49: 46.4871 | D49: =E49 | E49: 3.8695 | F49: 15.6929 | G49: =H49 | H49: 9.4951 | I49: 16.1199 | J49: =K49 | K49: 31.0878 | L49: 13.4547 | M49: =N49 | N49: 17.7475 | O49: 3.4555 | P49: =Q49 | Q49: 2.5105 | R49: 0.2351 | S49: =T49 | T49: 4.0509 | U49: ='Cash Flows'!U77 | V49: ='Cash Flows'!V77 | W49: =V49 | X49: ='Cash Flows'!X77 | Y49: ='Cash Flows'!Y77 | Z49: =Y49 | AA49: ='Cash Flows'!AA77 | AB49: ='Cash Flows'!AB77 | AC49: =AB49 | AD49: ='Cash Flows'!AD77 | AE49: ='Cash Flows'!AE77 | AF49: =AE49 | AG49: ='Cash Flows'!AG77 | AH49: ='Cash Flows'!AH77 | AI49: =AH49
B50: Bank Balance Other Than (Iii) Above | C50: 32.2782 | D50: =E50 | E50: 19.737 | F50: 42.8345 | G50: =H50 | H50: 41.8022 | I50: 18.394 | J50: =K50 | K50: 1.5082 | L50: 2.7802 | M50: =N50 | N50: 3.5273 | O50: 5.0193 | P50: =Q50 | Q50: 13.1705 | R50: 14.3871 | S50: =T50 | T50: 8.5545 | U50: =T50 | V50: =U50 | W50: =V50 | X50: =W50 | Y50: =X50 | Z50: =Y50 | AA50: =Z50 | AB50: =AA50 | ... AI50: =AH50
B51: Other Financial Assets | C51: 0.4456 | D51: =E51 | E51: 0.322 | F51: 0.8492 | G51: =H51 | H51: 0.506 | I51: 0.2628 | J51: =K51 | K51: 0.1817 | L51: 0.7966 | M51: =N51 | N51: 1.6875 | O51: 0.4941 | P51: =Q51 | Q51: 0.3433 | R51: 0.723 | S51: =T51 | T51: 0.2481 | U51: =U80*('Income Statement'!U8+'Income Statement'!S8) | V51: =V80*('Income Statement'!V$8+'Income Statement'!U$8) | W51: =V51 | X51: =X80*('Income Statement'!X8+'Income Statement'!V8) | Y51: =Y80*('Income Statement'!Y$8+'Income Statement'!X$8) | Z51: =Y51 | AA51: =AA80*('Income Statement'!AA8+'Income Statement'!Y8) | AB51: =AB80*('Income Statement'!AB$8+'Income Statement'!AA$8) | AC51: =AB51 | AD51: =AD80*('Income Statement'!AD8+'Income Statement'!AB8) | AE51: =AE80*('Income Statement'!AE$8+'Income Statement'!AD$8) | AF51: =AE51 | AG51: =AG80*('Income Statement'!AG8+'Income Statement'!AE8) | AH51: =AH80*('Income Statement'!AH$8+'Income Statement'!AG$8) | AI51: =AH51
B52: Current Tax Assets (Net) | C52: 1.3722 | D52: =E52 | E52: 5.2088 | F52: 2.3422 | G52: =H52 | H52: 0 | I52: 0 | J52: =K52 | K52: 0 | L52: 0 | M52: =N52 | N52: 0 | O52: 0 | P52: =Q52 | Q52: 0 | R52: 0 | S52: =T52 | T52: 0 | U52: =T52 | V52: =U52 | W52: =V52 | X52: =W52 | Y52: =X52 | Z52: =Y52 | AA52: =Z52 | AB52: =AA52 | ... AI52: =AH52
B53: Other Current Assets | C53: 5.515 | D53: =E53 | E53: 10.1727 | F53: 7.5327 | G53: =H53 | H53: 12.7262 | I53: 33.301 | J53: =K53 | K53: 25.9255 | L53: 15.9807 | M53: =N53 | N53: 45.425 | O53: 63.9388 | P53: =Q53 | Q53: 87.6998 | R53: 79.8661 | S53: =T53 | T53: 34.9287 | U53: =U81*('Income Statement'!U8+'Income Statement'!S8) | V53: =V81*('Income Statement'!V$8+'Income Statement'!U$8) | W53: =V53 | X53: =X81*('Income Statement'!X8+'Income Statement'!V8) | Y53: =Y81*('Income Statement'!Y$8+'Income Statement'!X$8) | Z53: =Y53 | AA53: =AA81*('Income Statement'!AA8+'Income Statement'!Y8) | AB53: =AB81*('Income Statement'!AB$8+'Income Statement'!AA$8) | AC53: =AB53 | AD53: =AD81*('Income Statement'!AD8+'Income Statement'!AB8) | AE53: =AE81*('Income Statement'!AE$8+'Income Statement'!AD$8) | AF53: =AE53 | AG53: =AG81*('Income Statement'!AG8+'Income Statement'!AE8) | AH53: =AH81*('Income Statement'!AH$8+'Income Statement'!AG$8) | AI53: =AH53
B54: Total Current Assets | C54: =SUM(C45:C53) | D54: =SUM(D45:D53) | E54: =SUM(E45:E53) | F54: =SUM(F45:F53) | G54: =SUM(G45:G53) | H54: =SUM(H45:H53) | I54: =SUM(I45:I53) | J54: =SUM(J45:J53) | ... AI54: =SUM(AI45:AI53)
B55: TOTAL ASSETS | C55: =C43+C54 | D55: =D43+D54 | E55: =E43+E54 | F55: =F43+F54 | G55: =G43+G54 | H55: =H43+H54 | I55: =I43+I54 | J55: =J43+J54 | ... AI55: =AI43+AI54
B56: Difference | C56: 462.398 | E56: 430.7219 | F56: 457.3137 | H56: 525.3136 | I56: 537.9981 | K56: 642.9146 | L56: 688.0934 | N56: 808.4308 | O56: 872.0043 | Q56: 926.1552 | R56: 996.8792 | T56: 970.6592
B57: Check | C57: =C55-C56 | E57: =E55-E56 | F57: =F55-F56 | H57: =H55-H56 | I57: =I55-I56 | K57: =K55-K56 | L57: =L55-L56 | N57: =N55-N56 | O57: =O55-O56 | Q57: =Q55-Q56 | R57: =R55-R56 | T57: =T55-T56
B58: Master Check | C58: =C29-C55 | D58: =D29-D55 | E58: =E29-E55 | F58: =F29-F55 | G58: =G29-G55 | H58: =H29-H55 | I58: =I29-I55 | J58: =J29-J55 | ... AI58: =AI29-AI55
B61: PPE Schedule
B62: Opening PPE | D62: =C65 | E62: =D65 | F62: =E65 | G62: =F65 | H62: =E65 | I62: =H65 | J62: =I65 | K62: =H65 | L62: =K65 | M62: =L65 | N62: =K65 | O62: =N65 | P62: =O65 | Q62: =N65 | R62: =Q65 | S62: =R65 | T62: =Q65 | U62: =T65 | V62: =U65 | W62: =T65 | X62: =W65 | Y62: =X65 | Z62: =W65 | AA62: =Z65 | AB62: =AA65 | AC62: =Z65 | AD62: =AC65 | AE62: =AD65 | AF62: =AC65 | AG62: =AF65 | AH62: =AG65 | AI62: =AF65
B63: Depreciation | C63: ='Income Statement'!C26 | D63: ='Income Statement'!D26 | E63: ='Income Statement'!E26 | F63: ='Income Statement'!F26 | G63: ='Income Statement'!G26 | H63: ='Income Statement'!H26 | I63: ='Income Statement'!I26 | J63: ='Income Statement'!J26 | ... T63: ='Income Statement'!T26 | U63: =(U62*U67)/2 | V63: =(V62*V67)/2 | W63: =U63+V63 | X63: =(X62*X67)/2 | Y63: =(Y62*Y67)/2 | Z63: =X63+Y63 | AA63: =(AA62*AA67)/2 | AB63: =(AB62*AB67)/2 | AC63: =AA63+AB63 | AD63: =(AD62*AD67)/2 | AE63: =(AE62*AE67)/2 | AF63: =AD63+AE63 | AG63: =(AG62*AG67)/2 | AH63: =(AH62*AH67)/2 | AI63: =AG63+AH63
B64: Capex | D64: =D65+D63-D62 | E64: =E65+E63-E62 | F64: =F65+F63-F62 | G64: =G65+G63-G62 | H64: =H65+H63-H62 | I64: =I65+I63-I62 | J64: =J65+J63-J62 | K64: =K65+K63-K62 | ... S64: =S65+S63-S62 | T64: 68.05 | U64: =W64/2 | V64: =W64/2 | W64: 35 | X64: =Z64/2 | Y64: =Z64/2 | Z64: 30 | AA64: =AC64/2 | AB64: =AC64/2 | AC64: 30 | AD64: =AF64/2 | AE64: =AF64/2 | AF64: 30 | AG64: =AI64/2 | AH64: =AI64/2 | AI64: 30
B65: Closing PPE | C65: ='Balance Sheet'!C35 | D65: ='Balance Sheet'!D35 | E65: ='Balance Sheet'!E35 | F65: ='Balance Sheet'!F35 | G65: ='Balance Sheet'!G35 | H65: ='Balance Sheet'!H35 | I65: ='Balance Sheet'!I35 | J65: ='Balance Sheet'!J35 | ... T65: ='Balance Sheet'!T35 | U65: =U62-U63+U64 | V65: =V62-V63+V64 | W65: =W62-W63+W64 | X65: =X62-X63+X64 | Y65: =Y62-Y63+Y64 | Z65: =Z62-Z63+Z64 | AA65: =AA62-AA63+AA64 | AB65: =AB62-AB63+AB64 | ... AI65: =AI62-AI63+AI64
B67: Dep Rate | D67: =(D63+C63)/D62 | E67: =E63/E62 | F67: =(F63+D63)/F62 | G67: =(G63+F63)/G62 | H67: =H63/H62 | I67: =(I63+G63)/I62 | J67: =(J63+I63)/J62 | K67: =K63/K62 | L67: =(L63+J63)/L62 | M67: =(M63+L63)/M62 | N67: =N63/N62 | O67: =(O63+M63)/O62 | P67: =(P63+O63)/P62 | Q67: =Q63/Q62 | R67: =(R63+P63)/R62 | S67: =(S63+R63)/S62 | T67: =T63/T62 | U67: =S67 | V67: =U67 | W67: =W63/W62 | X67: =V67 | Y67: =X67 | Z67: =Z63/Z62 | AA67: =Y67 | AB67: =AA67 | AC67: =AC63/AC62 | AD67: =AB67 | AE67: =AD67 | AF67: =AF63/AF62 | AG67: =AE67 | AH67: =AG67 | AI67: =AI63/AI62
B69: Ratio Analysis
B70: Payable Turnover Ratio | C70: =('Income Statement'!C14+'Income Statement'!A14)/'Balance Sheet'!C23 | D70: =('Income Statement'!D14+'Income Statement'!C14)/'Balance Sheet'!D23 | E70: ='Income Statement'!E14/'Balance Sheet'!E23 | F70: =('Income Statement'!F14+'Income Statement'!D14)/'Balance Sheet'!F23 | G70: =('Income Statement'!G14+'Income Statement'!F14)/'Balance Sheet'!G23 | H70: ='Income Statement'!H14/'Balance Sheet'!H23 | I70: =('Income Statement'!I14+'Income Statement'!G14)/'Balance Sheet'!I23 | J70: =('Income Statement'!J14+'Income Statement'!I14)/'Balance Sheet'!J23 | K70: ='Income Statement'!K14/'Balance Sheet'!K23 | L70: =('Income Statement'!L14+'Income Statement'!J14)/'Balance Sheet'!L23 | M70: =('Income Statement'!M14+'Income Statement'!L14)/'Balance Sheet'!M23 | N70: ='Income Statement'!N14/'Balance Sheet'!N23 | O70: =('Income Statement'!O14+'Income Statement'!M14)/'Balance Sheet'!O23 | P70: =('Income Statement'!P14+'Income Statement'!O14)/'Balance Sheet'!P23 | Q70: ='Income Statement'!Q14/'Balance Sheet'!Q23 | R70: =('Income Statement'!R14+'Income Statement'!P14)/'Balance Sheet'!R23 | S70: =('Income Statement'!S14+'Income Statement'!R14)/'Balance Sheet'!S23 | T70: ='Income Statement'!T14/'Balance Sheet'!T23 | U70: 4.7 | V70: =U70 | W70: ='Income Statement'!W14/'Balance Sheet'!W23 | X70: 4.5 | Y70: =X70 | Z70: ='Income Statement'!Z14/'Balance Sheet'!Z23 | AA70: 4.3 | AB70: =AA70 | AC70: ='Income Statement'!AC14/'Balance Sheet'!AC23 | AD70: 4.2 | AE70: =AD70 | AF70: ='Income Statement'!AF14/'Balance Sheet'!AF23 | AG70: 4 | AH70: =AG70 | AI70: ='Income Statement'!AI14/'Balance Sheet'!AI23
B71: Payable Days | C71: =365/'Balance Sheet'!C70 | D71: =365/'Balance Sheet'!D70 | E71: =365/'Balance Sheet'!E70 | F71: =365/'Balance Sheet'!F70 | G71: =365/'Balance Sheet'!G70 | H71: =365/'Balance Sheet'!H70 | I71: =365/'Balance Sheet'!I70 | J71: =365/'Balance Sheet'!J70 | K71: =365/'Balance Sheet'!K70 | L71: =366/'Balance Sheet'!L70 | M71: =366/'Balance Sheet'!M70 | N71: =366/'Balance Sheet'!N70 | O71: =365/'Balance Sheet'!O70 | P71: =365/'Balance Sheet'!P70 | Q71: =365/'Balance Sheet'!Q70 | R71: =365/'Balance Sheet'!R70 | S71: =365/'Balance Sheet'!S70 | T71: =365/'Balance Sheet'!T70 | U71: =365/'Balance Sheet'!U70 | V71: =365/'Balance Sheet'!V70 | ... AI71: =365/'Balance Sheet'!AI70
B72: Other Financial Liabilities as % of Revenue | C72: =C24/('Income Statement'!C8+'Income Statement'!A8) | D72: =D24/('Income Statement'!D8+'Income Statement'!C8) | E72: =E24/'Income Statement'!E8 | F72: =F24/('Income Statement'!F8+'Income Statement'!D8) | G72: =G24/('Income Statement'!G8+'Income Statement'!F8) | H72: =H24/'Income Statement'!H8 | I72: =I24/('Income Statement'!I8+'Income Statement'!G8) | J72: =J24/('Income Statement'!J8+'Income Statement'!I8) | K72: =K24/'Income Statement'!K8 | L72: =L24/('Income Statement'!L8+'Income Statement'!J8) | M72: =M24/('Income Statement'!M8+'Income Statement'!L8) | N72: =N24/'Income Statement'!N8 | O72: =O24/('Income Statement'!O8+'Income Statement'!M8) | P72: =P24/('Income Statement'!P8+'Income Statement'!O8) | Q72: =Q24/'Income Statement'!Q8 | R72: =R24/('Income Statement'!R8+'Income Statement'!P8) | S72: =S24/('Income Statement'!S8+'Income Statement'!R8) | T72: =T24/'Income Statement'!T8 | U72: =S72 | V72: =U72 | W72: =W24/'Income Statement'!W8 | X72: =V72 | Y72: =X72 | Z72: =Z24/'Income Statement'!Z8 | AA72: =Y72 | AB72: =AA72 | AC72: =AC24/'Income Statement'!AC8 | AD72: =AB72 | AE72: =AD72 | AF72: =AF24/'Income Statement'!AF8 | AG72: =AE72 | AH72: =AG72 | AI72: =AI24/'Income Statement'!AI8
B73: Other Current Liabilities as % of Revenue | C73: ='Balance Sheet'!C26/('Income Statement'!C8+'Income Statement'!A8) | D73: ='Balance Sheet'!D26/('Income Statement'!D8+'Income Statement'!C8) | E73: ='Balance Sheet'!E26/'Income Statement'!E8 | F73: ='Balance Sheet'!F26/('Income Statement'!F8+'Income Statement'!D8) | G73: ='Balance Sheet'!G26/('Income Statement'!G8+'Income Statement'!F8) | H73: ='Balance Sheet'!H26/'Income Statement'!H8 | I73: ='Balance Sheet'!I26/('Income Statement'!I8+'Income Statement'!G8) | J73: ='Balance Sheet'!J26/('Income Statement'!J8+'Income Statement'!I8) | K73: ='Balance Sheet'!K26/'Income Statement'!K8 | L73: ='Balance Sheet'!L26/('Income Statement'!L8+'Income Statement'!J8) | M73: ='Balance Sheet'!M26/('Income Statement'!M8+'Income Statement'!L8) | N73: ='Balance Sheet'!N26/'Income Statement'!N8 | O73: ='Balance Sheet'!O26/('Income Statement'!O8+'Income Statement'!M8) | P73: ='Balance Sheet'!P26/('Income Statement'!P8+'Income Statement'!O8) | Q73: ='Balance Sheet'!Q26/'Income Statement'!Q8 | R73: ='Balance Sheet'!R26/('Income Statement'!R$8+'Income Statement'!P$8) | S73: ='Balance Sheet'!S26/('Income Statement'!S$8+'Income Statement'!R$8) | T73: ='Balance Sheet'!T26/'Income Statement'!T8 | U73: =T73 | V73: =U73 | W73: ='Balance Sheet'!W26/'Income Statement'!W8 | X73: =V73 | Y73: =X73 | Z73: ='Balance Sheet'!Z26/'Income Statement'!Z8 | AA73: =Y73 | AB73: =AA73 | AC73: ='Balance Sheet'!AC26/'Income Statement'!AC8 | AD73: =AB73 | AE73: =AD73 | AF73: ='Balance Sheet'!AF26/'Income Statement'!AF8 | AG73: =AE73 | AH73: =AG73 | AI73: ='Balance Sheet'!AI26/'Income Statement'!AI8
B74: Short Term Provisions as % of Revenue | C74: ='Balance Sheet'!C27/('Income Statement'!C$8+'Income Statement'!A$8) | D74: ='Balance Sheet'!D27/('Income Statement'!D$8+'Income Statement'!C$8) | E74: =E25/'Income Statement'!E8 | F74: ='Balance Sheet'!F27/('Income Statement'!F$8+'Income Statement'!D$8) | G74: ='Balance Sheet'!G27/('Income Statement'!G$8+'Income Statement'!F$8) | H74: =H25/'Income Statement'!H8 | I74: ='Balance Sheet'!I27/('Income Statement'!I$8+'Income Statement'!G$8) | J74: ='Balance Sheet'!J27/('Income Statement'!J$8+'Income Statement'!I$8) | K74: =K25/'Income Statement'!K8 | L74: ='Balance Sheet'!L27/('Income Statement'!L$8+'Income Statement'!J$8) | M74: ='Balance Sheet'!M27/('Income Statement'!M$8+'Income Statement'!L$8) | N74: =N25/'Income Statement'!N8 | O74: ='Balance Sheet'!O27/('Income Statement'!O$8+'Income Statement'!M$8) | P74: ='Balance Sheet'!P27/('Income Statement'!P$8+'Income Statement'!O$8) | Q74: =Q25/'Income Statement'!Q8 | R74: ='Balance Sheet'!R27/('Income Statement'!R$8+'Income Statement'!P$8) | S74: ='Balance Sheet'!S27/('Income Statement'!S$8+'Income Statement'!R$8) | T74: =T25/'Income Statement'!T8 | U74: =S74 | V74: =U74 | W74: =W25/'Income Statement'!W8 | X74: =V74 | Y74: =X74 | Z74: =Z25/'Income Statement'!Z8 | AA74: =Y74 | AB74: =AA74 | AC74: =AC25/'Income Statement'!AC8 | AD74: =AB74 | AE74: =AD74 | AF74: =AF25/'Income Statement'!AF8 | AG74: =AE74 | AH74: =AG74 | AI74: =AI25/'Income Statement'!AI8
B76: Inventory Turnover Ratio | C76: =('Income Statement'!C14+'Income Statement'!A14)/'Balance Sheet'!C45 | D76: =('Income Statement'!D14+'Income Statement'!C14)/'Balance Sheet'!D45 | E76: ='Income Statement'!E14/'Balance Sheet'!E45 | F76: =('Income Statement'!F14+'Income Statement'!D14)/'Balance Sheet'!F45 | G76: =('Income Statement'!G14+'Income Statement'!F14)/'Balance Sheet'!G45 | H76: ='Income Statement'!H14/'Balance Sheet'!H45 | I76: =('Income Statement'!I14+'Income Statement'!G14)/'Balance Sheet'!I45 | J76: =('Income Statement'!J14+'Income Statement'!I14)/'Balance Sheet'!J45 | K76: ='Income Statement'!K14/'Balance Sheet'!K45 | L76: =('Income Statement'!L14+'Income Statement'!J14)/'Balance Sheet'!L45 | M76: =('Income Statement'!M14+'Income Statement'!L14)/'Balance Sheet'!M45 | N76: ='Income Statement'!N14/'Balance Sheet'!N45 | O76: =('Income Statement'!O14+'Income Statement'!M14)/'Balance Sheet'!O45 | P76: =('Income Statement'!P14+'Income Statement'!O14)/'Balance Sheet'!P45 | Q76: ='Income Statement'!Q14/'Balance Sheet'!Q45 | R76: =('Income Statement'!R14+'Income Statement'!P14)/'Balance Sheet'!R45 | S76: =('Income Statement'!S14+'Income Statement'!R14)/'Balance Sheet'!S45 | T76: ='Income Statement'!T14/'Balance Sheet'!T45 | U76: 3.9 | V76: =U76 | W76: ='Income Statement'!W14/'Balance Sheet'!W45 | X76: 4 | Y76: =X76 | Z76: ='Income Statement'!Z14/'Balance Sheet'!Z45 | AA76: 4.1 | AB76: =AA76 | AC76: ='Income Statement'!AC14/'Balance Sheet'!AC45 | AD76: 4.3 | AE76: =AD76 | AF76: ='Income Statement'!AF14/'Balance Sheet'!AF45 | AG76: 4.5 | AH76: =AG76 | AI76: ='Income Statement'!AI14/'Balance Sheet'!AI45
B77: Inventory Days | C77: =365/C76 | D77: =365/D76 | E77: =365/E76 | F77: =365/F76 | G77: =365/G76 | H77: =365/H76 | I77: =365/I76 | J77: =365/J76 | ... AI77: =365/AI76
B78: Recievable Turnover Ratio | C78: =('Income Statement'!C$8+'Income Statement'!A$8)/'Balance Sheet'!C48 | D78: =('Income Statement'!D$8+'Income Statement'!C$8)/'Balance Sheet'!D48 | E78: ='Income Statement'!E8/'Balance Sheet'!E48 | F78: =('Income Statement'!F$8+'Income Statement'!D$8)/'Balance Sheet'!F48 | G78: =('Income Statement'!G$8+'Income Statement'!F$8)/'Balance Sheet'!G48 | H78: ='Income Statement'!H8/'Balance Sheet'!H48 | I78: =('Income Statement'!I$8+'Income Statement'!G$8)/'Balance Sheet'!I48 | J78: =('Income Statement'!J$8+'Income Statement'!I$8)/'Balance Sheet'!J48 | K78: ='Income Statement'!K8/'Balance Sheet'!K48 | L78: =('Income Statement'!L$8+'Income Statement'!J$8)/'Balance Sheet'!L48 | M78: =('Income Statement'!M$8+'Income Statement'!L$8)/'Balance Sheet'!M48 | N78: ='Income Statement'!N8/'Balance Sheet'!N48 | O78: =('Income Statement'!O$8+'Income Statement'!M$8)/'Balance Sheet'!O48 | P78: =('Income Statement'!P$8+'Income Statement'!O$8)/'Balance Sheet'!P48 | Q78: ='Income Statement'!Q8/'Balance Sheet'!Q48 | R78: =('Income Statement'!R$8+'Income Statement'!P$8)/'Balance Sheet'!R48 | S78: =('Income Statement'!S$8+'Income Statement'!R$8)/'Balance Sheet'!S48 | T78: ='Income Statement'!T8/'Balance Sheet'!T48 | U78: 2.2 | V78: =U78 | W78: ='Income Statement'!W8/'Balance Sheet'!W48 | X78: 2.7 | Y78: =X78 | Z78: ='Income Statement'!Z8/'Balance Sheet'!Z48 | AA78: 3.1 | AB78: =AA78 | AC78: ='Income Statement'!AC8/'Balance Sheet'!AC48 | AD78: 3.6 | AE78: =AD78 | AF78: ='Income Statement'!AF8/'Balance Sheet'!AF48 | AG78: 4.2 | AH78: =AG78 | AI78: ='Income Statement'!AI8/'Balance Sheet'!AI48
B79: Recievable Days | C79: =365/'Balance Sheet'!C78 | D79: =365/'Balance Sheet'!D78 | E79: =365/'Balance Sheet'!E78 | F79: =365/'Balance Sheet'!F78 | G79: =365/'Balance Sheet'!G78 | H79: =365/'Balance Sheet'!H78 | I79: =365/'Balance Sheet'!I78 | J79: =365/'Balance Sheet'!J78 | K79: =365/'Balance Sheet'!K78 | L79: =366/'Balance Sheet'!L78 | M79: =366/'Balance Sheet'!M78 | N79: =366/'Balance Sheet'!N78 | O79: =365/'Balance Sheet'!O78 | P79: =365/'Balance Sheet'!P78 | Q79: =365/'Balance Sheet'!Q78 | R79: =365/'Balance Sheet'!R78 | S79: =365/'Balance Sheet'!S78 | T79: =365/'Balance Sheet'!T78 | U79: =365/'Balance Sheet'!U78 | V79: =365/'Balance Sheet'!V78 | ... AI79: =365/'Balance Sheet'!AI78
B80: Other Financial Assets as % of Revenue | C80: =C51/('Income Statement'!C$8+'Income Statement'!A$8) | D80: =D51/('Income Statement'!D$8+'Income Statement'!C$8) | E80: =E51/'Income Statement'!E8 | F80: =F51/('Income Statement'!F$8+'Income Statement'!D$8) | G80: =G51/('Income Statement'!G$8+'Income Statement'!F$8) | H80: =H51/'Income Statement'!H8 | I80: =I51/('Income Statement'!I$8+'Income Statement'!G$8) | J80: =J51/('Income Statement'!J$8+'Income Statement'!I$8) | K80: =K51/'Income Statement'!K8 | L80: =L51/('Income Statement'!L$8+'Income Statement'!J$8) | M80: =M51/('Income Statement'!M$8+'Income Statement'!L$8) | N80: =N51/'Income Statement'!N8 | O80: =O51/('Income Statement'!O$8+'Income Statement'!M$8) | P80: =P51/('Income Statement'!P$8+'Income Statement'!O$8) | Q80: =Q51/'Income Statement'!Q8 | R80: =R51/('Income Statement'!R$8+'Income Statement'!P$8) | S80: =S51/('Income Statement'!S$8+'Income Statement'!R$8) | T80: =T51/'Income Statement'!T8 | U80: =S80 | V80: =U80 | W80: =W51/'Income Statement'!W8 | X80: =V80 | Y80: =X80 | Z80: =Z51/'Income Statement'!Z8 | AA80: =Y80 | AB80: =AA80 | AC80: =AC51/'Income Statement'!AC8 | AD80: =AB80 | AE80: =AD80 | AF80: =AF51/'Income Statement'!AF8 | AG80: =AE80 | AH80: =AG80 | AI80: =AI51/'Income Statement'!AI8
B81: Other Current Assets as % of Revenue | C81: =C53/('Income Statement'!C$8+'Income Statement'!A$8) | D81: =D53/('Income Statement'!D$8+'Income Statement'!C$8) | E81: =E53/'Income Statement'!E8 | F81: =F53/('Income Statement'!F$8+'Income Statement'!D$8) | G81: =G53/('Income Statement'!G$8+'Income Statement'!F$8) | H81: =H53/'Income Statement'!H8 | I81: =I53/('Income Statement'!I$8+'Income Statement'!G$8) | J81: =J53/('Income Statement'!J$8+'Income Statement'!I$8) | K81: =K53/'Income Statement'!K8 | L81: =L53/('Income Statement'!L$8+'Income Statement'!J$8) | M81: =M53/('Income Statement'!M$8+'Income Statement'!L$8) | N81: =N53/'Income Statement'!N8 | O81: =O53/('Income Statement'!O$8+'Income Statement'!M$8) | P81: =P53/('Income Statement'!P$8+'Income Statement'!O$8) | Q81: =Q53/'Income Statement'!Q8 | R81: =R53/('Income Statement'!R$8+'Income Statement'!P$8) | S81: =S53/('Income Statement'!S$8+'Income Statement'!R$8) | T81: =T53/'Income Statement'!T8 | U81: =T81 | V81: =U81 | W81: =W53/'Income Statement'!W8 | X81: =V81 | Y81: =X81 | Z81: =Z53/'Income Statement'!Z8 | AA81: =Y81 | AB81: =AA81 | AC81: =AC53/'Income Statement'!AC8 | AD81: =AB81 | AE81: =AD81 | AF81: =AF53/'Income Statement'!AF8 | AG81: =AE81 | AH81: =AG81 | AI81: =AI53/'Income Statement'!AI8
B83: Current Ratio | C83: ='Balance Sheet'!C54/'Balance Sheet'!C28 | D83: ='Balance Sheet'!D54/'Balance Sheet'!D28 | E83: ='Balance Sheet'!E54/'Balance Sheet'!E28 | F83: ='Balance Sheet'!F54/'Balance Sheet'!F28 | G83: ='Balance Sheet'!G54/'Balance Sheet'!G28 | H83: ='Balance Sheet'!H54/'Balance Sheet'!H28 | I83: ='Balance Sheet'!I54/'Balance Sheet'!I28 | J83: ='Balance Sheet'!J54/'Balance Sheet'!J28 | ... AI83: ='Balance Sheet'!AI54/'Balance Sheet'!AI28
B84: Quick Ratio | C84: =('Balance Sheet'!C54-'Balance Sheet'!C45)/'Balance Sheet'!C28 | D84: =('Balance Sheet'!D54-'Balance Sheet'!D45)/'Balance Sheet'!D28 | E84: =('Balance Sheet'!E54-'Balance Sheet'!E45)/'Balance Sheet'!E28 | F84: =('Balance Sheet'!F54-'Balance Sheet'!F45)/'Balance Sheet'!F28 | G84: =('Balance Sheet'!G54-'Balance Sheet'!G45)/'Balance Sheet'!G28 | H84: =('Balance Sheet'!H54-'Balance Sheet'!H45)/'Balance Sheet'!H28 | I84: =('Balance Sheet'!I54-'Balance Sheet'!I45)/'Balance Sheet'!I28 | J84: =('Balance Sheet'!J54-'Balance Sheet'!J45)/'Balance Sheet'!J28 | ... AI84: =('Balance Sheet'!AI54-'Balance Sheet'!AI45)/'Balance Sheet'!AI28
B85: Cash Ratio | C85: ='Balance Sheet'!C49/'Balance Sheet'!C28 | D85: ='Balance Sheet'!D49/'Balance Sheet'!D28 | E85: ='Balance Sheet'!E49/'Balance Sheet'!E28 | F85: ='Balance Sheet'!F49/'Balance Sheet'!F28 | G85: ='Balance Sheet'!G49/'Balance Sheet'!G28 | H85: ='Balance Sheet'!H49/'Balance Sheet'!H28 | I85: ='Balance Sheet'!I49/'Balance Sheet'!I28 | J85: ='Balance Sheet'!J49/'Balance Sheet'!J28 | ... AI85: ='Balance Sheet'!AI49/'Balance Sheet'!AI28
B87: Debt-Equity Ratio | C87: =SUM('Balance Sheet'!C13,'Balance Sheet'!C14,'Balance Sheet'!C19,'Balance Sheet'!C20)/'Balance Sheet'!C11 | D87: =SUM('Balance Sheet'!D13,'Balance Sheet'!D14,'Balance Sheet'!D19,'Balance Sheet'!D20)/'Balance Sheet'!D11 | E87: =SUM('Balance Sheet'!E13,'Balance Sheet'!E14,'Balance Sheet'!E19,'Balance Sheet'!E20)/'Balance Sheet'!E11 | F87: =SUM('Balance Sheet'!F13,'Balance Sheet'!F14,'Balance Sheet'!F19,'Balance Sheet'!F20)/'Balance Sheet'!F11 | G87: =SUM('Balance Sheet'!G13,'Balance Sheet'!G14,'Balance Sheet'!G19,'Balance Sheet'!G20)/'Balance Sheet'!G11 | H87: =SUM('Balance Sheet'!H13,'Balance Sheet'!H14,'Balance Sheet'!H19,'Balance Sheet'!H20)/'Balance Sheet'!H11 | I87: =SUM('Balance Sheet'!I13,'Balance Sheet'!I14,'Balance Sheet'!I19,'Balance Sheet'!I20)/'Balance Sheet'!I11 | J87: =SUM('Balance Sheet'!J13,'Balance Sheet'!J14,'Balance Sheet'!J19,'Balance Sheet'!J20)/'Balance Sheet'!J11 | ... AI87: =SUM('Balance Sheet'!AI13,'Balance Sheet'!AI14,'Balance Sheet'!AI19,'Balance Sheet'!AI20)/'Balance Sheet'!AI11
B88: Debt-Assets Ratio | C88: =SUM('Balance Sheet'!C13,'Balance Sheet'!C14,'Balance Sheet'!C19,'Balance Sheet'!C20)/'Balance Sheet'!C55 | D88: =SUM('Balance Sheet'!D13,'Balance Sheet'!D14,'Balance Sheet'!D19,'Balance Sheet'!D20)/'Balance Sheet'!D55 | E88: =SUM('Balance Sheet'!E13,'Balance Sheet'!E14,'Balance Sheet'!E19,'Balance Sheet'!E20)/'Balance Sheet'!E55 | F88: =SUM('Balance Sheet'!F13,'Balance Sheet'!F14,'Balance Sheet'!F19,'Balance Sheet'!F20)/'Balance Sheet'!F55 | G88: =SUM('Balance Sheet'!G13,'Balance Sheet'!G14,'Balance Sheet'!G19,'Balance Sheet'!G20)/'Balance Sheet'!G55 | H88: =SUM('Balance Sheet'!H13,'Balance Sheet'!H14,'Balance Sheet'!H19,'Balance Sheet'!H20)/'Balance Sheet'!H55 | I88: =SUM('Balance Sheet'!I13,'Balance Sheet'!I14,'Balance Sheet'!I19,'Balance Sheet'!I20)/'Balance Sheet'!I55 | J88: =SUM('Balance Sheet'!J13,'Balance Sheet'!J14,'Balance Sheet'!J19,'Balance Sheet'!J20)/'Balance Sheet'!J55 | ... AI88: =SUM('Balance Sheet'!AI13,'Balance Sheet'!AI14,'Balance Sheet'!AI19,'Balance Sheet'!AI20)/'Balance Sheet'!AI55
B89: Debt-Service Coverage Ratio | C89: ='Income Statement'!C23/('Income Statement'!C31+SUM('Balance Sheet'!C19+'Balance Sheet'!C13)) | D89: ='Income Statement'!D23/('Income Statement'!D31+SUM('Balance Sheet'!D19+'Balance Sheet'!D13)) | E89: ='Income Statement'!E23/('Income Statement'!E31+SUM('Balance Sheet'!E19+'Balance Sheet'!E13)) | F89: ='Income Statement'!F23/('Income Statement'!F31+SUM('Balance Sheet'!F19+'Balance Sheet'!F13)) | G89: ='Income Statement'!G23/('Income Statement'!G31+SUM('Balance Sheet'!G19+'Balance Sheet'!G13)) | H89: ='Income Statement'!H23/('Income Statement'!H31+SUM('Balance Sheet'!H19+'Balance Sheet'!H13)) | I89: ='Income Statement'!I23/('Income Statement'!I31+SUM('Balance Sheet'!I19+'Balance Sheet'!I13)) | J89: ='Income Statement'!J23/('Income Statement'!J31+SUM('Balance Sheet'!J19+'Balance Sheet'!J13)) | ... AI89: ='Income Statement'!AI23/('Income Statement'!AI31+SUM('Balance Sheet'!AI19+'Balance Sheet'!AI13))
B91: Cash Conversion Cycle | C91: ='Balance Sheet'!C79+C77-'Balance Sheet'!C71 | D91: ='Balance Sheet'!D79+D77-'Balance Sheet'!D71 | E91: ='Balance Sheet'!E79+E77-'Balance Sheet'!E71 | F91: ='Balance Sheet'!F79+F77-'Balance Sheet'!F71 | G91: ='Balance Sheet'!G79+G77-'Balance Sheet'!G71 | H91: ='Balance Sheet'!H79+H77-'Balance Sheet'!H71 | I91: ='Balance Sheet'!I79+I77-'Balance Sheet'!I71 | J91: ='Balance Sheet'!J79+J77-'Balance Sheet'!J71 | ... AI91: ='Balance Sheet'!AI79+AI77-'Balance Sheet'!AI71
B93: Working Capital | C93: ='Balance Sheet'!C54-'Balance Sheet'!C28 | D93: ='Balance Sheet'!D54-'Balance Sheet'!D28 | E93: ='Balance Sheet'!E54-'Balance Sheet'!E28 | F93: ='Balance Sheet'!F54-'Balance Sheet'!F28 | G93: ='Balance Sheet'!G54-'Balance Sheet'!G28 | H93: ='Balance Sheet'!H54-'Balance Sheet'!H28 | I93: ='Balance Sheet'!I54-'Balance Sheet'!I28 | J93: ='Balance Sheet'!J54-'Balance Sheet'!J28 | ... AI93: ='Balance Sheet'!AI54-'Balance Sheet'!AI28
B94: Working Capital Days | C94: =(C93/'Income Statement'!C8)*182.5 | D94: =(D93/'Income Statement'!D8)*182.5 | E94: =(E93/'Income Statement'!E8)*365 | F94: =(F93/'Income Statement'!F8)*182.5 | G94: =(G93/'Income Statement'!G8)*182.5 | H94: =(H93/'Income Statement'!H8)*365 | I94: =(I93/'Income Statement'!I8)*182.5 | J94: =(J93/'Income Statement'!J8)*182.5 | K94: =(K93/'Income Statement'!K8)*365 | L94: =(L93/'Income Statement'!L8)*183 | M94: =(M93/'Income Statement'!M8)*183 | N94: =(N93/'Income Statement'!N8)*366 | O94: =(O93/'Income Statement'!O8)*182.5 | P94: =(P93/'Income Statement'!P8)*182.5 | Q94: =(Q93/'Income Statement'!Q8)*365 | R94: =(R93/'Income Statement'!R8)*182.5 | S94: =(S93/'Income Statement'!S8)*182.5 | T94: =(T93/'Income Statement'!T8)*365 | U94: =(U93/'Income Statement'!U8)*182.5 | V94: =(V93/'Income Statement'!V8)*182.5 | W94: =(W93/'Income Statement'!W8)*365 | X94: =(X93/'Income Statement'!X8)*183 | Y94: =(Y93/'Income Statement'!Y8)*183 | Z94: =(Z93/'Income Statement'!Z8)*366 | AA94: =(AA93/'Income Statement'!AA8)*182.5 | AB94: =(AB93/'Income Statement'!AB8)*182.5 | AC94: =(AC93/'Income Statement'!AC8)*365 | AD94: =(AD93/'Income Statement'!AD8)*182.5 | AE94: =(AE93/'Income Statement'!AE8)*182.5 | AF94: =(AF93/'Income Statement'!AF8)*365 | AG94: =(AG93/'Income Statement'!AG8)*182.5 | AH94: =(AH93/'Income Statement'!AH8)*182.5 | AI94: =(AI93/'Income Statement'!AI8)*365
B95: Operating Working Capital | C95: ='Balance Sheet'!C45+'Balance Sheet'!C48-'Balance Sheet'!C23 | D95: ='Balance Sheet'!D45+'Balance Sheet'!D48-'Balance Sheet'!D23 | E95: ='Balance Sheet'!E45+'Balance Sheet'!E48-'Balance Sheet'!E23 | F95: ='Balance Sheet'!F45+'Balance Sheet'!F48-'Balance Sheet'!F23 | G95: ='Balance Sheet'!G45+'Balance Sheet'!G48-'Balance Sheet'!G23 | H95: ='Balance Sheet'!H45+'Balance Sheet'!H48-'Balance Sheet'!H23 | I95: ='Balance Sheet'!I45+'Balance Sheet'!I48-'Balance Sheet'!I23 | J95: ='Balance Sheet'!J45+'Balance Sheet'!J48-'Balance Sheet'!J23 | ... AI95: ='Balance Sheet'!AI45+'Balance Sheet'!AI48-'Balance Sheet'!AI23
B96: Difference | F96: =F95-E95 | G96: =G95-F95 | H96: =H95-E95 | I96: =I95-H95 | J96: =J95-I95 | K96: =K95-H95 | L96: =L95-K95 | M96: =M95-L95 | N96: =N95-K95 | O96: =O95-N95 | P96: =P95-O95 | Q96: =Q95-N95 | R96: =R95-Q95 | S96: =S95-R95 | T96: =T95-Q95 | U96: =U95-T95 | V96: =V95-U95 | W96: =W95-T95 | X96: =X95-W95 | Y96: =Y95-X95 | Z96: =Z95-W95 | AA96: =AA95-Z95 | AB96: =AB95-AA95 | AC96: =AC95-Z95 | AD96: =AD95-AC95 | AE96: =AE95-AD95 | AF96: =AF95-AC95 | AG96: =AG95-AF95 | AH96: =AH95-AG95 | AI96: =AI95-AF95

Sheet Cash Flows
B1: Anup Engineering Limited
B2: Fiscal year ending 31st Mar, 2026 | C2: H1 | D2: H2 | E2: FY | F2: H1 | G2: H2 | H2: FY | I2: H1 | J2: H2 | K2: FY | L2: H1 | M2: H2 | N2: FY | O2: H1 | P2: H2 | Q2: FY | R2: H1 | S2: H2 | T2: FY | U2: H1 | V2: H2 | W2: FY | X2: H1 | Y2: H2 | Z2: FY | AA2: H1 | AB2: H2 | AC2: FY | AD2: H1 | AE2: H2 | AF2: FY | AG2: H1 | AH2: H2 | AI2: FY
B3: All amounts in ₹ crores except per share data | C3: 2021 | D3: 2021 | E3: 2021 | F3: 2022 | G3: 2022 | H3: 2022 | I3: 2023 | J3: 2023 | K3: 2023 | L3: 2024 | M3: 2024 | N3: 2024 | O3: 2025 | P3: 2025 | Q3: 2025 | R3: 2026 | S3: 2026 | T3: 2026 | U3: 2027 E | V3: 2027 E | W3: 2027 E | X3: 2028 E | Y3: 2028 E | Z3: 2028 E | AA3: 2029 E | AB3: 2029 E | AC3: 2029 E | AD3: 2030 E | AE3: 2030 E | AF3: 2030 E | AG3: 2031 E | AH3: 2031 E | AI3: 2031 E
B5: CASH FLOW STATEMENT
B7: Cash Flow from Operating Activities
B8: Profit Before Tax | C8: 23.2984 | D8: =E8-C8 | E8: 61.465 | F8: 30.1529 | G8: =H8-F8 | H8: 61.1222 | I8: 24.0461 | J8: =K8-I8 | K8: 69.9982 | L8: 54.1866 | M8: =N8-L8 | N8: 116.1759 | O8: 67.0169 | P8: =Q8-O8 | Q8: 143.2002 | R8: 78.2991 | S8: =T8-R8 | T8: 139.3005 | U8: ='Income Statement'!U32 | V8: ='Income Statement'!V32 | W8: =U8+V8 | X8: ='Income Statement'!X32 | Y8: ='Income Statement'!Y32 | Z8: =X8+Y8 | AA8: ='Income Statement'!AA32 | AB8: ='Income Statement'!AB32 | AC8: =AA8+AB8 | AD8: ='Income Statement'!AD32 | AE8: ='Income Statement'!AE32 | AF8: =AD8+AE8 | AG8: ='Income Statement'!AG32 | AH8: ='Income Statement'!AH32 | AI8: =AG8+AH8
B9: Adjustments for: | D9: =E9-C9 | E9: 0 | F9: 0 | G9: =H9-F9 | H9: 0 | I9: 0 | J9: =K9-I9 | K9: 0 | L9: 0 | M9: =N9-L9 | N9: 0 | O9: 0 | P9: =Q9-O9 | Q9: 0 | R9: 0 | S9: =T9-R9 | T9: 0 | W9: =U9+V9 | Z9: =X9+Y9 | AC9: =AA9+AB9 | AF9: =AD9+AE9 | AI9: =AG9+AH9
B10: Depreciation and Amortization expenses | C10: 4.5149 | D10: =E10-C10 | E10: 10.5059 | F10: 5.7862 | G10: =H10-F10 | H10: 11.5922 | I10: 5.8629 | J10: =K10-I10 | K10: 12.5405 | L10: 7.0289 | M10: =N10-L10 | N10: 17.464 | O10: 11.3557 | P10: =Q10-O10 | Q10: 23.819 | R10: 13.2423 | S10: =T10-R10 | T10: 27.841 | U10: ='Balance Sheet'!U63 | V10: ='Balance Sheet'!V63 | W10: =U10+V10 | X10: ='Balance Sheet'!X63 | Y10: ='Balance Sheet'!Y63 | Z10: =X10+Y10 | AA10: ='Balance Sheet'!AA63 | AB10: ='Balance Sheet'!AB63 | AC10: =AA10+AB10 | AD10: ='Balance Sheet'!AD63 | AE10: ='Balance Sheet'!AE63 | AF10: =AD10+AE10 | AG10: ='Balance Sheet'!AG63 | AH10: ='Balance Sheet'!AH63 | AI10: =AG10+AH10
B11: Addition/(Deductions) to Right to use Assets | C11: 0 | D11: 0 | E11: 0 | F11: 0 | G11: 0 | H11: 0 | I11: 0 | J11: 0 | K11: 0 | L11: 0 | M11: 0 | N11: 0 | O11: 0 | P11: 0 | Q11: 0 | R11: 0 | S11: 0 | T11: 0 | U11: ='Balance Sheet'!T40-'Balance Sheet'!U40 | V11: ='Balance Sheet'!U40-'Balance Sheet'!V40 | W11: =U11+V11 | X11: ='Balance Sheet'!W40-'Balance Sheet'!X40 | Y11: ='Balance Sheet'!X40-'Balance Sheet'!Y40 | Z11: =X11+Y11 | AA11: ='Balance Sheet'!Z40-'Balance Sheet'!AA40 | AB11: ='Balance Sheet'!AA40-'Balance Sheet'!AB40 | AC11: =AA11+AB11 | AD11: ='Balance Sheet'!AC40-'Balance Sheet'!AD40 | AE11: ='Balance Sheet'!AD40-'Balance Sheet'!AE40 | AF11: =AD11+AE11 | AG11: ='Balance Sheet'!AF40-'Balance Sheet'!AG40 | AH11: ='Balance Sheet'!AG40-'Balance Sheet'!AH40 | AI11: =AG11+AH11
B12: Increase/(Decrease) in Long term provisions | C12: 0 | D12: 0 | E12: 0 | F12: 0 | G12: 0 | H12: 0 | I12: 0 | J12: 0 | K12: 0 | L12: 0 | M12: 0 | N12: 0 | O12: 0 | P12: 0 | Q12: 0 | R12: 0 | S12: 0 | T12: 0 | U12: ='Balance Sheet'!U15-'Balance Sheet'!T15 | V12: ='Balance Sheet'!V15-'Balance Sheet'!U15 | W12: =U12+V12 | X12: ='Balance Sheet'!X15-'Balance Sheet'!W15 | Y12: ='Balance Sheet'!Y15-'Balance Sheet'!X15 | Z12: =X12+Y12 | AA12: ='Balance Sheet'!AA15-'Balance Sheet'!Z15 | AB12: ='Balance Sheet'!AB15-'Balance Sheet'!AA15 | AC12: =AA12+AB12 | AD12: ='Balance Sheet'!AD15-'Balance Sheet'!AC15 | AE12: ='Balance Sheet'!AE15-'Balance Sheet'!AD15 | AF12: =AD12+AE12 | AG12: ='Balance Sheet'!AG15-'Balance Sheet'!AF15 | AH12: ='Balance Sheet'!AH15-'Balance Sheet'!AG15 | AI12: =AG12+AH12
B13: Deferred Tax (Income)/Expense | C13: 0 | D13: 0 | E13: 0 | F13: 0 | G13: 0 | H13: 0 | I13: 0 | J13: 0 | K13: 0 | L13: 0 | M13: 0 | N13: 0 | O13: 0 | P13: 0 | Q13: 0 | R13: 0 | S13: 0 | T13: 0 | U13: ='Balance Sheet'!U16-'Balance Sheet'!T16 | V13: ='Balance Sheet'!V16-'Balance Sheet'!U16 | W13: =U13+V13 | X13: ='Balance Sheet'!X16-'Balance Sheet'!W16 | Y13: ='Balance Sheet'!Y16-'Balance Sheet'!X16 | Z13: =X13+Y13 | AA13: ='Balance Sheet'!AA16-'Balance Sheet'!Z16 | AB13: ='Balance Sheet'!AB16-'Balance Sheet'!AA16 | AC13: =AA13+AB13 | AD13: ='Balance Sheet'!AD16-'Balance Sheet'!AC16 | AE13: ='Balance Sheet'!AE16-'Balance Sheet'!AD16 | AF13: =AD13+AE13 | AG13: ='Balance Sheet'!AG16-'Balance Sheet'!AF16 | AH13: ='Balance Sheet'!AH16-'Balance Sheet'!AG16 | AI13: =AG13+AH13
B14: Interest income from financial assets measured at amortised cost | C14: -0.8366 | D14: =E14-C14 | E14: -2.0066 | F14: -0.8986 | G14: =H14-F14 | H14: -3.5992 | I14: -0.6182 | J14: =K14-I14 | K14: -0.9531 | L14: -0.0896 | M14: =N14-L14 | N14: -1.8442 | O14: -0.4494 | P14: =Q14-O14 | Q14: -0.89 | R14: -0.5536 | S14: =T14-R14 | T14: -0.8627 | W14: =U14+V14 | Z14: =X14+Y14 | AC14: =AA14+AB14 | AF14: =AD14+AE14 | AI14: =AG14+AH14
B15: Gain on sale of current investments | C15: -0.7108 | D15: =E15-C15 | E15: -0.7108 | F15: 0 | G15: =H15-F15 | H15: 0 | I15: 0 | J15: =K15-I15 | K15: 0 | L15: 0 | M15: =N15-L15 | N15: -2.8948 | O15: -2.6097 | P15: =Q15-O15 | Q15: -1.8109 | R15: -0.0777 | S15: =T15-R15 | T15: -0.1208 | W15: =U15+V15 | Z15: =X15+Y15 | AC15: =AA15+AB15 | AF15: =AD15+AE15 | AI15: =AG15+AH15
B16: Change in fair valuation of current investments | C16: 0 | D16: =E16-C16 | E16: 0 | F16: 0 | G16: =H16-F16 | H16: 0 | I16: 0 | J16: =K16-I16 | K16: 0 | L16: -1.4636 | M16: =N16-L16 | N16: -1.6486 | O16: 0.1398 | P16: =Q16-O16 | Q16: -1.196 | R16: 0 | S16: =T16-R16 | T16: 0 | W16: =U16+V16 | Z16: =X16+Y16 | AC16: =AA16+AB16 | AF16: =AD16+AE16 | AI16: =AG16+AH16
B17: Finance Costs | C17: 0.2708 | D17: =E17-C17 | E17: 0.3444 | F17: 0.2223 | G17: =H17-F17 | H17: 1.0315 | I17: 0.5961 | J17: =K17-I17 | K17: 1.4083 | L17: 0.2067 | M17: =N17-L17 | N17: 2.1744 | O17: 1.9606 | P17: =Q17-O17 | Q17: 3.3389 | R17: 2.9776 | S17: =T17-R17 | T17: 8.6983 | U17: ='Income Statement'!U31 | V17: ='Income Statement'!V31 | W17: =U17+V17 | X17: ='Income Statement'!X31 | Y17: ='Income Statement'!Y31 | Z17: =X17+Y17 | AA17: ='Income Statement'!AA31 | AB17: ='Income Statement'!AB31 | AC17: =AA17+AB17 | AD17: ='Income Statement'!AD31 | AE17: ='Income Statement'!AE31 | AF17: =AD17+AE17 | AG17: ='Income Statement'!AG31 | AH17: ='Income Statement'!AH31 | AI17: =AG17+AH17
B18: Allowance/(Reversal) for doubtful debts | C18: 1.4253 | D18: =E18-C18 | E18: 1.6853 | F18: 1.1071 | G18: =H18-F18 | H18: 1.8949 | I18: -1.0368 | J18: =K18-I18 | K18: -0.2126 | L18: -0.1986 | M18: =N18-L18 | N18: 2.5438 | O18: -0.1268 | P18: =Q18-O18 | Q18: 0.0154 | R18: 0.659 | S18: =T18-R18 | T18: 0.9183 | W18: =U18+V18 | Z18: =X18+Y18 | AC18: =AA18+AB18 | AF18: =AD18+AE18 | AI18: =AG18+AH18
B19: Remeasurement (Gain)/Loss on lease | T19: -0.0085
B20: Property, Plant & Equipment written off | C20: 0 | D20: =E20-C20 | E20: 0.355 | F20: 0 | G20: =H20-F20 | H20: 0 | I20: 0.0287 | J20: =K20-I20 | K20: 0.0771 | L20: 0 | M20: =N20-L20 | N20: 0 | O20: 0 | P20: =Q20-O20 | Q20: 0 | R20: 0 | S20: =T20-R20 | T20: 0 | W20: =U20+V20 | Z20: =X20+Y20 | AC20: =AA20+AB20 | AF20: =AD20+AE20 | AI20: =AG20+AH20
B21: Bad Debts Written off | C21: 0.0339 | D21: =E21-C21 | E21: 0.0339 | F21: 0 | G21: =H21-F21 | H21: 0 | I21: 0 | J21: =K21-I21 | K21: 0 | L21: 0 | M21: =N21-L21 | N21: 0 | O21: 0 | P21: =Q21-O21 | Q21: 0.0214 | R21: 0 | S21: =T21-R21 | T21: 0 | W21: =U21+V21 | Z21: =X21+Y21 | AC21: =AA21+AB21 | AF21: =AD21+AE21 | AI21: =AG21+AH21
B22: Sundry Debit/(Credit) Balances appropriated (Net) | C22: 0 | D22: =E22-C22 | E22: -0.7912 | F22: 0.0029 | G22: =H22-F22 | H22: -0.0715 | I22: 0 | J22: =K22-I22 | K22: -0.0764 | L22: 0 | M22: =N22-L22 | N22: 0.2386 | O22: 0.016 | P22: =Q22-O22 | Q22: -0.0017 | R22: 0.0006 | S22: =T22-R22 | T22: 0.0311 | W22: =U22+V22 | Z22: =X22+Y22 | AC22: =AA22+AB22 | AF22: =AD22+AE22 | AI22: =AG22+AH22
B23: (Profit)/Loss on sale of Property, Plant & Equipment and Intangible | C23: 0.0557 | D23: =E23-C23 | E23: 0.0637 | F23: -0.0069 | G23: =H23-F23 | H23: -0.0187 | I23: 0.0235 | J23: =K23-I23 | K23: 0.0383 | L23: -0.0685 | M23: =N23-L23 | N23: -0.1228 | O23: -0.3665 | P23: =Q23-O23 | Q23: -0.3846 | R23: 0.0124 | S23: =T23-R23 | T23: 0.037 | W23: =U23+V23 | Z23: =X23+Y23 | AC23: =AA23+AB23 | AF23: =AD23+AE23 | AI23: =AG23+AH23
B24: Unrealised gain on foreign exchange fluctuation (net) | C24: 0 | D24: =E24-C24 | E24: 0 | F24: 0 | G24: =H24-F24 | H24: 0 | I24: 0 | J24: =K24-I24 | K24: -0.2922 | L24: 0 | M24: =N24-L24 | N24: -1.095 | O24: 0 | P24: =Q24-O24 | Q24: -0.0912 | R24: 0 | S24: =T24-R24 | T24: -6.4154 | W24: =U24+V24 | Z24: =X24+Y24 | AC24: =AA24+AB24 | AF24: =AD24+AE24 | AI24: =AG24+AH24
B25: Provision for Warranty | C25: 0 | D25: =E25-C25 | E25: 0 | F25: 0 | G25: =H25-F25 | H25: 0 | I25: 0 | J25: =K25-I25 | K25: 0 | L25: 0 | M25: =N25-L25 | N25: 2 | O25: 0 | P25: =Q25-O25 | Q25: 0.5 | R25: 1 | S25: =T25-R25 | T25: 0 | W25: =U25+V25 | Z25: =X25+Y25 | AC25: =AA25+AB25 | AF25: =AD25+AE25 | AI25: =AG25+AH25
B26: Tax on Exceptional Item | T26: -0.4886
B27: Share based payment expense | C27: 0.2233 | D27: =E27-C27 | E27: 0.4455 | F27: 0.1422 | G27: =H27-F27 | H27: 0.3892 | I27: 0.2263 | J27: =K27-I27 | K27: 0.4313 | L27: 0.6567 | M27: =N27-L27 | N27: 1.4646 | O27: 1.3978 | P27: =Q27-O27 | Q27: 2.8123 | R27: 1.7697 | S27: =T27-R27 | T27: 3.6731 | W27: =U27+V27 | Z27: =X27+Y27 | AC27: =AA27+AB27 | AF27: =AD27+AE27 | AI27: =AG27+AH27
B29: Operating Cash flow before Working Capital Changes | C29: =SUM(C8:C28) | D29: =SUM(D8:D28) | E29: =SUM(E8:E28) | F29: =SUM(F8:F28) | G29: =SUM(G8:G28) | H29: =SUM(H8:H28) | I29: =SUM(I8:I28) | J29: =SUM(J8:J28) | ... AI29: =SUM(AI8:AI28)
B30: Adjustments for changes in working capital :
B31: (Increase)/Decrease in inventories | C31: 21.0053 | D31: =E31-C31 | E31: 39.4015 | F31: 2.3306 | G31: =H31-F31 | H31: -23.4167 | I31: -25.6346 | J31: =K31-I31 | K31: -36.7215 | L31: 7.9555 | M31: =N31-L31 | N31: -38.3661 | O31: -9.0219 | P31: =Q31-O31 | Q31: 23.37 | R31: -1.0137 | S31: =T31-R31 | T31: 46.5445 | U31: ='Balance Sheet'!T45-'Balance Sheet'!U45 | V31: ='Balance Sheet'!U45-'Balance Sheet'!V45 | W31: =U31+V31 | X31: ='Balance Sheet'!W45-'Balance Sheet'!X45 | Y31: ='Balance Sheet'!X45-'Balance Sheet'!Y45 | Z31: =SUM(X31:Y31) | AA31: ='Balance Sheet'!Z45-'Balance Sheet'!AA45 | AB31: ='Balance Sheet'!AA45-'Balance Sheet'!AB45 | AC31: =SUM(AA31:AB31) | AD31: ='Balance Sheet'!AC45-'Balance Sheet'!AD45 | AE31: ='Balance Sheet'!AD45-'Balance Sheet'!AE45 | AF31: =SUM(AD31:AE31) | AG31: ='Balance Sheet'!AF45-'Balance Sheet'!AG45 | AH31: ='Balance Sheet'!AG45-'Balance Sheet'!AH45 | AI31: =SUM(AG31:AH31)
B32: (Increase)/Decrease in trade receivables | C32: -12.5228 | D32: =E32-C32 | E32: -47.3927 | F32: -3.2583 | G32: =H32-F32 | H32: -16.5402 | I32: 48.4625 | J32: =K32-I32 | K32: -23.318 | L32: 21.4571 | M32: =N32-L32 | N32: 19.7854 | O32: -84.0345 | P32: =Q32-O32 | Q32: -138.857 | R32: -67.442 | S32: =T32-R32 | T32: -126.7835 | U32: ='Balance Sheet'!T48-'Balance Sheet'!U48 | V32: ='Balance Sheet'!U48-'Balance Sheet'!V48 | W32: =U32+V32 | X32: ='Balance Sheet'!W48-'Balance Sheet'!X48 | Y32: ='Balance Sheet'!X48-'Balance Sheet'!Y48 | Z32: ='Balance Sheet'!W48-'Balance Sheet'!Z48 | AA32: ='Balance Sheet'!Z48-'Balance Sheet'!AA48 | AB32: ='Balance Sheet'!AA48-'Balance Sheet'!AB48 | AC32: ='Balance Sheet'!Z48-'Balance Sheet'!AC48 | AD32: ='Balance Sheet'!AC48-'Balance Sheet'!AD48 | AE32: ='Balance Sheet'!AD48-'Balance Sheet'!AE48 | AF32: ='Balance Sheet'!AC48-'Balance Sheet'!AF48 | AG32: ='Balance Sheet'!AF48-'Balance Sheet'!AG48 | AH32: ='Balance Sheet'!AG48-'Balance Sheet'!AH48 | AI32: ='Balance Sheet'!AF48-'Balance Sheet'!AI48
B33: (Increase)/Decrease in other financial assets | C33: 10.6973 | D33: =E33-C33 | E33: -0.023 | F33: 2.559 | G33: =H33-F33 | H33: -0.1408 | I33: -20.6075 | J33: =K33-I33 | K33: -0.2143 | L33: 1.3122 | M33: =N33-L33 | N33: 0.4982 | O33: -1.3542 | P33: =Q33-O33 | Q33: -0.1357 | R33: 3.0901 | S33: =T33-R33 | T33: -1.0209 | U33: ='Balance Sheet'!T51-'Balance Sheet'!U51 | V33: ='Balance Sheet'!U51-'Balance Sheet'!V51 | W33: =U33+V33 | X33: ='Balance Sheet'!W51-'Balance Sheet'!X51 | Y33: ='Balance Sheet'!X51-'Balance Sheet'!Y51 | Z33: ='Balance Sheet'!W51-'Balance Sheet'!Z51 | AA33: ='Balance Sheet'!Z51-'Balance Sheet'!AA51 | AB33: ='Balance Sheet'!AA51-'Balance Sheet'!AB51 | AC33: ='Balance Sheet'!Z51-'Balance Sheet'!AC51 | AD33: ='Balance Sheet'!AC51-'Balance Sheet'!AD51 | AE33: ='Balance Sheet'!AD51-'Balance Sheet'!AE51 | AF33: ='Balance Sheet'!AC51-'Balance Sheet'!AF51 | AG33: ='Balance Sheet'!AF51-'Balance Sheet'!AG51 | AH33: ='Balance Sheet'!AG51-'Balance Sheet'!AH51 | AI33: ='Balance Sheet'!AF51-'Balance Sheet'!AI51
B34: (Increase)/Decrease in other assets | C34: -0.003 | D34: =E34-C34 | E34: 6.1475 | F34: -0.041 | G34: =H34-F34 | H34: -2.6011 | I34: 0.0036 | J34: =K34-I34 | K34: -13.1796 | L34: 10.5316 | M34: =N34-L34 | N34: -19.837 | O34: -18.0463 | P34: =Q34-O34 | Q34: -41.2285 | R34: 7.8807 | S34: =T34-R34 | T34: 52.7883 | U34: ='Balance Sheet'!T53-'Balance Sheet'!U53 | V34: ='Balance Sheet'!U53-'Balance Sheet'!V53 | W34: =U34+V34 | X34: ='Balance Sheet'!W53-'Balance Sheet'!X53 | Y34: ='Balance Sheet'!X53-'Balance Sheet'!Y53 | Z34: ='Balance Sheet'!W53-'Balance Sheet'!Z53 | AA34: ='Balance Sheet'!Z53-'Balance Sheet'!AA53 | AB34: ='Balance Sheet'!AA53-'Balance Sheet'!AB53 | AC34: ='Balance Sheet'!Z53-'Balance Sheet'!AC53 | AD34: ='Balance Sheet'!AC53-'Balance Sheet'!AD53 | AE34: ='Balance Sheet'!AD53-'Balance Sheet'!AE53 | AF34: ='Balance Sheet'!AC53-'Balance Sheet'!AF53 | AG34: ='Balance Sheet'!AF53-'Balance Sheet'!AG53 | AH34: ='Balance Sheet'!AG53-'Balance Sheet'!AH53 | AI34: ='Balance Sheet'!AF53-'Balance Sheet'!AI53
B35: Increase/(Decrease) in trade payables | C35: 5.1684 | D35: =E35-C35 | E35: 4.5451 | F35: 3.8756 | G35: =H35-F35 | H35: 16.42 | I35: -2.5282 | J35: =K35-I35 | K35: 22.6063 | L35: -24.7018 | M35: =N35-L35 | N35: -2.8986 | O35: 13.8164 | P35: =Q35-O35 | Q35: 21.484 | R35: -7.6949 | S35: =T35-R35 | T35: -3.4548 | U35: ='Balance Sheet'!U23-'Balance Sheet'!T23 | V35: ='Balance Sheet'!V23-'Balance Sheet'!U23 | W35: =U35+V35 | X35: =-('Balance Sheet'!W23-'Balance Sheet'!X23) | Y35: =-('Balance Sheet'!X23-'Balance Sheet'!Y23) | Z35: =-('Balance Sheet'!W23-'Balance Sheet'!Z23) | AA35: =-('Balance Sheet'!Z23-'Balance Sheet'!AA23) | AB35: =-('Balance Sheet'!AA23-'Balance Sheet'!AB23) | AC35: =-('Balance Sheet'!Z23-'Balance Sheet'!AC23) | AD35: =-('Balance Sheet'!AC23-'Balance Sheet'!AD23) | AE35: =-('Balance Sheet'!AD23-'Balance Sheet'!AE23) | AF35: =-('Balance Sheet'!AC23-'Balance Sheet'!AF23) | AG35: =-('Balance Sheet'!AF23-'Balance Sheet'!AG23) | AH35: =-('Balance Sheet'!AG23-'Balance Sheet'!AH23) | AI35: =-('Balance Sheet'!AF23-'Balance Sheet'!AI23)
B36: Increase/(Decrease) in other financial liabilities | C36: -1.1206 | D36: =E36-C36 | E36: 0.0786 | F36: 0.2074 | G36: =H36-F36 | H36: 0.056 | I36: 2.7611 | J36: =K36-I36 | K36: 1.1055 | L36: -0.7377 | M36: =N36-L36 | N36: 4.2963 | O36: -1.1073 | P36: =Q36-O36 | Q36: 1.5413 | R36: 0.9584 | S36: =T36-R36 | T36: 8.5584 | U36: ='Balance Sheet'!U24-'Balance Sheet'!T24 | V36: ='Balance Sheet'!V24-'Balance Sheet'!U24 | W36: =U36+V36 | X36: =-('Balance Sheet'!W24-'Balance Sheet'!X24) | Y36: =-('Balance Sheet'!X24-'Balance Sheet'!Y24) | Z36: =-('Balance Sheet'!W24-'Balance Sheet'!Z24) | AA36: =-('Balance Sheet'!Z24-'Balance Sheet'!AA24) | AB36: =-('Balance Sheet'!AA24-'Balance Sheet'!AB24) | AC36: =-('Balance Sheet'!Z24-'Balance Sheet'!AC24) | AD36: =-('Balance Sheet'!AC24-'Balance Sheet'!AD24) | AE36: =-('Balance Sheet'!AD24-'Balance Sheet'!AE24) | AF36: =-('Balance Sheet'!AC24-'Balance Sheet'!AF24) | AG36: =-('Balance Sheet'!AF24-'Balance Sheet'!AG24) | AH36: =-('Balance Sheet'!AG24-'Balance Sheet'!AH24) | AI36: =-('Balance Sheet'!AF24-'Balance Sheet'!AI24)
B37: Increase/(Decrease) in other current liabilities | C37: 19.087 | D37: =E37-C37 | E37: -8.6732 | F37: 5.3667 | G37: =H37-F37 | H37: 12.0146 | I37: 1.894 | J37: =K37-I37 | K37: 10.0085 | L37: 28.3995 | M37: =N37-L37 | N37: 81.5457 | O37: 17.7573 | P37: =Q37-O37 | Q37: -16.1041 | R37: -81.9795 | S37: =T37-R37 | T37: -119.2975 | U37: ='Balance Sheet'!U26-'Balance Sheet'!T26 | V37: ='Balance Sheet'!V26-'Balance Sheet'!U26 | W37: =U37+V37 | X37: =-('Balance Sheet'!W26-'Balance Sheet'!X26) | Y37: =-('Balance Sheet'!X26-'Balance Sheet'!Y26) | Z37: =-('Balance Sheet'!W26-'Balance Sheet'!Z26) | AA37: =-('Balance Sheet'!Z26-'Balance Sheet'!AA26) | AB37: =-('Balance Sheet'!AA26-'Balance Sheet'!AB26) | AC37: =-('Balance Sheet'!Z26-'Balance Sheet'!AC26) | AD37: =-('Balance Sheet'!AC26-'Balance Sheet'!AD26) | AE37: =-('Balance Sheet'!AD26-'Balance Sheet'!AE26) | AF37: =-('Balance Sheet'!AC26-'Balance Sheet'!AF26) | AG37: =-('Balance Sheet'!AF26-'Balance Sheet'!AG26) | AH37: =-('Balance Sheet'!AG26-'Balance Sheet'!AH26) | AI37: =-('Balance Sheet'!AF26-'Balance Sheet'!AI26)
B38: Increase/(Decrease) in provisions | C38: 0.181 | D38: =E38-C38 | E38: -0.1984 | F38: 0.1158 | G38: =H38-F38 | H38: 0.2054 | I38: 0.2705 | J38: =K38-I38 | K38: -0.1167 | L38: 0.1416 | M38: =N38-L38 | N38: -0.0693 | O38: 0.6493 | P38: =Q38-O38 | Q38: 1.69 | R38: 0.4431 | S38: =T38-R38 | T38: 2.8927 | U38: ='Balance Sheet'!U25-'Balance Sheet'!T25 | V38: ='Balance Sheet'!V25-'Balance Sheet'!U25 | W38: =U38+V38 | X38: =-('Balance Sheet'!W25-'Balance Sheet'!X25) | Y38: =-('Balance Sheet'!X25-'Balance Sheet'!Y25) | Z38: =-('Balance Sheet'!W25-'Balance Sheet'!Z25) | AA38: =-('Balance Sheet'!Z25-'Balance Sheet'!AA25) | AB38: =-('Balance Sheet'!AA25-'Balance Sheet'!AB25) | AC38: =-('Balance Sheet'!Z25-'Balance Sheet'!AC25) | AD38: =-('Balance Sheet'!AC25-'Balance Sheet'!AD25) | AE38: =-('Balance Sheet'!AD25-'Balance Sheet'!AE25) | AF38: =-('Balance Sheet'!AC25-'Balance Sheet'!AF25) | AG38: =-('Balance Sheet'!AF25-'Balance Sheet'!AG25) | AH38: =-('Balance Sheet'!AG25-'Balance Sheet'!AH25) | AI38: =-('Balance Sheet'!AF25-'Balance Sheet'!AI25)
B39: Net Changes in Working Capital | C39: =SUM(C31:C38) | D39: =SUM(D31:D38) | E39: -6.1146 | F39: =SUM(F31:F38) | G39: =SUM(G31:G38) | H39: -14.0028 | I39: =SUM(I31:I38) | J39: =SUM(J31:J38) | K39: -39.8298 | L39: =SUM(L31:L38) | M39: =SUM(M31:M38) | N39: 44.9546 | O39: =SUM(O31:O38) | P39: =SUM(P31:P38) | Q39: =SUM(Q31:Q38) | R39: =SUM(R31:R38) | S39: =SUM(S31:S38) | T39: =SUM(T31:T38) | U39: =SUM(U31:U38) | V39: =SUM(V31:V38) | ... AI39: =SUM(AI31:AI38)
B40: Cash Generated from Operations | C40: =C29+C39 | D40: =D29+D39 | E40: 65.2755 | F40: =F29+F39 | G40: =G29+G39 | H40: 58.3378 | I40: =I29+I39 | J40: =J29+J39 | K40: 43.1296 | L40: =L29+L39 | M40: =M29+M39 | N40: =N29+N39 | O40: =O29+O39 | P40: =P29+P39 | Q40: =Q29+Q39 | R40: =R29+R39 | S40: =S29+S39 | ... AI40: =AI29+AI39
B41: Direct Taxes paid (Net of Tax refund) | C41: -4.6335 | D41: =E41-C41 | E41: -12.2944 | F41: -4.2634 | G41: =H41-F41 | H41: 15.7049 | I41: -6.1715 | J41: =K41-I41 | K41: -13.1125 | L41: -8.94401 | M41: =N41-L41 | N41: -10.0262 | O41: -12.8494 | P41: =Q41-O41 | Q41: -28.2461 | R41: -13.7643 | S41: =T41-R41 | T41: -30.6684 | U41: =-'Income Statement'!U41+('Balance Sheet'!U27-'Balance Sheet'!T27)+('Balance Sheet'!T52-'Balance Sheet'!U52) | V41: =-'Income Statement'!V41+('Balance Sheet'!V27-'Balance Sheet'!U27)+('Balance Sheet'!U52-'Balance Sheet'!V52) | W41: =U41+V41 | X41: =-'Income Statement'!X41+('Balance Sheet'!X27-'Balance Sheet'!W27)+('Balance Sheet'!W52-'Balance Sheet'!X52) | Y41: =-'Income Statement'!Y41+('Balance Sheet'!Y27-'Balance Sheet'!X27)+('Balance Sheet'!X52-'Balance Sheet'!Y52) | Z41: =-'Income Statement'!Z41 | AA41: =-'Income Statement'!AA41+('Balance Sheet'!AA27-'Balance Sheet'!Z27)+('Balance Sheet'!Z52-'Balance Sheet'!AA52) | AB41: =-'Income Statement'!AB41+('Balance Sheet'!AB27-'Balance Sheet'!AA27)+('Balance Sheet'!AA52-'Balance Sheet'!AB52) | AC41: =-'Income Statement'!AC41 | AD41: =-'Income Statement'!AD41+('Balance Sheet'!AD27-'Balance Sheet'!AC27)+('Balance Sheet'!AC52-'Balance Sheet'!AD52) | AE41: =-'Income Statement'!AE41+('Balance Sheet'!AE27-'Balance Sheet'!AD27)+('Balance Sheet'!AD52-'Balance Sheet'!AE52) | AF41: =-'Income Statement'!AF41 | AG41: =-'Income Statement'!AG41+('Balance Sheet'!AG27-'Balance Sheet'!AF27)+('Balance Sheet'!AF52-'Balance Sheet'!AG52) | AH41: =-'Income Statement'!AH41+('Balance Sheet'!AH27-'Balance Sheet'!AG27)+('Balance Sheet'!AG52-'Balance Sheet'!AH52) | AI41: =-'Income Statement'!AI41
B42: Net Cash Flow from Operating Activities | C42: =SUM(C40:C41) | D42: =SUM(D40:D41) | E42: =SUM(E40:E41) | F42: =SUM(F40:F41) | G42: =SUM(G40:G41) | H42: =SUM(H40:H41) | I42: =SUM(I40:I41) | J42: =SUM(J40:J41) | ... AI42: =SUM(AI40:AI41)
B43: check | C43: 66.134 | E43: 52.9811 | F43: 43.4005 | H43: 74.0427 | I43: 27.5785 | K43: 30.0171 | L43: 95.67259 | N43: 169.3843 | O43: -15.8562 | Q43: -7.1533 | R43: -62.1927 | T43: 2.1621
B44: difference | C44: =C42-C43 | E44: =E42-E43 | F44: =F42-F43 | H44: =H42-H43 | I44: =I42-I43 | K44: =K42-K43 | L44: =L42-L43 | N44: =N42-N43 | O44: =O42-O43 | Q44: =Q42-Q43 | R44: =R42-R43 | T44: =T42-T43
B46: Cash Flow from Investing Activities
B47: Payments for Property, Plant & Equipment, Intangible Assets (including work in progress & Capital advances) | C47: -34.7196 | D47: =E47-C47 | E47: -40.2812 | F47: -2.6373 | G47: =H47-F47 | H47: -41.5518 | I47: -38.0977 | J47: =K47-I47 | K47: -74.9186 | L47: -18.4411 | M47: =N47-L47 | N47: -42.9118 | O47: -22.0158 | P47: =Q47-O47 | Q47: -44.6183 | R47: -38.5815 | S47: =T47-R47 | T47: -52.8782 | U47: =-('Balance Sheet'!U64)+('Balance Sheet'!T36-'Balance Sheet'!U36)+('Balance Sheet'!T38-'Balance Sheet'!U38)+('Balance Sheet'!T39-'Balance Sheet'!U39) | V47: =-('Balance Sheet'!V64)+('Balance Sheet'!U36-'Balance Sheet'!V36)+('Balance Sheet'!U38-'Balance Sheet'!V38)+('Balance Sheet'!U39-'Balance Sheet'!V39) | W47: =U47+V47 | X47: =-('Balance Sheet'!X64)+('Balance Sheet'!W36-'Balance Sheet'!X36)+('Balance Sheet'!W38-'Balance Sheet'!X38)+('Balance Sheet'!W39-'Balance Sheet'!X39) | Y47: =-('Balance Sheet'!Y64)+('Balance Sheet'!X36-'Balance Sheet'!Y36)+('Balance Sheet'!X38-'Balance Sheet'!Y38)+('Balance Sheet'!X39-'Balance Sheet'!Y39) | Z47: =X47+Y47 | AA47: =-('Balance Sheet'!AA64)+('Balance Sheet'!Z36-'Balance Sheet'!AA36)+('Balance Sheet'!Z38-'Balance Sheet'!AA38)+('Balance Sheet'!Z39-'Balance Sheet'!AA39) | AB47: =-('Balance Sheet'!AB64)+('Balance Sheet'!AA36-'Balance Sheet'!AB36)+('Balance Sheet'!AA38-'Balance Sheet'!AB38)+('Balance Sheet'!AA39-'Balance Sheet'!AB39) | AC47: =AA47+AB47 | AD47: =-('Balance Sheet'!AD64)+('Balance Sheet'!AC36-'Balance Sheet'!AD36)+('Balance Sheet'!AC38-'Balance Sheet'!AD38)+('Balance Sheet'!AC39-'Balance Sheet'!AD39) | AE47: =-('Balance Sheet'!AE64)+('Balance Sheet'!AD36-'Balance Sheet'!AE36)+('Balance Sheet'!AD38-'Balance Sheet'!AE38)+('Balance Sheet'!AD39-'Balance Sheet'!AE39) | AF47: =AD47+AE47 | AG47: =-('Balance Sheet'!AG64)+('Balance Sheet'!AF36-'Balance Sheet'!AG36)+('Balance Sheet'!AF38-'Balance Sheet'!AG38)+('Balance Sheet'!AF39-'Balance Sheet'!AG39) | AH47: =-('Balance Sheet'!AH64)+('Balance Sheet'!AG36-'Balance Sheet'!AH36)+('Balance Sheet'!AG38-'Balance Sheet'!AH38)+('Balance Sheet'!AG39-'Balance Sheet'!AH39) | AI47: =AG47+AH47
B48: Proceeds from disposal of Property, Plant & Equipment | C48: 0.0104 | D48: =E48-C48 | E48: 0.2421 | F48: 0.1478 | G48: =H48-F48 | H48: 0.166 | I48: 0.034 | J48: =K48-I48 | K48: 0.1747 | L48: 0.1504 | M48: =N48-L48 | N48: 0.3018 | O48: 0.6875 | P48: =Q48-O48 | Q48: 0.945 | R48: 0.1171 | S48: =T48-R48 | T48: 0.1607 | W48: =U48+V48 | Z48: =X48+Y48 | AC48: =AA48+AB48 | AF48: =AD48+AE48 | AI48: =AG48+AH48
B49: Investment in Subsidiary | C49: 0 | D49: =E49-C49 | E49: 0 | F49: 0 | G49: =H49-F49 | H49: 0 | I49: 0 | J49: =K49-I49 | K49: 0 | L49: 0 | M49: =N49-L49 | N49: 0 | O49: -33 | P49: =Q49-O49 | Q49: -33 | R49: 0 | S49: =T49-R49 | T49: 0 | U49: ='Balance Sheet'!T37-'Balance Sheet'!U37 | V49: ='Balance Sheet'!U37-'Balance Sheet'!V37 | W49: =U49+V49 | X49: ='Balance Sheet'!W37-'Balance Sheet'!X37 | Y49: ='Balance Sheet'!X37-'Balance Sheet'!Y37 | Z49: =X49+Y49 | AA49: ='Balance Sheet'!Z37-'Balance Sheet'!AA37 | AB49: ='Balance Sheet'!AA37-'Balance Sheet'!AB37 | AC49: =AA49+AB49 | AD49: ='Balance Sheet'!AC37-'Balance Sheet'!AD37 | AE49: ='Balance Sheet'!AD37-'Balance Sheet'!AE37 | AF49: =AD49+AE49 | AG49: ='Balance Sheet'!AF37-'Balance Sheet'!AG37 | AH49: ='Balance Sheet'!AG37-'Balance Sheet'!AH37 | AI49: =AG49+AH49
B50: Purchase of Current Investments | C50: 0 | D50: =E50-C50 | E50: 0 | F50: 0 | G50: =H50-F50 | H50: 0 | I50: 0 | J50: =K50-I50 | K50: 0 | L50: -88.2708 | M50: =N50-L50 | N50: -102.1076 | O50: 0 | P50: =Q50-O50 | Q50: 0 | R50: 0 | S50: =T50-R50 | T50: 0 | W50: =U50+V50 | Z50: =X50+Y50 | AC50: =AA50+AB50 | AF50: =AD50+AE50 | AI50: =AG50+AH50
B51: Sale of Current Investments | C51: 44.9339 | D51: =E51-C51 | E51: 44.9339 | F51: 0 | G51: =H51-F51 | H51: 0 | I51: 0 | J51: =K51-I51 | K51: 0 | L51: 0 | M51: =N51-L51 | N51: 2.8948 | O51: 83.2964 | P51: =Q51-O51 | Q51: 96.2296 | R51: 10.7096 | S51: =T51-R51 | T51: 10.7527 | W51: =U51+V51 | Z51: =X51+Y51 | AC51: =AA51+AB51 | AF51: =AD51+AE51 | AI51: =AG51+AH51
B52: Changes in other bank balances not considered as cash and cash | C52: -31.064 | D52: =E52-C52 | E52: -18.5228 | F52: -23.1996 | G52: =H52-F52 | H52: -23.5587 | I52: 24.9017 | J52: =K52-I52 | K52: 40.0825 | L52: -1.272 | M52: =N52-L52 | N52: -10.9406 | O52: 9.1345 | P52: =Q52-O52 | Q52: 0.1156 | R52: -1.2166 | S52: =T52-R52 | T52: 4.616 | U52: =('Balance Sheet'!T41-'Balance Sheet'!U41)+('Balance Sheet'!T42-'Balance Sheet'!U42)+('Balance Sheet'!T50-'Balance Sheet'!U50) | V52: =('Balance Sheet'!U41-'Balance Sheet'!V41)+('Balance Sheet'!U42-'Balance Sheet'!V42)+('Balance Sheet'!U50-'Balance Sheet'!V50) | W52: =U52+V52 | X52: =('Balance Sheet'!W41-'Balance Sheet'!X41)+('Balance Sheet'!W42-'Balance Sheet'!X42)+('Balance Sheet'!W50-'Balance Sheet'!X50) | Y52: =('Balance Sheet'!X41-'Balance Sheet'!Y41)+('Balance Sheet'!X42-'Balance Sheet'!Y42)+('Balance Sheet'!X50-'Balance Sheet'!Y50) | Z52: =X52+Y52 | AA52: =('Balance Sheet'!Z41-'Balance Sheet'!AA41)+('Balance Sheet'!Z42-'Balance Sheet'!AA42)+('Balance Sheet'!Z50-'Balance Sheet'!AA50) | AB52: =('Balance Sheet'!AA41-'Balance Sheet'!AB41)+('Balance Sheet'!AA42-'Balance Sheet'!AB42)+('Balance Sheet'!AA50-'Balance Sheet'!AB50) | AC52: =AA52+AB52 | AD52: =('Balance Sheet'!AC41-'Balance Sheet'!AD41)+('Balance Sheet'!AC42-'Balance Sheet'!AD42)+('Balance Sheet'!AC50-'Balance Sheet'!AD50) | AE52: =('Balance Sheet'!AD41-'Balance Sheet'!AE41)+('Balance Sheet'!AD42-'Balance Sheet'!AE42)+('Balance Sheet'!AD50-'Balance Sheet'!AE50) | AF52: =AD52+AE52 | AG52: =('Balance Sheet'!AF41-'Balance Sheet'!AG41)+('Balance Sheet'!AF42-'Balance Sheet'!AG42)+('Balance Sheet'!AF50-'Balance Sheet'!AG50) | AH52: =('Balance Sheet'!AG41-'Balance Sheet'!AH41)+('Balance Sheet'!AG42-'Balance Sheet'!AH42)+('Balance Sheet'!AG50-'Balance Sheet'!AH50) | AI52: =AG52+AH52
B53: Interest Received/other income | C53: 0.4287 | D53: =E53-C53 | E53: 1.7121 | F53: 0.3714 | G53: =H53-F53 | H53: 3.5992 | I53: 0.6182 | J53: =K53-I53 | K53: 1.2774 | L53: 0.2047 | M53: =N53-L53 | N53: 0.24 | O53: 2.0528 | P53: =Q53-O53 | Q53: 2.2362 | R53: 0.1739 | S53: =T53-R53 | T53: 0.9579 | W53: =U53+V53 | Z53: =X53+Y53 | AC53: =AA53+AB53 | AF53: =AD53+AE53 | AI53: =AG53+AH53
B54: Net Cash from Investing Activities | C54: =SUM(C47:C53) | D54: =SUM(D47:D53) | E54: =SUM(E47:E53) | F54: =SUM(F47:F53) | G54: =SUM(G47:G53) | H54: =SUM(H47:H53) | I54: =SUM(I47:I53) | J54: =SUM(J47:J53) | ... AI54: =SUM(AI47:AI53)
B55: check | C55: -20.4106 | E55: -11.9159 | F55: -25.3177 | H55: -61.3453 | I55: -12.5438 | K55: -33.384 | L55: -107.6288 | N55: -152.5234 | O55: 40.1554 | Q55: 21.9081 | R55: -28.7975 | T55: -36.3909
B56: difference | C56: =C54-C55 | E56: =E54-E55 | F56: =F54-F55 | H56: =H54-H55 | I56: =I54-I55 | K56: =K54-K55 | L56: =L54-L55 | N56: =N54-N55 | O56: =O54-O55 | Q56: =Q54-Q55 | R56: =R54-R55 | T56: =T54-T55
B58: Cash Flow from Financing Activities
B59: Proceeds from Issue of Share Capital | C59: 0.2132 | D59: =E59-C59 | E59: 0.4753 | F59: 0.7571 | G59: =H59-F59 | H59: 0.7572 | I59: 0 | J59: =K59-I59 | K59: 0.2273 | L59: 0.3835 | M59: =N59-L59 | N59: 1.7586 | O59: 2.2079 | P59: =Q59-O59 | Q59: 3.1418 | R59: 0 | S59: =T59-R59 | T59: 0.005 | W59: =U59+V59 | Z59: =X59+Y59 | AC59: =AA59+AB59 | AF59: =AD59+AE59 | AI59: =AG59+AH59
B60: Buy Back of Equity Shares | C60: 0 | D60: =E60-C60 | E60: -31.1246 | F60: 0 | G60: =H60-F60 | H60: 0 | I60: 0 | J60: =K60-I60 | K60: 0 | L60: 0 | M60: =N60-L60 | N60: 0 | O60: 0 | P60: =Q60-O60 | Q60: 0 | R60: 0 | S60: =T60-R60 | T60: 0 | W60: =U60+V60 | Z60: =X60+Y60 | AC60: =AA60+AB60 | AF60: =AD60+AE60 | AI60: =AG60+AH60
B61: Share Issue Expense | C61: 0 | D61: =E61-C61 | E61: 0 | F61: 0 | G61: =H61-F61 | H61: 0 | I61: 0 | J61: =K61-I61 | K61: 0 | L61: 0 | M61: =N61-L61 | N61: 0 | O61: -0.1817 | P61: =Q61-O61 | Q61: -0.1817 | R61: 0 | S61: =T61-R61 | T61: 0 | W61: =U61+V61 | Z61: =X61+Y61 | AC61: =AA61+AB61 | AF61: =AD61+AE61 | AI61: =AG61+AH61
B62: Proceeds from Long Term Borrowings (Net) | C62: 0 | D62: =E62-C62 | E62: 0 | F62: 0 | G62: =H62-F62 | H62: 0 | I62: 0 | J62: =K62-I62 | K62: 34.3405 | L62: 10.4885 | M62: =N62-L62 | N62: -15.0669 | O62: 0 | P62: =Q62-O62 | Q62: 0 | R62: 0 | S62: =T62-R62 | T62: 53.2998 | W62: =U62+V62 | Z62: =X62+Y62 | AC62: =AA62+AB62 | AF62: =AD62+AE62 | AI62: =AG62+AH62
B63: Repayment of Long Term Borrowings | C63: 0 | D63: =E63-C63 | E63: 0 | F63: 0 | G63: =H63-F63 | H63: 0 | I63: 0 | J63: =K63-I63 | K63: 0 | L63: 0 | M63: =N63-L63 | N63: 0 | O63: -2.057 | P63: =Q63-O63 | Q63: -5.5244 | R63: -2.7091 | S63: =T63-R63 | T63: -9.8885 | U63: ='Balance Sheet'!U13-'Balance Sheet'!T13 | V63: ='Balance Sheet'!V13-'Balance Sheet'!U13 | W63: =U63+V63 | X63: ='Balance Sheet'!X13-'Balance Sheet'!W13 | Y63: ='Balance Sheet'!Y13-'Balance Sheet'!X13 | Z63: =X63+Y63 | AA63: ='Balance Sheet'!AA13-'Balance Sheet'!Z13 | AB63: ='Balance Sheet'!AB13-'Balance Sheet'!AA13 | AC63: =AA63+AB63 | AD63: ='Balance Sheet'!AD13-'Balance Sheet'!AC13 | AE63: ='Balance Sheet'!AE13-'Balance Sheet'!AD13 | AF63: =AD63+AE63 | AG63: ='Balance Sheet'!AG13-'Balance Sheet'!AF13 | AH63: ='Balance Sheet'!AH13-'Balance Sheet'!AG13 | AI63: =AG63+AH63
B64: Proceeds/(Repayment) of Short Term Borrowings (Net) | C64: 0 | D64: =E64-C64 | E64: 0 | F64: 0 | G64: =H64-F64 | H64: 0 | I64: 0 | J64: =K64-I64 | K64: 0 | L64: 0 | M64: =N64-L64 | N64: 0 | O64: 0.172 | P64: =Q64-O64 | Q64: 15.1639 | R64: 128.123 | S64: =T64-R64 | T64: 34.4803 | U64: ='Balance Sheet'!U19-'Balance Sheet'!T19 | V64: ='Balance Sheet'!V19-'Balance Sheet'!U19 | W64: =U64+V64 | X64: ='Balance Sheet'!X19-'Balance Sheet'!W19 | Y64: ='Balance Sheet'!Y19-'Balance Sheet'!X19 | Z64: =X64+Y64 | AA64: ='Balance Sheet'!AA19-'Balance Sheet'!Z19 | AB64: ='Balance Sheet'!AB19-'Balance Sheet'!AA19 | AC64: =AA64+AB64 | AD64: ='Balance Sheet'!AD19-'Balance Sheet'!AC19 | AE64: ='Balance Sheet'!AE19-'Balance Sheet'!AD19 | AF64: =AD64+AE64 | AG64: ='Balance Sheet'!AG19-'Balance Sheet'!AF19 | AH64: ='Balance Sheet'!AH19-'Balance Sheet'!AG19 | AI64: =AG64+AH64
B65: Dividend paid | C65: -0.0006 | D65: =E65-C65 | E65: -7.0228 | F65: -6.7938 | G65: =H65-F65 | H65: -6.7964 | I65: -7.8133 | J65: =K65-I65 | K65: -7.81 | L65: -14.6934 | M65: =N65-L65 | N65: -14.6675 | O65: -39.2369 | P65: =Q65-O65 | Q65: -39.189 | R65: -33.5658 | S65: =T65-R65 | T65: -33.5213 | U65: =-'Income Statement'!U56 | V65: =-'Income Statement'!V56 | W65: =U65+V65 | X65: =-'Income Statement'!X56 | Y65: =-'Income Statement'!Y56 | Z65: =X65+Y65 | AA65: =-'Income Statement'!AA56 | AB65: =-'Income Statement'!AB56 | AC65: =AA65+AB65 | AD65: =-'Income Statement'!AD56 | AE65: =-'Income Statement'!AE56 | AF65: =AD65+AE65 | AG65: =-'Income Statement'!AG56 | AH65: =-'Income Statement'!AH56 | AI65: =AG65+AH65
B66: Payments towards fractional entitlement | C66: -0.0009 | D66: =E66-C66 | E66: -0.0019 | F66: -0.0004 | G66: =H66-F66 | H66: -0.0011 | I66: -0.0005 | J66: =K66-I66 | K66: -0.001 | L66: -0.0007 | M66: =N66-L66 | N66: -0.0016 | O66: -0.0012 | P66: =Q66-O66 | Q66: -0.0026 | R66: -0.0013 | S66: =T66-R66 | T66: -0.0027 | W66: =U66+V66 | Z66: =X66+Y66 | AC66: =AA66+AB66 | AF66: =AD66+AE66 | AI66: =AG66+AH66
B67: Principal repayment of lease liabilities | C67: 0 | D67: =E67-C67 | E67: 0 | F67: 0 | G67: =H67-F67 | H67: 0 | I67: 0 | J67: =K67-I67 | K67: 0 | L67: 0 | M67: =N67-L67 | N67: -0.0696 | O67: -0.0773 | P67: =Q67-O67 | Q67: -0.6663 | R67: -0.2799 | S67: =T67-R67 | T67: -0.5439 | U67: ='Balance Sheet'!U20-'Balance Sheet'!T20 | V67: ='Balance Sheet'!V20-'Balance Sheet'!U20 | W67: =U67+V67 | X67: ='Balance Sheet'!X20-'Balance Sheet'!W20 | Y67: ='Balance Sheet'!Y20-'Balance Sheet'!X20 | Z67: =X67+Y67 | AA67: ='Balance Sheet'!AA20-'Balance Sheet'!Z20 | AB67: ='Balance Sheet'!AB20-'Balance Sheet'!AA20 | AC67: =AA67+AB67 | AD67: ='Balance Sheet'!AD20-'Balance Sheet'!AC20 | AE67: ='Balance Sheet'!AE20-'Balance Sheet'!AD20 | AF67: =AD67+AE67 | AG67: ='Balance Sheet'!AG20-'Balance Sheet'!AF20 | AH67: ='Balance Sheet'!AH20-'Balance Sheet'!AG20 | AI67: =AG67+AH67
B68: Interest Paid on Lease Liability | C68: 0 | D68: =E68-C68 | E68: 0 | F68: 0 | G68: =H68-F68 | H68: 0 | I68: 0 | J68: =K68-I68 | K68: 0 | L68: 0 | M68: =N68-L68 | N68: -0.0251 | O68: -0.0422 | P68: =Q68-O68 | Q68: 0 | R68: 0.1255 | S68: =T68-R68 | T68: 0 | U68: ='Balance Sheet'!U14-'Balance Sheet'!T14 | V68: ='Balance Sheet'!V14-'Balance Sheet'!U14 | W68: =U68+V68 | X68: ='Balance Sheet'!X14-'Balance Sheet'!W14 | Y68: ='Balance Sheet'!Y14-'Balance Sheet'!X14 | Z68: =X68+Y68 | AA68: ='Balance Sheet'!AA14-'Balance Sheet'!Z14 | AB68: ='Balance Sheet'!AB14-'Balance Sheet'!AA14 | AC68: =AA68+AB68 | AD68: ='Balance Sheet'!AD14-'Balance Sheet'!AC14 | AE68: ='Balance Sheet'!AE14-'Balance Sheet'!AD14 | AF68: =AD68+AE68 | AG68: ='Balance Sheet'!AG14-'Balance Sheet'!AF14 | AH68: ='Balance Sheet'!AH14-'Balance Sheet'!AG14 | AI68: =AG68+AH68
B69: Interest Paid | C69: -0.2708 | D69: =E69-C69 | E69: -0.3444 | F69: -0.2223 | G69: =H69-F69 | H69: -1.0315 | I69: -0.5961 | J69: =K69-I69 | K69: -1.7972 | L69: -1.85481 | M69: =N69-L69 | N69: -2.1493 | O69: -1.9184 | P69: =Q69-O69 | Q69: -3.2194 | R69: -2.9776 | S69: =T69-R69 | T69: -8.0595 | U69: =-'Income Statement'!U31 | V69: =-'Income Statement'!V31 | W69: =U69+V69 | X69: =-'Income Statement'!X31 | Y69: =-'Income Statement'!Y31 | Z69: =X69+Y69 | AA69: =-'Income Statement'!AA31 | AB69: =-'Income Statement'!AB31 | AC69: =AA69+AB69 | AD69: =-'Income Statement'!AD31 | AE69: =-'Income Statement'!AE31 | AF69: =AD69+AE69 | AG69: =-'Income Statement'!AG31 | AH69: =-'Income Statement'!AH31 | AI69: =AG69+AH69
B70: Net Cash Flow from Financing Activities | C70: =SUM(C59:C69) | D70: =SUM(D59:D69) | E70: =SUM(E59:E69) | F70: =SUM(F59:F69) | G70: =SUM(G59:G69) | H70: =SUM(H59:H69) | I70: =SUM(I59:I69) | J70: =SUM(J59:J69) | ... AI70: =SUM(AI59:AI69)
B71: check | C71: -0.0591 | E71: -38.0184 | F71: -6.2594 | H71: -7.0718 | I71: -8.4099 | K71: 24.9596 | L71: -5.67691 | N71: -30.2214 | O71: -41.1348 | Q71: -30.4777 | R71: 88.7148 | T71: 35.7692
B72: difference | C72: =C70-C71 | E72: =E70-E71 | F72: =F70-F71 | H72: =H70-H71 | I72: =I70-I71 | K72: =K70-K71 | L72: =L70-L71 | N72: =N70-N71 | O72: =O70-O71 | Q72: =Q70-Q71 | R72: =R70-R71 | T72: =T70-T71
B74: Net Increase/(Decrease) in cash and cash equivalents | C74: =C42+C54+C70 | D74: =D42+D54+D70 | E74: =E42+E54+E70 | F74: =F42+F54+F70 | G74: =G42+G54+G70 | H74: =H42+H54+H70 | I74: =I42+I54+I70 | J74: =J42+J54+J70 | ... AI74: =AI42+AI54+AI70
B75: Cash and Cash equivalent at the beginning of the period | C75: 0.8227 | D75: =C77 | E75: 0.8227 | F75: 3.8695 | G75: =F77 | H75: 3.8695 | I75: 9.4951 | J75: =I77 | K75: 9.4951 | L75: 31.0878 | M75: =L77 | N75: 31.0878 | O75: 17.7475 | P75: =O77 | Q75: 17.7475 | R75: 2.5105 | S75: =R77 | T75: 2.5105 | U75: =T77 | V75: =U77 | W75: =T77 | X75: =W77 | Y75: =X77 | Z75: =W77 | AA75: =Z77 | AB75: =AA77 | AC75: =Z77 | AD75: =AC77 | AE75: =AD77 | AF75: =AC77 | AG75: =AF77 | AH75: =AG77 | AI75: =AF77
B76: Add: Adjustment due to acquisition of Subsidiarv | M76: =N76-L76 | N76: 0.0202 | O76: 2.5436 | P76: =Q76-O76 | Q76: 0.4859 | S76: =T76-R76 | T76: 0
B77: Cash and Cash equivalent at the end of the period | C77: =C74+C75+C76 | D77: =D74+D75+D76 | E77: =E74+E75+E76 | F77: =F74+F75+F76 | G77: =G74+G75+G76 | H77: =H74+H75+H76 | I77: =I74+I75+I76 | J77: =J74+J75+J76 | ... AI77: =AI74+AI75+AI76
B79: Capex | C79: =-C47 | D79: =-D47 | E79: =-E47 | F79: =-F47 | G79: =-G47 | H79: =-H47 | I79: =-I47 | J79: =-J47 | ... AI79: =-AI47
B80: Capex As % of Sales | C80: =C79/'Income Statement'!C8 | D80: =D79/'Income Statement'!D8 | E80: =E79/'Income Statement'!E8 | F80: =F79/'Income Statement'!F8 | G80: =G79/'Income Statement'!G8 | H80: =H79/'Income Statement'!H8 | I80: =I79/'Income Statement'!I8 | J80: =J79/'Income Statement'!J8 | ... AI80: =AI79/'Income Statement'!AI8

Sheet Graphical Representation
B1: Anup Engineering Limited
B2: Fiscal year ending 31st Mar, 2026
B3: All amounts in ₹ crores except per share data
B5: GRAPHICAL REPRESENTATION
B154: Key Financials
B155: Year | C155: H1 | D155: H2 | E155: FY21 | F155: H1 | G155: H2 | H155: FY22 | I155: H1 | J155: H2 | K155: FY23 | L155: H1 | M155: H2 | N155: FY24 | O155: H1 | P155: H2 | Q155: FY25 | R155: H1 | S155: H2 | T155: FY26 | U155: H1 | V155: H2 | W155: FY27 E | X155: H1 | Y155: H2 | Z155: FY28 E | AA155: H1 | AB155: H2 | AC155: FY29 E | AD155: H1 | AE155: H2 | AF155: FY30 E | AG155: H1 | AH155: H2 | AI155: FY31 E
C156: 2021 | D156: 2021 | F156: 2022 | G156: 2022 | I156: 2023 | J156: 2023 | L156: 2024 | M156: 2024 | O156: 2025 | P156: 2025 | R156: 2026 | S156: 2026 | U156: 2027 E | V156: 2027 E | X156: 2028 E | Y156: 2028 E | AA156: 2029 E | AB156: 2029 E | AD156: 2030 E | AE156: 2030 E | AG156: 2031 E | AH156: 2031 E
B157: Revenue from operations | C157: ='Income Statement'!C8 | D157: ='Income Statement'!D8 | E157: ='Income Statement'!E8 | F157: ='Income Statement'!F8 | G157: ='Income Statement'!G8 | H157: ='Income Statement'!H8 | I157: ='Income Statement'!I8 | J157: ='Income Statement'!J8 | ... AI157: ='Income Statement'!AI8
B158: Growth % | F158: =(F157-C157)/C157 | G158: =(G157-D157)/D157 | H158: =(H157-E157)/E157 | I158: =(I157-F157)/F157 | J158: =(J157-G157)/G157 | K158: =(K157-H157)/H157 | L158: =(L157-I157)/I157 | M158: =(M157-J157)/J157 | ... AI158: =(AI157-AF157)/AF157
B160: Segment Wise Revenue Execution
B161: Heat Exchangers | C161: ='Revenue Segments'!C14 | D161: ='Revenue Segments'!D14 | E161: ='Revenue Segments'!E14 | F161: ='Revenue Segments'!F14 | G161: ='Revenue Segments'!G14 | H161: ='Revenue Segments'!H14 | I161: ='Revenue Segments'!I14 | J161: ='Revenue Segments'!J14 | ... AI161: ='Revenue Segments'!AI14
B162: as % of Revenue | E162: =E161/E$157 | F162: =F161/F$157 | G162: =G161/G$157 | H162: =H161/H$157 | I162: =I161/I$157 | J162: =J161/J$157 | K162: =K161/K$157 | L162: =L161/L$157 | ... AI162: =AI161/AI$157
B163: Vessels | C163: ='Revenue Segments'!C26 | D163: ='Revenue Segments'!D26 | E163: ='Revenue Segments'!E26 | F163: ='Revenue Segments'!F26 | G163: ='Revenue Segments'!G26 | H163: ='Revenue Segments'!H26 | I163: ='Revenue Segments'!I26 | J163: ='Revenue Segments'!J26 | ... AI163: ='Revenue Segments'!AI26
B164: as % of Revenue | E164: =E163/E$157 | F164: =F163/F$157 | G164: =G163/G$157 | H164: =H163/H$157 | I164: =I163/I$157 | J164: =J163/J$157 | K164: =K163/K$157 | L164: =L163/L$157 | ... AI164: =AI163/AI$157
B165: Towers & Reactors | C165: ='Revenue Segments'!C38 | D165: ='Revenue Segments'!D38 | E165: ='Revenue Segments'!E38 | F165: ='Revenue Segments'!F38 | G165: ='Revenue Segments'!G38 | H165: ='Revenue Segments'!H38 | I165: ='Revenue Segments'!I38 | J165: ='Revenue Segments'!J38 | ... AI165: ='Revenue Segments'!AI38
B166: as % of Revenue | E166: =E165/E$157 | F166: =F165/F$157 | G166: =G165/G$157 | H166: =H165/H$157 | I166: =I165/I$157 | J166: =J165/J$157 | K166: =K165/K$157 | L166: =L165/L$157 | ... AI166: =AI165/AI$157
B167: Tank & Silos | C167: ='Revenue Segments'!C50 | D167: ='Revenue Segments'!D50 | E167: ='Revenue Segments'!E50 | F167: ='Revenue Segments'!F50 | G167: ='Revenue Segments'!G50 | H167: ='Revenue Segments'!H50 | I167: ='Revenue Segments'!I50 | J167: ='Revenue Segments'!J50 | ... AI167: ='Revenue Segments'!AI50
B168: as % of Revenue | E168: =E167/E$157 | F168: =F167/F$157 | G168: =G167/G$157 | H168: =H167/H$157 | I168: =I167/I$157 | J168: =J167/J$157 | K168: =K167/K$157 | L168: =L167/L$157 | ... AI168: =AI167/AI$157
B169: Centrifuge & Others | C169: ='Revenue Segments'!C62 | D169: ='Revenue Segments'!D62 | E169: ='Revenue Segments'!E62 | F169: ='Revenue Segments'!F62 | G169: ='Revenue Segments'!G62 | H169: ='Revenue Segments'!H62 | I169: ='Revenue Segments'!I62 | J169: ='Revenue Segments'!J62 | ... AI169: ='Revenue Segments'!AI62
B170: as % of Revenue | E170: =E169/E$157 | F170: =F169/F$157 | G170: =G169/G$157 | H170: =H169/H$157 | I170: =I169/I$157 | J170: =J169/J$157 | K170: =K169/K$157 | L170: =L169/L$157 | ... AI170: =AI169/AI$157
B172: Order Book | C172: ='Revenue Segments'!C68 | D172: ='Revenue Segments'!D68 | E172: ='Revenue Segments'!E68 | F172: ='Revenue Segments'!F68 | G172: ='Revenue Segments'!G68 | H172: ='Revenue Segments'!H68 | I172: ='Revenue Segments'!I68 | J172: ='Revenue Segments'!J68 | ... AI172: ='Revenue Segments'!AI68
B173: Order Inflow | C173: ='Revenue Segments'!C11+'Revenue Segments'!C23+'Revenue Segments'!C35+'Revenue Segments'!C47+'Revenue Segments'!C59 | D173: ='Revenue Segments'!D11+'Revenue Segments'!D23+'Revenue Segments'!D35+'Revenue Segments'!D47+'Revenue Segments'!D59 | E173: ='Revenue Segments'!E11+'Revenue Segments'!E23+'Revenue Segments'!E35+'Revenue Segments'!E47+'Revenue Segments'!E59 | F173: ='Revenue Segments'!F11+'Revenue Segments'!F23+'Revenue Segments'!F35+'Revenue Segments'!F47+'Revenue Segments'!F59 | G173: ='Revenue Segments'!G11+'Revenue Segments'!G23+'Revenue Segments'!G35+'Revenue Segments'!G47+'Revenue Segments'!G59 | H173: ='Revenue Segments'!H11+'Revenue Segments'!H23+'Revenue Segments'!H35+'Revenue Segments'!H47+'Revenue Segments'!H59 | I173: ='Revenue Segments'!I11+'Revenue Segments'!I23+'Revenue Segments'!I35+'Revenue Segments'!I47+'Revenue Segments'!I59 | J173: ='Revenue Segments'!J11+'Revenue Segments'!J23+'Revenue Segments'!J35+'Revenue Segments'!J47+'Revenue Segments'!J59 | ... AI173: ='Revenue Segments'!AI11+'Revenue Segments'!AI23+'Revenue Segments'!AI35+'Revenue Segments'!AI47+'Revenue Segments'!AI59
B174: Order Book to Bill Ratio | C174: =C172/C157 | D174: =D172/D157 | E174: =E172/E157 | F174: =F172/F157 | G174: =G172/G157 | H174: =H172/H157 | I174: =I172/I157 | J174: =J172/J157 | ... AI174: =AI172/AI157
B175: Book to Bill Ratio | E175: =E173/E157 | F175: =F173/F157 | G175: =G173/G157 | H175: =H173/H157 | I175: =I173/I157 | J175: =J173/J157 | K175: =K173/K157 | L175: =L173/L157 | ... AI175: =AI173/AI157
B177: EBITDA | C177: ='Income Statement'!C23 | D177: ='Income Statement'!D23 | E177: ='Income Statement'!E23 | F177: ='Income Statement'!F23 | G177: ='Income Statement'!G23 | H177: ='Income Statement'!H23 | I177: ='Income Statement'!I23 | J177: ='Income Statement'!J23 | ... AI177: ='Income Statement'!AI23
B178: EBITDA Margin | C178: ='Income Statement'!C24 | D178: ='Income Statement'!D24 | E178: ='Income Statement'!E24 | F178: ='Income Statement'!F24 | G178: ='Income Statement'!G24 | H178: ='Income Statement'!H24 | I178: ='Income Statement'!I24 | J178: ='Income Statement'!J24 | ... AI178: ='Income Statement'!AI24
B180: EBIT | C180: ='Income Statement'!C27 | D180: ='Income Statement'!D27 | E180: ='Income Statement'!E27 | F180: ='Income Statement'!F27 | G180: ='Income Statement'!G27 | H180: ='Income Statement'!H27 | I180: ='Income Statement'!I27 | J180: ='Income Statement'!J27 | ... AI180: ='Income Statement'!AI27
B181: EBIT Margin | C181: ='Income Statement'!C28 | D181: ='Income Statement'!D28 | E181: ='Income Statement'!E28 | F181: ='Income Statement'!F28 | G181: ='Income Statement'!G28 | H181: ='Income Statement'!H28 | I181: ='Income Statement'!I28 | J181: ='Income Statement'!J28 | ... AI181: ='Income Statement'!AI28
B183: PAT | C183: ='Income Statement'!C43 | D183: ='Income Statement'!D43 | E183: ='Income Statement'!E43 | F183: ='Income Statement'!F43 | G183: ='Income Statement'!G43 | H183: ='Income Statement'!H43 | I183: ='Income Statement'!I43 | J183: ='Income Statement'!J43 | ... AI183: ='Income Statement'!AI43
B184: PAT Margin | C184: ='Income Statement'!C46 | D184: ='Income Statement'!D46 | E184: ='Income Statement'!E46 | F184: ='Income Statement'!F46 | G184: ='Income Statement'!G46 | H184: ='Income Statement'!H46 | I184: ='Income Statement'!I46 | J184: ='Income Statement'!J46 | ... AI184: ='Income Statement'!AI46
B186: EPS | C186: ='Income Statement'!C49 | D186: ='Income Statement'!D49 | E186: ='Income Statement'!E49 | F186: ='Income Statement'!F49 | G186: ='Income Statement'!G49 | H186: ='Income Statement'!H49 | I186: ='Income Statement'!I49 | J186: ='Income Statement'!J49 | ... AI186: ='Income Statement'!AI49
B187: PE ratio | C187: ='Income Statement'!C76 | D187: ='Income Statement'!D76 | E187: ='Income Statement'!E76 | F187: ='Income Statement'!F76 | G187: ='Income Statement'!G76 | H187: ='Income Statement'!H76 | I187: ='Income Statement'!I76 | J187: ='Income Statement'!J76 | ... AI187: ='Income Statement'!AI76
B188: CMP | C188: ='Income Statement'!C50 | D188: ='Income Statement'!D50 | E188: ='Income Statement'!E50 | F188: ='Income Statement'!F50 | G188: ='Income Statement'!G50 | H188: ='Income Statement'!H50 | I188: ='Income Statement'!I50 | J188: ='Income Statement'!J50 | ... AI188: ='Income Statement'!AI50
B189: 10x | C189: =C$186*10 | D189: =D$186*10 | E189: =E$186*10 | F189: =F$186*10 | G189: =G$186*10 | H189: =H$186*10 | I189: =I$186*10 | J189: =J$186*10 | ... AI189: =AI$186*10
B190: 15x | C190: =C$186*15 | D190: =D$186*15 | E190: =E$186*15 | F190: =F$186*15 | G190: =G$186*15 | H190: =H$186*15 | I190: =I$186*15 | J190: =J$186*15 | ... AI190: =AI$186*15
B191: 20x | C191: =C$186*20 | D191: =D$186*20 | E191: =E$186*20 | F191: =F$186*20 | G191: =G$186*20 | H191: =H$186*20 | I191: =I$186*20 | J191: =J$186*20 | ... AI191: =AI$186*20
B192: 25x | C192: =C$186*25 | D192: =D$186*25 | E192: =E$186*25 | F192: =F$186*25 | G192: =G$186*25 | H192: =H$186*25 | I192: =I$186*25 | J192: =J$186*25 | ... AI192: =AI$186*25
B193: 30x | C193: =C$186*30 | D193: =D$186*30 | E193: =E$186*30 | F193: =F$186*30 | G193: =G$186*30 | H193: =H$186*30 | I193: =I$186*30 | J193: =J$186*30 | ... AI193: =AI$186*30
B195: Export | C195: ='Revenue Segments'!C77 | D195: ='Revenue Segments'!D77 | E195: ='Revenue Segments'!E77 | F195: ='Revenue Segments'!F77 | G195: ='Revenue Segments'!G77 | H195: ='Revenue Segments'!H77 | I195: ='Revenue Segments'!I77 | J195: ='Revenue Segments'!J77 | ... R195: ='Revenue Segments'!R77 | S195: ='Revenue Segments'!S77-'Revenue Segments'!S105 | T195: ='Revenue Segments'!T77-'Revenue Segments'!T105 | U195: ='Revenue Segments'!U77-'Revenue Segments'!U105 | V195: ='Revenue Segments'!V77-'Revenue Segments'!V105 | W195: ='Revenue Segments'!W77-'Revenue Segments'!W105 | X195: ='Revenue Segments'!X77-'Revenue Segments'!X105 | Y195: ='Revenue Segments'!Y77-'Revenue Segments'!Y105 | Z195: ='Revenue Segments'!Z77-'Revenue Segments'!Z105 | ... AI195: ='Revenue Segments'!AI77-'Revenue Segments'!AI105
B196: Domestic | C196: ='Revenue Segments'!C73 | D196: ='Revenue Segments'!D73 | E196: ='Revenue Segments'!E73 | F196: ='Revenue Segments'!F73 | G196: ='Revenue Segments'!G73 | H196: ='Revenue Segments'!H73 | I196: ='Revenue Segments'!I73 | J196: ='Revenue Segments'!J73 | ... AI196: ='Revenue Segments'!AI73
B197: DE/SEX | C197: ='Revenue Segments'!C81 | D197: ='Revenue Segments'!D81 | E197: ='Revenue Segments'!E81 | F197: ='Revenue Segments'!F81 | G197: ='Revenue Segments'!G81 | H197: ='Revenue Segments'!H81 | I197: ='Revenue Segments'!I81 | J197: ='Revenue Segments'!J81 | ... AI197: ='Revenue Segments'!AI81
B199: ROA | C199: ='Income Statement'!C70 | D199: ='Income Statement'!D70 | E199: ='Income Statement'!E70 | F199: ='Income Statement'!F70 | G199: ='Income Statement'!G70 | H199: ='Income Statement'!H70 | I199: ='Income Statement'!I70 | J199: ='Income Statement'!J70 | ... AI199: ='Income Statement'!AI70
B200: ROE | C200: ='Income Statement'!C71 | D200: ='Income Statement'!D71 | E200: ='Income Statement'!E71 | F200: ='Income Statement'!F71 | G200: ='Income Statement'!G71 | H200: ='Income Statement'!H71 | I200: ='Income Statement'!I71 | J200: ='Income Statement'!J71 | ... AI200: ='Income Statement'!AI71
B201: ROCE | C201: ='Income Statement'!C72 | D201: ='Income Statement'!D72 | E201: ='Income Statement'!E72 | F201: ='Income Statement'!F72 | G201: ='Income Statement'!G72 | H201: ='Income Statement'!H72 | I201: ='Income Statement'!I72 | J201: ='Income Statement'!J72 | ... AI201: ='Income Statement'!AI72
B203: Recievable Days | C203: ='Balance Sheet'!C79 | D203: ='Balance Sheet'!D79 | E203: ='Balance Sheet'!E79 | F203: ='Balance Sheet'!F79 | G203: ='Balance Sheet'!G79 | H203: ='Balance Sheet'!H79 | I203: ='Balance Sheet'!I79 | J203: ='Balance Sheet'!J79 | ... AI203: ='Balance Sheet'!AI79
B204: YoY Growth % | H204: =(H203-E203)/E203 | I204: =(I203-F203)/F203 | J204: =(J203-G203)/G203 | K204: =(K203-H203)/H203 | L204: =(L203-I203)/I203 | M204: =(M203-J203)/J203 | N204: =(N203-K203)/K203 | O204: =(O203-L203)/L203 | ... AI204: =(AI203-AF203)/AF203
B206: Stress Test Scenario
B207: Base Case | C207: ='Revenue Segments'!C114 | D207: ='Revenue Segments'!D114 | E207: ='Revenue Segments'!E114 | F207: ='Revenue Segments'!F114 | G207: ='Revenue Segments'!G114 | H207: ='Revenue Segments'!H114 | I207: ='Revenue Segments'!I114 | J207: ='Revenue Segments'!J114 | ... AI207: ='Revenue Segments'!AI114
B208: Moderate Case | C208: ='Revenue Segments'!C119 | D208: ='Revenue Segments'!D119 | E208: ='Revenue Segments'!E119 | F208: ='Revenue Segments'!F119 | G208: ='Revenue Segments'!G119 | H208: ='Revenue Segments'!H119 | I208: ='Revenue Segments'!I119 | J208: ='Revenue Segments'!J119 | ... AI208: ='Revenue Segments'!AI119
B209: Severe Case | C209: ='Revenue Segments'!C126 | D209: ='Revenue Segments'!D126 | E209: ='Revenue Segments'!E126 | F209: ='Revenue Segments'!F126 | G209: ='Revenue Segments'!G126 | H209: ='Revenue Segments'!H126 | I209: ='Revenue Segments'!I126 | J209: ='Revenue Segments'!J126 | ... AI209: ='Revenue Segments'!AI126
B211: Risk Analysis
B212: Currency CVaR | W212: ='Revenue Segments'!W102 | X212: ='Revenue Segments'!X102 | Y212: ='Revenue Segments'!Y102 | Z212: ='Revenue Segments'!Z102 | AA212: ='Revenue Segments'!AA102 | AB212: ='Revenue Segments'!AB102 | AC212: ='Revenue Segments'!AC102 | AD212: ='Revenue Segments'!AD102 | ... AI212: ='Revenue Segments'!AI102
B213: Geopolitical CVaR | W213: ='Revenue Segments'!W103 | X213: ='Revenue Segments'!X103 | Y213: ='Revenue Segments'!Y103 | Z213: ='Revenue Segments'!Z103 | AA213: ='Revenue Segments'!AA103 | AB213: ='Revenue Segments'!AB103 | AC213: ='Revenue Segments'!AC103 | AD213: ='Revenue Segments'!AD103 | ... AI213: ='Revenue Segments'!AI103
B214: Combined CVaR (Markowitz) | W214: ='Revenue Segments'!W105 | X214: ='Revenue Segments'!X105 | Y214: ='Revenue Segments'!Y105 | Z214: ='Revenue Segments'!Z105 | AA214: ='Revenue Segments'!AA105 | AB214: ='Revenue Segments'!AB105 | AC214: ='Revenue Segments'!AC105 | AD214: ='Revenue Segments'!AD105 | ... AI214: ='Revenue Segments'!AI105
B215: Undiversified Sum | W215: =W212+W213 | X215: =X212+X213 | Y215: =Y212+Y213 | Z215: =Z212+Z213 | AA215: =AA212+AA213 | AB215: =AB212+AB213 | AC215: =AC212+AC213 | AD215: =AD212+AD213 | ... AI215: =AI212+AI213
B216: Combined Sigma
E218: FY26 EPS | H218: FY25 EPS | K218: EPS Growth | N218: P/E Ratio | Q218: EV/EBITDA | T218: EBITDA %
K219: 0 | N219: 0
B220: ISGEC Heavy Engineering | E220: ='Peer Comps'!J8 | H220: 33.89 | K220: =(E220-H220)/H220 | N220: ='Peer Comps'!W8 | Q220: ='Peer Data'!O9 | T220: ='Peer Data'!D28/'Peer Data'!D20
B221: Praj Industries | E221: ='Peer Comps'!J9 | H221: 11.91 | K221: =(E221-H221)/H221 | N221: ='Peer Comps'!W9 | Q221: ='Peer Data'!O10 | T221: ='Peer Data'!E28/'Peer Data'!E20
B222: GMM Pfaudler | E222: ='Peer Comps'!J10 | H222: 11.78 | K222: =(E222-H222)/H222 | N222: ='Peer Comps'!W10 | Q222: ='Peer Data'!O11 | T222: ='Peer Data'!F28/'Peer Data'!F20
B223: Thermax | E223: 60.47 | H223: 53.25 | K223: =(E223-H223)/H223 | N223: ='Peer Data'!D12/'Peer Data'!G52 | Q223: ='Peer Data'!O12 | T223: ='Peer Data'!G28/'Peer Data'!G20
B224: Patels Airtemp India | E224: ='Peer Data'!H52 | H224: 30.18 | K224: =(E224-H224)/H224 | N224: ='Peer Data'!D13/'Peer Data'!H52 | Q224: ='Peer Data'!O13 | T224: ='Peer Data'!H28/'Peer Data'!H20
B225: Anup Engineering Ltd | E225: ='Peer Comps'!J11 | H225: 59.07 | K225: =(E225-H225)/H225 | N225: ='Peer Comps'!W11 | Q225: ='Peer Data'!O14 | T225: ='Peer Data'!C28/'Peer Data'!C20
B227: Football Field Chart | E227: Max | H227: Min | K227: Range | Q227: Scenario | T227: DCF per share
B228: DCF | E228: =MAX('DCF Model'!I54:I58) | H228: =MIN('DCF Model'!I54:I58) | K228: =E228-H228 | Q228: Conservative | T228: ='DCF Model'!I55
B229: EV/EBITDA Implied | E229: =$E$225*Q221 | H229: =$E$225*Q222 | K229: =E229-H229 | Q229: Base Case | T229: ='DCF Model'!I56
B230: EV/EBITDA Peer Implied | E230: =((MAX('Peer Comps'!X8:X10)*'Peer Comps'!F11)-'Peer Comps'!K11+'Peer Comps'!L11)/'Peer Comps'!T11 | H230: =((MIN('Peer Comps'!X8:X10)*'Peer Comps'!F11)-'Peer Comps'!K11+'Peer Comps'!L11)/'Peer Comps'!T11 | K230: =E230-H230 | Q230: Aggressive | T230: ='DCF Model'!I57
B231: P/E Implied | E231: =E225*N222 | H231: =E225*N224 | K231: =E231-H231
B233: Combined CVaR Chart | E233: Potential Loss (Cr) | H233: Probability Density | Q233: Chart: Refineries capacity in India
E234: -210 | H234: =_xlfn.NORM.DIST(E234,0,70.38,0) | Q234: Year | T234: Actuals | W234: Projected
E235: -180 | H235: =_xlfn.NORM.DIST(E235,0,70.38,0) | Q235: FY20 | T235: 249.866
E236: -150 | H236: =_xlfn.NORM.DIST(E236,0,70.38,0) | Q236: FY21 | T236: 248.866
E237: -120 | H237: =_xlfn.NORM.DIST(E237,0,70.38,0) | Q237: FY22 | T237: 251.216
E238: -90 | H238: =_xlfn.NORM.DIST(E238,0,70.38,0) | Q238: FY23 | T238: 253.916
E239: -60 | H239: =_xlfn.NORM.DIST(E239,0,70.38,0) | Q239: FY24 | T239: 256.8
E240: -30 | H240: =_xlfn.NORM.DIST(E240,0,70.38,0) | Q240: FY25 | T240: 258.116 | W240: =T240
E241: 0 | H241: =_xlfn.NORM.DIST(E241,0,70.38,0) | Q241: FY30 | W241: 309.5
E242: 30 | H242: =_xlfn.NORM.DIST(E242,0,70.38,0) | Q242: FY47 (Viksit Bharat) | W242: 450
E243: 60 | H243: =_xlfn.NORM.DIST(E243,0,70.38,0) | Q243: Source: Ministry of Petroleum & Natural Gas
E244: 90 | H244: =_xlfn.NORM.DIST(E244,0,70.38,0)
E245: 120 | H245: =_xlfn.NORM.DIST(E245,0,70.38,0)
E246: 150 | H246: =_xlfn.NORM.DIST(E246,0,70.38,0)
E247: 180 | H247: =_xlfn.NORM.DIST(E247,0,70.38,0)
E248: 210 | H248: =_xlfn.NORM.DIST(E248,0,70.38,0)
B250: Chart Helper: Equity value to Enterprise Value | K250: Chart: Export Vs Domestic
B251: Equity Value | E251: ='Peer Data'!E14 | K251: Segment | N251: FY25 Opn OB | Q251: FY27 Opn OB
B252: +Debt | E252: ='Peer Data'!G14 | K252: Export | N252: 0.74 | Q252: 0.399
B253: -Cash | E253: =-'Peer Data'!F14 | K253: Domestic | N253: 0.26 | Q253: 0.601
B254: Enterprise Value | E254: =SUM(E251:E253)
B256: Chart Helper: Revenue Bridge Chart | K256: Series | N256: Values
B257: Revenue FY25 | E257: ='Revenue Segments'!Q69 | K257: Estimate | N257: ='Estimate Sheet'!C8
B258: Heat Exchangers | E258: =T161-Q161 | K258: Consensus | N258: ='Estimate Sheet'!D8
B259: Vessels | E259: =T163-Q163 | K259: Actual | N259: ='Estimate Sheet'!F8
B260: Towers & Reactors | E260: =T165-Q165
B261: Tank & Silos | E261: =T167-Q167
B262: Centrifuge & Others | E262: =T169-Q169
B263: Revenue FY26 | E263: =SUM(E257:E262)
B265: Anup stock price vs BSE Capital Goods Chart
B266: Date | E266: Anup Clg Price | H266: Anup Indexed at 100 | K266: BSE Capital Goods Clg Price | N266: BSE Capital Goods Indexed at 100 | T266: Date | W266: Anup PE (Daily-5 Years)
...

Sheet Revenue Segments
B1: Anup Engineering Limited
B2: Fiscal year ending 31st Mar, 2026 | C2: H1 | D2: H2 | E2: FY | F2: H1 | G2: H2 | H2: FY | I2: H1 | J2: H2 | K2: FY | L2: H1 | M2: H2 | N2: FY | O2: H1 | P2: H2 | Q2: FY | R2: H1 | S2: H2 | T2: FY | U2: H1 | V2: H2 | W2: FY | X2: H1 | Y2: H2 | Z2: FY | AA2: H1 | AB2: H2 | AC2: FY | AD2: H1 | AE2: H2 | AF2: FY | AG2: H1 | AH2: H2 | AI2: FY
B3: All amounts in ₹ crores except per share data | C3: 2021 | D3: 2021 | E3: 2021 | F3: 2022 | G3: 2022 | H3: 2022 | I3: 2023 | J3: 2023 | K3: 2023 | L3: 2024 | M3: 2024 | N3: 2024 | O3: 2025 | P3: 2025 | Q3: 2025 | R3: 2026 | S3: 2026 | T3: 2026 | U3: 2027 E | V3: 2027 E | W3: 2027 E | X3: 2028 E | Y3: 2028 E | Z3: 2028 E | AA3: 2029 E | AB3: 2029 E | AC3: 2029 E | AD3: 2030 E | AE3: 2030 E | AF3: 2030 E | AG3: 2031 E | AH3: 2031 E | AI3: 2031 E
B5: REVENUE BIFURCATION
B7: PRODUCT CATEGORY
B8: Heat Exchangers
B9: Opening order book | D9: =C17 | E9: 0 | F9: =E17 | G9: =F17 | H9: =E17 | I9: =H17 | J9: =I17 | K9: =H17 | L9: =K17 | M9: =L17 | N9: =K17 | O9: =N17 | P9: =O17 | Q9: =N17 | R9: =Q17 | S9: =R17 | T9: =Q17 | U9: =T17 | V9: =U17 | W9: =T17 | X9: =W17 | Y9: =X17 | Z9: =W17 | AA9: =Z17 | AB9: =AA17 | AC9: =Z17 | AD9: =AC17 | AE9: =AD17 | AF9: =AC17 | AG9: =AF17 | AH9: =AG17 | AI9: =AF17
B11: Order Inflow | D11: =D17-D9+D14 | E11: =E17-E9+E14 | F11: =F17-F9+F14 | G11: =G17-G9+G14 | H11: =H17-H9+H14 | I11: =I17-I9+I14 | J11: =J17-J9+J14 | K11: =K17-K9+K14 | ... S11: =S17-S9+S14 | T11: =R11+S11 | U11: =AVERAGE(MAX(L11,0),MAX(O11,0),MAX(R11,0))*(1+U12) | V11: =AVERAGE(MAX(M11,0),MAX(P11,0),MAX(S11,0))*(1+V12) | W11: =U11+V11 | X11: =AVERAGE(MAX(O11,0),MAX(R11,0),MAX(U11,0))*(1+X12) | Y11: =AVERAGE(MAX(P11,0),MAX(S11,0),MAX(V11,0))*(1+Y12) | Z11: =X11+Y11 | AA11: =AVERAGE(MAX(R11,0),MAX(U11,0),MAX(X11,0))*(1+AA12) | AB11: =AVERAGE(MAX(S11,0),MAX(V11,0),MAX(Y11,0))*(1+AB12) | AC11: =AA11+AB11 | AD11: =AVERAGE(MAX(U11,0),MAX(X11,0),MAX(AA11,0))*(1+AD12) | AE11: =AVERAGE(MAX(V11,0),MAX(Y11,0),MAX(AB11,0))*(1+AE12) | AF11: =AD11+AE11 | AG11: =AVERAGE(MAX(X11,0),MAX(AA11,0),MAX(AD11,0))*(1+AG12) | AH11: =AVERAGE(MAX(Y11,0),MAX(AB11,0),MAX(AE11,0))*(1+AH12) | AI11: =AG11+AH11
B12: Growth % | G12: =(G11-D11)/D11 | H12: =(H11-E11)/E11 | I12: =(I11-F11)/F11 | J12: =(J11-G11)/G11 | K12: =(K11-H11)/H11 | L12: =(L11-I11)/I11 | M12: =(M11-J11)/J11 | N12: =(N11-K11)/K11 | ... T12: =(T11-Q11)/Q11 | U12: 0.08 | V12: =U12 | W12: =(W11-T11)/T11 | X12: =V12+3% | Y12: =X12 | Z12: =(Z11-W11)/W11 | AA12: =Y12+3% | AB12: =AA12 | AC12: =(AC11-Z11)/Z11 | AD12: =AB12+3% | AE12: =AD12 | AF12: =(AF11-AC11)/AC11 | AG12: =AE12+3% | AH12: =AG12 | AI12: =(AI11-AF11)/AF11
B14: Revenue Executed | D14: =E14-C14 | F14: 88 | G14: =H14-F14 | H14: 195.6 | I14: 115.7 | J14: =K14-I14 | K14: 305.8 | L14: 104.9 | M14: =N14-L14 | N14: 387.6 | O14: 243 | P14: =Q14-O14 | Q14: 467.6 | R14: 234.8 | S14: =T14-R14 | T14: 443.2 | U14: =U15*(U9+U11) | V14: =V15*(V9+V11) | W14: =U14+V14 | X14: =X15*(X9+X11) | Y14: =Y15*(Y9+Y11) | Z14: =X14+Y14 | AA14: =AA15*(AA9+AA11) | AB14: =AB15*(AB9+AB11) | AC14: =AA14+AB14 | AD14: =AD15*(AD9+AD11) | AE14: =AE15*(AE9+AE11) | AF14: =AD14+AE14 | AG14: =AG15*(AG9+AG11) | AH14: =AH15*(AH9+AH11) | AI14: =AG14+AH14
B15: Execution % | D15: =D14/(D9+D11) | E15: =E14/(E9+E11) | F15: =F14/(F9+F11) | G15: =G14/(G9+G11) | H15: =H14/(H9+H11) | I15: =I14/(I9+I11) | J15: =J14/(J9+J11) | K15: =K14/(K9+K11) | ... T15: =T14/(T9+T11) | U15: 0.45 | V15: =U15 | W15: =W14/(W9+W11) | X15: =V15+5% | Y15: =X15 | Z15: =Z14/(Z9+Z11) | AA15: =Y15+5% | AB15: =AA15 | AC15: =AC14/(AC9+AC11) | AD15: =AB15+5% | AE15: =AD15 | AF15: =AF14/(AF9+AF11) | AG15: =AE15+5% | AH15: =AG15 | AI15: =AI14/(AI9+AI11)
B17: Closing Order Book | D17: =E17 | E17: 178.3 | F17: 220.5 | G17: =H17 | H17: 295.2 | I17: 367 | J17: =K17 | K17: 343.3 | L17: 395 | M17: =N17 | N17: 573.6 | O17: 394.3 | P17: =Q17 | Q17: 404.8 | R17: 279.7 | S17: =T17 | T17: 363.5 | U17: =U9+U11-U14 | V17: =V9+V11-V14 | W17: =W9+W11-W14 | X17: =X9+X11-X14 | Y17: =Y9+Y11-Y14 | Z17: =Z9+Z11-Z14 | AA17: =AA9+AA11-AA14 | AB17: =AB9+AB11-AB14 | ... AI17: =AI9+AI11-AI14
B20: Vessels
B21: Opening order book | D21: =C29 | F21: =E29 | G21: =F29 | H21: =E29 | I21: =H29 | J21: =I29 | K21: =H29 | L21: =K29 | M21: =L29 | N21: =K29 | O21: =N29 | P21: =O29 | Q21: =N29 | R21: =Q29 | S21: =R29 | T21: =Q29 | U21: =T29 | V21: =U29 | W21: =T29 | X21: =W29 | Y21: =X29 | Z21: =W29 | AA21: =Z29 | AB21: =AA29 | AC21: =Z29 | AD21: =AC29 | AE21: =AD29 | AF21: =AC29 | AG21: =AF29 | AH21: =AG29 | AI21: =AF29
B23: Order Inflow | C23: =C29-C21+C26 | D23: =D29-D21+D26 | E23: =E29-E21+E26 | F23: =F29-F21+F26 | G23: =G29-G21+G26 | H23: =H29-H21+H26 | I23: =I29-I21+I26 | J23: =J29-J21+J26 | ... S23: =S29-S21+S26 | T23: =R23+S23 | U23: =AVERAGE(MAX(L23,0),MAX(O23,0),MAX(R23,0))*(1+U24) | V23: =AVERAGE(MAX(M23,0),MAX(P23,0),MAX(S23,0))*(1+V24) | W23: =U23+V23 | X23: =AVERAGE(MAX(O23,0),MAX(R23,0),MAX(U23,0))*(1+X24) | Y23: =AVERAGE(MAX(P23,0),MAX(S23,0),MAX(V23,0))*(1+Y24) | Z23: =X23+Y23 | AA23: =AVERAGE(MAX(R23,0),MAX(U23,0),MAX(X23,0))*(1+AA24) | AB23: =AVERAGE(MAX(S23,0),MAX(V23,0),MAX(Y23,0))*(1+AB24) | AC23: =AA23+AB23 | AD23: =AVERAGE(MAX(U23,0),MAX(X23,0),MAX(AA23,0))*(1+AD24) | AE23: =AVERAGE(MAX(V23,0),MAX(Y23,0),MAX(AB23,0))*(1+AE24) | AF23: =AD23+AE23 | AG23: =AVERAGE(MAX(X23,0),MAX(AA23,0),MAX(AD23,0))*(1+AG24) | AH23: =AVERAGE(MAX(Y23,0),MAX(AB23,0),MAX(AE23,0))*(1+AH24) | AI23: =AG23+AH23
B24: Growth % | H24: =(H23-E23)/E23 | I24: =(I23-F23)/F23 | J24: =(J23-G23)/G23 | K24: =(K23-H23)/H23 | L24: =(L23-I23)/I23 | M24: =(M23-J23)/J23 | N24: =(N23-K23)/K23 | O24: =(O23-L23)/L23 | ... T24: =(T23-Q23)/Q23 | U24: 0.25 | V24: =U24 | W24: =(W23-T23)/T23 | X24: =U24+10% | Y24: =X24 | Z24: =(Z23-W23)/W23 | AA24: =X24+10% | AB24: =AA24 | AC24: =(AC23-Z23)/Z23 | AD24: =AA24+10% | AE24: =AD24 | AF24: =(AF23-AC23)/AC23 | AG24: =AD24+10% | AH24: =AG24 | AI24: =(AI23-AF23)/AF23
B26: Revenue Executed | D26: =E26-C26 | F26: 42.8 | G26: =H26-F26 | H26: 53.2 | I26: 29.2 | J26: =K26-I26 | K26: 44.5 | L26: =28.9*K26/(K26+K38) | M26: =N26-L26 | N26: 71.5 | O26: 33.3 | P26: =Q26-O26 | Q26: 130.5 | R26: 128.8 | S26: =T26-R26 | T26: 267.1 | U26: =U27*(U21+U23) | V26: =V27*(V21+V23) | W26: =U26+V26 | X26: =X27*(X21+X23) | Y26: =Y27*(Y21+Y23) | Z26: =X26+Y26 | AA26: =AA27*(AA21+AA23) | AB26: =AB27*(AB21+AB23) | AC26: =AA26+AB26 | AD26: =AD27*(AD21+AD23) | AE26: =AE27*(AE21+AE23) | AF26: =AD26+AE26 | AG26: =AG27*(AG21+AG23) | AH26: =AH27*(AH21+AH23) | AI26: =AG26+AH26
B27: Execution % | D27: =D26/(D21+D23) | E27: =E26/(E21+E23) | F27: =F26/(F21+F23) | G27: =G26/(G21+G23) | H27: =H26/(H21+H23) | I27: =I26/(I21+I23) | J27: =J26/(J21+J23) | K27: =K26/(K21+K23) | ... T27: =T26/(T21+T23) | U27: 0.3 | V27: =U27 | W27: =W26/(W21+W23) | X27: =V27+10% | Y27: =X27 | Z27: =Z26/(Z21+Z23) | AA27: =Y27+10% | AB27: =AA27 | AC27: =AC26/(AC21+AC23) | AD27: =AB27+10% | AE27: =AD27 | AF27: =AF26/(AF21+AF23) | AG27: =AE27+10% | AH27: =AG27 | AI27: =AI26/(AI21+AI23)
B29: Closing Order Book | D29: =E29 | E29: 56.8 | F29: 48.4 | G29: =H29 | H29: 63.3 | I29: 72 | J29: =K29 | K29: 89.5 | L29: =209*K29/(K29+K47) | M29: =N29 | N29: 98.3 | O29: 324.3 | P29: =Q29 | Q29: 234.3 | R29: 180.5 | S29: =T29 | T29: 272.5 | U29: =U21+U23-U26 | V29: =V21+V23-V26 | W29: =W21+W23-W26 | X29: =X21+X23-X26 | Y29: =Y21+Y23-Y26 | Z29: =Z21+Z23-Z26 | AA29: =AA21+AA23-AA26 | AB29: =AB21+AB23-AB26 | ... AI29: =AI21+AI23-AI26
B32: Towers & Reactors
B33: Opening order book | D33: =C41 | F33: =E41 | G33: =F41 | H33: =E41 | I33: =H41 | J33: =I41 | K33: =H41 | L33: =K41 | M33: =L41 | N33: =K41 | O33: =N41 | P33: =O41 | Q33: =N41 | R33: =Q41 | S33: =R41 | T33: =Q41 | U33: =T41 | V33: =U41 | W33: =T41 | X33: =W41 | Y33: =X41 | Z33: =W41 | AA33: =Z41 | AB33: =AA41 | AC33: =Z41 | AD33: =AC41 | AE33: =AD41 | AF33: =AC41 | AG33: =AF41 | AH33: =AG41 | AI33: =AF41
B35: Order Inflow | C35: =C41-C33+C38 | D35: =D41-D33+D38 | E35: =E41-E33+E38 | F35: =F41-F33+F38 | G35: =G41-G33+G38 | H35: =H41-H33+H38 | I35: =I41-I33+I38 | J35: =J41-J33+J38 | ... S35: =S41-S33+S38 | T35: =R35+S35 | U35: =AVERAGE(MAX(L35,0),MAX(O35,0),MAX(R35,0))*(1+U36) | V35: =AVERAGE(MAX(M35,0),MAX(P35,0),MAX(S35,0))*(1+V36) | W35: =U35+V35 | X35: =AVERAGE(MAX(O35,0),MAX(R35,0),MAX(U35,0))*(1+X36) | Y35: =AVERAGE(MAX(P35,0),MAX(S35,0),MAX(V35,0))*(1+Y36) | Z35: =X35+Y35 | AA35: =AVERAGE(MAX(R35,0),MAX(U35,0),MAX(X35,0))*(1+AA36) | AB35: =AVERAGE(MAX(S35,0),MAX(V35,0),MAX(Y35,0))*(1+AB36) | AC35: =AA35+AB35 | AD35: =AVERAGE(MAX(U35,0),MAX(X35,0),MAX(AA35,0))*(1+AD36) | AE35: =AVERAGE(MAX(V35,0),MAX(Y35,0),MAX(AB35,0))*(1+AE36) | AF35: =AD35+AE35 | AG35: =AVERAGE(MAX(X35,0),MAX(AA35,0),MAX(AD35,0))*(1+AG36) | AH35: =AVERAGE(MAX(Y35,0),MAX(AB35,0),MAX(AE35,0))*(1+AH36) | AI35: =AG35+AH35
B36: Growth % | H36: =(H35-E35)/E35 | I36: =(I35-F35)/F35 | J36: =(J35-G35)/G35 | K36: =(K35-H35)/H35 | L36: =(L35-I35)/I35 | M36: =(M35-J35)/J35 | N36: =(N35-K35)/K35 | O36: =(O35-L35)/L35 | ... T36: =(T35-Q35)/Q35 | U36: 0.1 | V36: =U36 | W36: =(W35-T35)/T35 | X36: =V36+10% | Y36: =X36 | Z36: =(Z35-W35)/W35 | AA36: =Y36+10% | AB36: =AA36 | AC36: =(AC35-Z35)/Z35 | AD36: =AB36+10% | AE36: =AD36 | AF36: =(AF35-AC35)/AC35 | AG36: =AE36+10% | AH36: =AG36 | AI36: =(AI35-AF35)/AF35
B38: Revenue Executed | D38: =E38-C38 | G38: =H38-F38 | H38: 22 | I38: 3.3 | J38: =K38-I38 | K38: 30.6 | L38: =28.9*K38/(K26+K38) | M38: =N38-L38 | N38: 49.7 | O38: 48.1 | P38: =Q38-O38 | Q38: 94.9 | R38: 24.5 | S38: =T38-R38 | T38: 49.9 | U38: =U39*(U33+U35) | V38: =V39*(V33+V35) | W38: =U38+V38 | X38: =X39*(X33+X35) | Y38: =Y39*(Y33+Y35) | Z38: =X38+Y38 | AA38: =AA39*(AA33+AA35) | AB38: =AB39*(AB33+AB35) | AC38: =AA38+AB38 | AD38: =AD39*(AD33+AD35) | AE38: =AE39*(AE33+AE35) | AF38: =AD38+AE38 | AG38: =AG39*(AG33+AG35) | AH38: =AH39*(AH33+AH35) | AI38: =AG38+AH38
B39: Execution % | F39: =F38/(F33+F35) | G39: =G38/(G33+G35) | H39: =H38/(H33+H35) | I39: =I38/(I33+I35) | J39: =J38/(J33+J35) | K39: =K38/(K33+K35) | L39: =L38/(L33+L35) | M39: =M38/(M33+M35) | ... T39: =T38/(T33+T35) | U39: 0.6 | V39: =U39 | W39: =W38/(W33+W35) | X39: =V39+5% | Y39: =X39 | Z39: =Z38/(Z33+Z35) | AA39: =Y39+5% | AB39: =AA39 | AC39: =AC38/(AC33+AC35) | AD39: =AB39+5% | AE39: =AD39 | AF39: =AF38/(AF33+AF35) | AG39: =AE39+5% | AH39: =AG39 | AI39: =AI38/(AI33+AI35)
B41: Closing Order Book | D41: =E41 | E41: 18 | F41: 27.8 | G41: =H41 | H41: 15.7 | I41: 93.2 | J41: =K41 | K41: 90.3 | L41: =209*K41/(K31+K41) | M41: =N41 | N41: 174 | O41: 151.5 | P41: =Q41 | Q41: 56 | R41: 33.9 | S41: =T41 | T41: 8.1 | U41: =U33+U35-U38 | V41: =V33+V35-V38 | W41: =W33+W35-W38 | X41: =X33+X35-X38 | Y41: =Y33+Y35-Y38 | Z41: =Z33+Z35-Z38 | AA41: =AA33+AA35-AA38 | AB41: =AB33+AB35-AB38 | ... AI41: =AI33+AI35-AI38
B44: Tank & Silos
B45: Opening order book | D45: =C53 | F45: =E53 | G45: =F53 | H45: =E53 | I45: =H53 | J45: =I53 | K45: =H53 | L45: =K53 | M45: =L53 | N45: =K53 | O45: =N53 | P45: =O53 | Q45: =N53 | R45: =Q53 | S45: =R53 | T45: =Q53 | U45: =T53 | V45: =U53 | W45: =T53 | X45: =W53 | Y45: =X53 | Z45: =W53 | AA45: =Z53 | AB45: =AA53 | AC45: =Z53 | AD45: =AC53 | AE45: =AD53 | AF45: =AC53 | AG45: =AF53 | AH45: =AG53 | AI45: =AF53
B47: Order Inflow | C47: =C53-C45+C50 | D47: =D53-D45+D50 | E47: =E53-E45+E50 | F47: =F53-F45+F50 | G47: =G53-G45+G50 | H47: =H53-H45+H50 | I47: =I53-I45+I50 | J47: =J53-J45+J50 | ... S47: =S53-S45+S50 | T47: =R47+S47 | U47: =AVERAGE(MAX(L47,0),MAX(O47,0),MAX(R47,0))*(1+U48) | V47: =AVERAGE(MAX(M47,0),MAX(P47,0),MAX(S47,0))*(1+V48) | W47: =U47+V47 | X47: =AVERAGE(MAX(O47,0),MAX(R47,0),MAX(U47,0))*(1+X48) | Y47: =AVERAGE(MAX(P47,0),MAX(S47,0),MAX(V47,0))*(1+Y48) | Z47: =X47+Y47 | AA47: =AVERAGE(MAX(R47,0),MAX(U47,0),MAX(X47,0))*(1+AA48) | AB47: =AVERAGE(MAX(S47,0),MAX(V47,0),MAX(Y47,0))*(1+AB48) | AC47: =AA47+AB47 | AD47: =AVERAGE(MAX(U47,0),MAX(X47,0),MAX(AA47,0))*(1+AD48) | AE47: =AVERAGE(MAX(V47,0),MAX(Y47,0),MAX(AB47,0))*(1+AE48) | AF47: =AD47+AE47 | AG47: =AVERAGE(MAX(X47,0),MAX(AA47,0),MAX(AD47,0))*(1+AG48) | AH47: =AVERAGE(MAX(Y47,0),MAX(AB47,0),MAX(AE47,0))*(1+AH48) | AI47: =AG47+AH47
B48: Growth % | S48: =(S47-P47)/P47 | T48: =(T47-Q47)/Q47 | U48: 0.15 | V48: =U48 | W48: =(W47-T47)/T47 | X48: =V48+10% | Y48: =X48 | Z48: =(Z47-W47)/W47 | AA48: =Y48+10% | AB48: =AA48 | AC48: =(AC47-Z47)/Z47 | AD48: =AB48+10% | AE48: =AD48 | AF48: =(AF47-AC47)/AC47 | AG48: =AE48+10% | AH48: =AG48 | AI48: =(AI47-AF47)/AF47
B50: Revenue Executed | D50: =E50-C50 | G50: =H50-F50 | J50: =K50-I50 | M50: =N50-L50 | P50: =Q50-O50 | R50: 3.2 | S50: =T50-R50 | T50: 26.3 | U50: =U51*(U45+U47) | V50: =V51*(V45+V47) | W50: =U50+V50 | X50: =X51*(X45+X47) | Y50: =Y51*(Y45+Y47) | Z50: =X50+Y50 | AA50: =AA51*(AA45+AA47) | AB50: =AB51*(AB45+AB47) | AC50: =AA50+AB50 | AD50: =AD51*(AD45+AD47) | AE50: =AE51*(AE45+AE47) | AF50: =AD50+AE50 | AG50: =AG51*(AG45+AG47) | AH50: =AH51*(AH45+AH47) | AI50: =AG50+AH50
B51: Execution % | R51: =R50/(R45+R47) | S51: =S50/(S45+S47) | T51: =T50/(T45+T47) | U51: 0.15 | V51: =U51 | W51: =W50/(W45+W47) | X51: =V51+15% | Y51: =X51 | Z51: =Z50/(Z45+Z47) | AA51: =Y51+15% | AB51: =AA51 | AC51: =AC50/(AC45+AC47) | AD51: =AB51+15% | AE51: =AD51 | AF51: =AF50/(AF45+AF47) | AG51: =AE51+15% | AH51: =AG51 | AI51: =AI50/(AI45+AI47)
B53: Closing Order Book | D53: =E53 | G53: =H53 | J53: =K53 | M53: =N53 | P53: =Q53 | Q53: 26.5 | R53: 67.7 | S53: =T53 | T53: 95.2 | U53: =U45+U47-U50 | V53: =V45+V47-V50 | W53: =W45+W47-W50 | X53: =X45+X47-X50 | Y53: =Y45+Y47-Y50 | Z53: =Z45+Z47-Z50 | AA53: =AA45+AA47-AA50 | AB53: =AB45+AB47-AB50 | ... AI53: =AI45+AI47-AI50
B56: Centrifuge & Others
B57: Opening order book | D57: =C65 | F57: =E65 | G57: =F65 | H57: =E65 | I57: =H65 | J57: =I65 | K57: =H65 | L57: =K65 | M57: =L65 | N57: =K65 | O57: =N65 | P57: =O65 | Q57: =N65 | R57: =Q65 | S57: =R65 | T57: =Q65 | U57: =T65 | V57: =U65 | W57: =T65 | X57: =W65 | Y57: =X65 | Z57: =W65 | AA57: =Z65 | AB57: =AA65 | AC57: =Z65 | AD57: =AC65 | AE57: =AD65 | AF57: =AC65 | AG57: =AF65 | AH57: =AG65 | AI57: =AF65
B59: Order Inflow | C59: =C65-C57+C62 | D59: =D65-D57+D62 | E59: =E65-E57+E62 | F59: =F65-F57+F62 | G59: =G65-G57+G62 | H59: =H65-H57+H62 | I59: =I65-I57+I62 | J59: =J65-J57+J62 | ... S59: =S65-S57+S62 | T59: =R59+S59 | U59: =AVERAGE(MAX(L59,0),MAX(O59,0),MAX(R59,0))*(1+U60) | V59: =AVERAGE(MAX(M59,0),MAX(P59,0),MAX(S59,0))*(1+V60) | W59: =U59+V59 | X59: =AVERAGE(MAX(O59,0),MAX(R59,0),MAX(U59,0))*(1+X60) | Y59: =AVERAGE(MAX(P59,0),MAX(S59,0),MAX(V59,0))*(1+Y60) | Z59: =X59+Y59 | AA59: =AVERAGE(MAX(R59,0),MAX(U59,0),MAX(X59,0))*(1+AA60) | AB59: =AVERAGE(MAX(S59,0),MAX(V59,0),MAX(Y59,0))*(1+AB60) | AC59: =AA59+AB59 | AD59: =AVERAGE(MAX(U59,0),MAX(X59,0),MAX(AA59,0))*(1+AD60) | AE59: =AVERAGE(MAX(V59,0),MAX(Y59,0),MAX(AB59,0))*(1+AE60) | AF59: =AD59+AE59 | AG59: =AVERAGE(MAX(X59,0),MAX(AA59,0),MAX(AD59,0))*(1+AG60) | AH59: =AVERAGE(MAX(Y59,0),MAX(AB59,0),MAX(AE59,0))*(1+AH60) | AI59: =AG59+AH59
B60: Growth % | H60: =(H59-E59)/E59 | I60: =(I59-F59)/F59 | J60: =(J59-G59)/G59 | K60: =(K59-H59)/H59 | L60: =(L59-I59)/I59 | M60: =(M59-J59)/J59 | N60: =(N59-K59)/K59 | O60: =(O59-L59)/L59 | ... T60: =(T59-Q59)/Q59 | U60: 0.15 | V60: =U60 | W60: =(W59-T59)/T59 | X60: =V60+10% | Y60: =X60 | Z60: =(Z59-W59)/W59 | AA60: =Y60+10% | AB60: =AA60 | AC60: =(AC59-Z59)/Z59 | AD60: =AB60+10% | AE60: =AD60 | AF60: =(AF59-AC59)/AC59 | AG60: =AE60+10% | AH60: =AG60 | AI60: =(AI59-AF59)/AF59
B62: Revenue Executed | D62: =E62-C62 | F62: 10.3 | G62: =H62-F62 | H62: 17.4 | I62: 4.4 | J62: =K62-I62 | K62: 30.3 | L62: 3.6 | M62: =N62-L62 | N62: 41.7 | O62: 14.6 | P62: =Q62-O62 | Q62: 15.3 | R62: 16.2 | S62: =T62-R62 | T62: 35.8 | U62: =U63*(U57+U59) | V62: =V63*(V57+V59) | W62: =U62+V62 | X62: =X63*(X57+X59) | Y62: =Y63*(Y57+Y59) | Z62: =X62+Y62 | AA62: =AA63*(AA57+AA59) | AB62: =AB63*(AB57+AB59) | AC62: =AA62+AB62 | AD62: =AD63*(AD57+AD59) | AE62: =AE63*(AE57+AE59) | AF62: =AD62+AE62 | AG62: =AG63*(AG57+AG59) | AH62: =AH63*(AH57+AH59) | AI62: =AG62+AH62
B63: Execution % | F63: =F62/(F57+F59) | G63: =G62/(G57+G59) | H63: =H62/(H57+H59) | I63: =I62/(I57+I59) | J63: =J62/(J57+J59) | K63: =K62/(K57+K59) | L63: =L62/(L57+L59) | M63: =M62/(M57+M59) | ... T63: =T62/(T57+T59) | U63: 0.4 | V63: =U63 | W63: =W62/(W57+W59) | X63: =V63+10% | Y63: =X63 | Z63: =Z62/(Z57+Z59) | AA63: =Y63+10% | AB63: =AA63 | AC63: =AC62/(AC57+AC59) | AD63: =AB63+10% | AE63: =AD63 | AF63: =AF62/(AF57+AF59) | AG63: =AE63+10% | AH63: =AG63 | AI63: =AI62/(AI57+AI59)
B65: Closing Order Book | D65: =E65 | E65: 2.9 | F65: 1.8 | G65: =H65 | H65: 19.1 | I65: 4 | J65: =K65 | K65: 6.9 | L65: 6.3 | M65: =N65 | N65: 8.2 | O65: 12.5 | P65: =Q65 | Q65: 19.7 | R65: 6.2 | S65: =T65 | T65: 29.6 | U65: =U57+U59-U62 | V65: =V57+V59-V62 | W65: =W57+W59-W62 | X65: =X57+X59-X62 | Y65: =Y57+Y59-Y62 | Z65: =Z57+Z59-Z62 | AA65: =AA57+AA59-AA62 | AB65: =AB57+AB59-AB62 | ... AI65: =AI57+AI59-AI62
B68: Order Book Total | C68: =C17+C29+C41+C53+C65 | D68: =D17+D29+D41+D53+D65 | E68: =E17+E29+E41+E53+E65 | F68: =F17+F29+F41+F53+F65 | G68: =G17+G29+G41+G53+G65 | H68: =H17+H29+H41+H53+H65 | I68: =I17+I29+I41+I53+I65 | J68: =J17+J29+J41+J53+J65 | ... AI68: =AI17+AI29+AI41+AI53+AI65
B69: Revenue Total | C69: =C14+C26+C38+C50+C62 | D69: =D14+D26+D38+D50+D62 | E69: =E14+E26+E38+E50+E62 | F69: =F14+F26+F38+F50+F62 | G69: =G14+G26+G38+G50+G62 | H69: =H14+H26+H38+H50+H62 | I69: =I14+I26+I38+I50+I62 | J69: =J14+J26+J38+J50+J62 | ... AI69: =AI14+AI26+AI38+AI50+AI62
B70: YoY Growth % | I70: =(I69-F69)/F69 | J70: =(J69-G69)/G69 | K70: =(K69-H69)/H69 | L70: =(L69-I69)/I69 | M70: =(M69-J69)/J69 | N70: =(N69-K69)/K69 | O70: =(O69-L69)/L69 | P70: =(P69-M69)/M69 | ... AI70: =(AI69-AF69)/AF69
B72: Geographical Bifurcation
B73: Domestic | D73: =E73-C73 | F73: 125.2 | G73: =H73-F73 | H73: 260.7 | I73: 121.4 | J73: =K73-I73 | K73: 332.6 | L73: 109 | M73: =N73-L73 | N73: 325.6 | O73: 163.6 | P73: =Q73-O73 | Q73: 265 | R73: 145.7 | S73: =T73-R73 | T73: 396.7 | U73: =U69*U74 | V73: =V69*V74 | W73: =U73+V73 | X73: =X69*X74 | Y73: =Y69*Y74 | Z73: =X73+Y73 | AA73: =AA69*AA74 | AB73: =AB69*AB74 | AC73: =AA73+AB73 | AD73: =AD69*AD74 | AE73: =AE69*AE74 | AF73: =AD73+AE73 | AG73: =AG69*AG74 | AH73: =AH69*AH74 | AI73: =AG73+AH73
B74: % of Total Revenue | C74: =C73/'Income Statement'!C8 | D74: =D73/'Income Statement'!D8 | E74: =E73/'Income Statement'!E8 | F74: =F73/'Income Statement'!F8 | G74: =G73/'Income Statement'!G8 | H74: =H73/'Income Statement'!H8 | I74: =I73/'Income Statement'!I8 | J74: =J73/'Income Statement'!J8 | ... T74: =T73/'Income Statement'!T8 | U74: 0.59 | V74: =U74 | W74: =W73/W$69 | X74: =V74 | Y74: =X74 | Z74: =Z73/Z$69 | AA74: =Y74 | AB74: =AA74 | AC74: =AC73/AC$69 | AD74: =AB74 | AE74: =AD74 | AF74: =AF73/AF$69 | AG74: =AE74 | AH74: =AG74 | AI74: =AI73/AI$69
B75: Growth % | I75: =(I73-F73)/F73 | J75: =(J73-G73)/G73 | K75: =(K73-H73)/H73 | L75: =(L73-I73)/I73 | M75: =(M73-J73)/J73 | N75: =(N73-K73)/K73 | O75: =(O73-L73)/L73 | P75: =(P73-M73)/M73 | ... T75: =(T73-Q73)/Q73
B77: Export | D77: =E77-C77 | F77: 15.9 | G77: =H77-F77 | H77: 27.5 | I77: 31.3 | J77: =K77-I77 | K77: 78.7 | L77: 121.6 | M77: =N77-L77 | N77: 171.8 | O77: 158.8 | P77: =Q77-O77 | Q77: 380.2 | R77: 231.1 | S77: =T77-R77 | T77: 395.1 | U77: =U69*U78 | V77: =V69*V78 | W77: =U77+V77 | X77: =X69*X78 | Y77: =Y69*Y78 | Z77: =X77+Y77 | AA77: =AA69*AA78 | AB77: =AB69*AB78 | AC77: =AA77+AB77 | AD77: =AD69*AD78 | AE77: =AE69*AE78 | AF77: =AD77+AE77 | AG77: =AG69*AG78 | AH77: =AH69*AH78 | AI77: =AG77+AH77
B78: % of Total Revenue | C78: =C77/'Income Statement'!C8 | D78: =D77/'Income Statement'!D8 | E78: =E77/'Income Statement'!E8 | F78: =F77/'Income Statement'!F8 | G78: =G77/'Income Statement'!G8 | H78: =H77/'Income Statement'!H8 | I78: =I77/'Income Statement'!I8 | J78: =J77/'Income Statement'!J8 | ... T78: =T77/'Income Statement'!T8 | U78: 0.38 | V78: =U78 | W78: =W77/W$69 | X78: =V78 | Y78: =X78 | Z78: =Z77/Z$69 | AA78: =Y78 | AB78: =AA78 | AC78: =AC77/AC$69 | AD78: =AB78 | AE78: =AD78 | AF78: =AF77/AF$69 | AG78: =AE78 | AH78: =AG78 | AI78: =AI77/AI$69
B79: Growth % | I79: =(I77-F77)/F77 | J79: =(J77-G77)/G77 | K79: =(K77-H77)/H77 | L79: =(L77-I77)/I77 | M79: =(M77-J77)/J77 | N79: =(N77-K77)/K77 | O79: =(O77-L77)/L77 | P79: =(P77-M77)/M77 | ... T79: =(T77-Q77)/Q77
B81: DE/SEZ | D81: =E81-C81 | G81: =H81-F81 | J81: =K81-I81 | L81: 6.8 | M81: =N81-L81 | N81: 53 | O81: 16.7 | P81: =Q81-O81 | Q81: 63.1 | R81: 30.7 | S81: =T81-R81 | T81: 30.5 | U81: =U69*U82 | V81: =V69*V82 | W81: =U81+V81 | X81: =X69*X82 | Y81: =Y69*Y82 | Z81: =X81+Y81 | AA81: =AA69*AA82 | AB81: =AB69*AB82 | AC81: =AA81+AB81 | AD81: =AD69*AD82 | AE81: =AE69*AE82 | AF81: =AD81+AE81 | AG81: =AG69*AG82 | AH81: =AH69*AH82 | AI81: =AG81+AH81
B82: % of Total Revenue | C82: =C81/'Income Statement'!C8 | D82: =D81/'Income Statement'!D8 | E82: =E81/'Income Statement'!E8 | F82: =F81/'Income Statement'!F8 | G82: =G81/'Income Statement'!G8 | H82: =H81/'Income Statement'!H8 | I82: =I81/'Income Statement'!I8 | J82: =J81/'Income Statement'!J8 | ... T82: =T81/'Income Statement'!T8 | U82: =1-U74-U78 | V82: =U82 | W82: =W81/W$69 | X82: =V82 | Y82: =X82 | Z82: =Z81/Z$69 | AA82: =Y82 | AB82: =AA82 | AC82: =AC81/AC$69 | AD82: =AB82 | AE82: =AD82 | AF82: =AF81/AF$69 | AG82: =AE82 | AH82: =AG82 | AI82: =AI81/AI$69
B83: Growth % | O83: =(O81-L81)/L81 | P83: =(P81-M81)/M81 | Q83: =(Q81-N81)/N81 | R83: =(R81-O81)/O81 | S83: =(S81-P81)/P81 | T83: =(T81-Q81)/Q81
B85: Total | C85: =C73+C77+C81 | D85: =D73+D77+D81 | E85: =E73+E77+E81 | F85: =F73+F77+F81 | G85: =G73+G77+G81 | H85: =H73+H77+H81 | I85: =I73+I77+I81 | J85: =J73+J77+J81 | ... V85: =V73+V77+V81 | W85: =U85+V85 | X85: =X73+X77+X81 | Y85: =Y73+Y77+Y81 | Z85: =X85+Y85 | AA85: =AA73+AA77+AA81 | AB85: =AB73+AB77+AB81 | AC85: =AA85+AB85 | AD85: =AD73+AD77+AD81 | AE85: =AE73+AE77+AE81 | AF85: =AD85+AE85 | AG85: =AG73+AG77+AG81 | AH85: =AH73+AH77+AH81 | AI85: =AG85+AH85
B88: Estimated Export Regional Split (for Risk Analysis)
B89: Middle East Revenue | U89: =U77*U90 | V89: =V77*V90 | W89: =U89+V89 | X89: =X77*X90 | Y89: =Y77*Y90 | Z89: =X89+Y89 | AA89: =AA77*AA90 | AB89: =AB77*AB90 | AC89: =AA89+AB89 | AD89: =AD77*AD90 | AE89: =AE77*AE90 | AF89: =AD89+AE89 | AG89: =AG77*AG90 | AH89: =AH77*AH90 | AI89: =AG89+AH89
B90: % of Exports | U90: 0.4 | V90: =U90 | W90: =W89/W77 | X90: =V90 | Y90: =X90 | Z90: =Z89/Z77 | AA90: =Y90 | AB90: =AA90 | AC90: =AC89/AC77 | AD90: =AB90 | AE90: =AD90 | AF90: =AF89/AF77 | AG90: =AE90 | AH90: =AG90 | AI90: =AI89/AI77
B92: USA Revenue | U92: =U77*U93 | V92: =V77*V93 | W92: =U92+V92 | X92: =X77*X93 | Y92: =Y77*Y93 | Z92: =X92+Y92 | AA92: =AA77*AA93 | AB92: =AB77*AB93 | AC92: =AA92+AB92 | AD92: =AD77*AD93 | AE92: =AE77*AE93 | AF92: =AD92+AE92 | AG92: =AG77*AG93 | AH92: =AH77*AH93 | AI92: =AG92+AH92
B93: % of Exports | U93: 0.25 | V93: =U93 | W93: =W92/W77 | X93: =V93 | Y93: =X93 | Z93: =Z92/Z77 | AA93: =Y93 | AB93: =AA93 | AC93: =AC92/AC77 | AD93: =AB93 | AE93: =AD93 | AF93: =AF92/AF77 | AG93: =AE93 | AH93: =AG93 | AI93: =AI92/AI77
B95: Other Regions (Europe, Africa, SE Asia) Revenue | U95: =U77*U96 | V95: =V77*V96 | W95: =U95+V95 | X95: =X77*X96 | Y95: =Y77*Y96 | Z95: =X95+Y95 | AA95: =AA77*AA96 | AB95: =AB77*AB96 | AC95: =AA95+AB95 | AD95: =AD77*AD96 | AE95: =AE77*AE96 | AF95: =AD95+AE95 | AG95: =AG77*AG96 | AH95: =AH77*AH96 | AI95: =AG95+AH95
B96: % of Exports | U96: =1-U90-U93 | V96: =1-V90-V93 | W96: =W95/W77 | X96: =1-X90-X93 | Y96: =1-Y90-Y93 | Z96: =Z95/Z77 | AA96: =1-AA90-AA93 | AB96: =1-AB90-AB93 | AC96: =AC95/AC77 | AD96: =1-AD90-AD93 | AE96: =1-AE90-AE93 | AF96: =AF95/AF77 | AG96: =1-AG90-AG93 | AH96: =1-AH90-AH93 | AI96: =AI95/AI77
B98: Middle East % of Total Revenue | U98: =U89/U69 | V98: =V89/V69 | W98: =W89/W69 | X98: =X89/X69 | Y98: =Y89/Y69 | Z98: =Z89/Z69 | AA98: =AA89/AA69 | AB98: =AB89/AB69 | ... AI98: =AI89/AI69
B101: Risk Analysis (95% Confidence)
B102: Currency CVaR (USD/INR Risk on all Exports) | U102: =U77*'Risk Data'!$M$3*'Risk Data'!$M$10 | V102: =V77*'Risk Data'!$M$3*'Risk Data'!$M$10 | W102: =W77*'Risk Data'!$M$3*'Risk Data'!$M$10 | X102: =X77*'Risk Data'!$M$3*'Risk Data'!$M$10 | Y102: =Y77*'Risk Data'!$M$3*'Risk Data'!$M$10 | Z102: =Z77*'Risk Data'!$M$3*'Risk Data'!$M$10 | AA102: =AA77*'Risk Data'!$M$3*'Risk Data'!$M$10 | AB102: =AB77*'Risk Data'!$M$3*'Risk Data'!$M$10 | ... AI102: =AI77*'Risk Data'!$M$3*'Risk Data'!$M$10
B103: Geopolitical CVaR (ME Exposure with Brent Crude as proxy) | U103: =U89*'Risk Data'!$M$4*'Risk Data'!$M$10 | V103: =V89*'Risk Data'!$M$4*'Risk Data'!$M$10 | W103: =W89*'Risk Data'!$M$4*'Risk Data'!$M$10 | X103: =X89*'Risk Data'!$M$4*'Risk Data'!$M$10 | Y103: =Y89*'Risk Data'!$M$4*'Risk Data'!$M$10 | Z103: =Z89*'Risk Data'!$M$4*'Risk Data'!$M$10 | AA103: =AA89*'Risk Data'!$M$4*'Risk Data'!$M$10 | AB103: =AB89*'Risk Data'!$M$4*'Risk Data'!$M$10 | ... AI103: =AI89*'Risk Data'!$M$4*'Risk Data'!$M$10
B105: Combined CVaR (Markowitz Portfolio Formula) | U105: =SQRT(U102^2+U103^2+2*'Risk Data'!$M$6*'Revenue Segments'!U102*'Revenue Segments'!U103) | V105: =SQRT(V102^2+V103^2+2*'Risk Data'!$M$6*'Revenue Segments'!V102*'Revenue Segments'!V103) | W105: =SQRT(W102^2+W103^2+2*'Risk Data'!$M$6*'Revenue Segments'!W102*'Revenue Segments'!W103) | X105: =SQRT(X102^2+X103^2+2*'Risk Data'!$M$6*'Revenue Segments'!X102*'Revenue Segments'!X103) | Y105: =SQRT(Y102^2+Y103^2+2*'Risk Data'!$M$6*'Revenue Segments'!Y102*'Revenue Segments'!Y103) | Z105: =SQRT(Z102^2+Z103^2+2*'Risk Data'!$M$6*'Revenue Segments'!Z102*'Revenue Segments'!Z103) | AA105: =SQRT(AA102^2+AA103^2+2*'Risk Data'!$M$6*'Revenue Segments'!AA102*'Revenue Segments'!AA103) | AB105: =SQRT(AB102^2+AB103^2+2*'Risk Data'!$M$6*'Revenue Segments'!AB102*'Revenue Segments'!AB103) | ... AI105: =SQRT(AI102^2+AI103^2+2*'Risk Data'!$M$6*'Revenue Segments'!AI102*'Revenue Segments'!AI103)
B106: Combined CVaR as % of Total Revenue | U106: =U105/U69 | V106: =V105/V69 | W106: =W105/W69 | X106: =X105/X69 | Y106: =Y105/Y69 | Z106: =Z105/Z69 | AA106: =AA105/AA69 | AB106: =AB105/AB69 | ... AI106: =AI105/AI69
B108: Steel Price Risk Analysis
B109: Steel Exposure | U109: ='Income Statement'!U14*65% | V109: ='Income Statement'!V14*65% | W109: ='Income Statement'!W14*65% | X109: ='Income Statement'!X14*65% | Y109: ='Income Statement'!Y14*65% | Z109: ='Income Statement'!Z14*65% | AA109: ='Income Statement'!AA14*65% | AB109: ='Income Statement'!AB14*65% | ... AI109: ='Income Statement'!AI14*65%
B110: Steel CVaR | U110: =U109*'Risk Data'!$M$5*'Risk Data'!$M$10 | V110: =V109*'Risk Data'!$M$5*'Risk Data'!$M$10 | W110: =W109*'Risk Data'!$M$5*'Risk Data'!$M$10 | X110: =X109*'Risk Data'!$M$5*'Risk Data'!$M$10 | Y110: =Y109*'Risk Data'!$M$5*'Risk Data'!$M$10 | Z110: =Z109*'Risk Data'!$M$5*'Risk Data'!$M$10 | AA110: =AA109*'Risk Data'!$M$5*'Risk Data'!$M$10 | AB110: =AB109*'Risk Data'!$M$5*'Risk Data'!$M$10 | ... AI110: =AI109*'Risk Data'!$M$5*'Risk Data'!$M$10
B111: Steel CVaR as % of EBITDA | U111: =U110/'Income Statement'!U23 | V111: =V110/'Income Statement'!V23 | W111: =W110/'Income Statement'!W23 | X111: =X110/'Income Statement'!X23 | Y111: =Y110/'Income Statement'!Y23 | Z111: =Z110/'Income Statement'!Z23 | AA111: =AA110/'Income Statement'!AA23 | AB111: =AB110/'Income Statement'!AB23 | ... AI111: =AI110/'Income Statement'!AI23
B113: Stress Scenarios
B114: Base Case | C114: =C69 | D114: =D69 | E114: =E69 | F114: =F69 | G114: =G69 | H114: =H69 | I114: =I69 | J114: =J69 | ... AI114: =AI69
B116: Moderate Case
B117: ME Order deferral % | E117: 0.2 | U117: =$E$117*U89 | V117: =$E$117*V89 | W117: =U117+V117 | X117: =$E$117*X89 | Y117: =$E$117*Y89 | Z117: =X117+Y117 | AA117: =$E$117*AA89 | AB117: =$E$117*AB89 | AC117: =AA117+AB117 | AD117: =$E$117*AD89 | AE117: =$E$117*AE89 | AF117: =AD117+AE117 | AG117: =$E$117*AG89 | AH117: =$E$117*AH89 | AI117: =AG117+AH117
B118: US Tariff Impact | E118: 0.1 | U118: =$E$118*U92 | V118: =$E$118*V92 | W118: =U118+V118 | X118: =$E$118*X92 | Y118: =$E$118*Y92 | Z118: =X118+Y118 | AA118: =$E$118*AA92 | AB118: =$E$118*AB92 | AC118: =AA118+AB118 | AD118: =$E$118*AD92 | AE118: =$E$118*AE92 | AF118: =AD118+AE118 | AG118: =$E$118*AG92 | AH118: =$E$118*AH92 | AI118: =AG118+AH118
B119: Adjusted Revenue | U119: =U114-U117-U118 | V119: =V114-V117-V118 | W119: =U119+V119 | X119: =X114-X117-X118 | Y119: =Y114-Y117-Y118 | Z119: =X119+Y119 | AA119: =AA114-AA117-AA118 | AB119: =AB114-AB117-AB118 | AC119: =AA119+AB119 | AD119: =AD114-AD117-AD118 | AE119: =AE114-AE117-AE118 | AF119: =AD119+AE119 | AG119: =AG114-AG117-AG118 | AH119: =AH114-AH117-AH118 | AI119: =AG119+AH119
B120: % Variance Vs Base | U120: =IFERROR((U119-U114)/U114,0) | V120: =IFERROR((V119-V114)/V114,0) | W120: =IFERROR((W119-W114)/W114,0) | X120: =IFERROR((X119-X114)/X114,0) | Y120: =IFERROR((Y119-Y114)/Y114,0) | Z120: =IFERROR((Z119-Z114)/Z114,0) | AA120: =IFERROR((AA119-AA114)/AA114,0) | AB120: =IFERROR((AB119-AB114)/AB114,0) | ... AI120: =IFERROR((AI119-AI114)/AI114,0)
B122: Severe Case
B123: ME Order deferral % | E123: 0.4 | U123: =$E$123*U89 | V123: =$E$123*V89 | X123: =$E$123*X89 | Y123: =$E$123*Y89 | AA123: =$E$123*AA89 | AB123: =$E$123*AB89 | AD123: =$E$123*AD89 | AE123: =$E$123*AE89 | AG123: =$E$123*AG89 | AH123: =$E$123*AH89
B124: US Tariff Impact | E124: 0.25 | U124: =$E$124*U92 | V124: =$E$124*V92 | X124: =$E$124*X92 | Y124: =$E$124*Y92 | AA124: =$E$124*AA92 | AB124: =$E$124*AB92 | AD124: =$E$124*AD92 | AE124: =$E$124*AE92 | AG124: =$E$124*AG92 | AH124: =$E$124*AH92
B125: Adverse FX impact on all exports | E125: 0.1 | U125: =$E$125*U77 | V125: =$E$125*V77 | X125: =$E$125*X77 | Y125: =$E$125*Y77 | AA125: =$E$125*AA77 | AB125: =$E$125*AB77 | AD125: =$E$125*AD77 | AE125: =$E$125*AE77 | AG125: =$E$125*AG77 | AH125: =$E$125*AH77
B126: Adjusted Revenue | U126: =U114-SUM(U123:U125) | V126: =V114-SUM(V123:V125) | W126: =U126+V126 | X126: =X114-SUM(X123:X125) | Y126: =Y114-SUM(Y123:Y125) | Z126: =X126+Y126 | AA126: =AA114-SUM(AA123:AA125) | AB126: =AB114-SUM(AB123:AB125) | AC126: =AA126+AB126 | AD126: =AD114-SUM(AD123:AD125) | AE126: =AE114-SUM(AE123:AE125) | AF126: =AD126+AE126 | AG126: =AG114-SUM(AG123:AG125) | AH126: =AH114-SUM(AH123:AH125) | AI126: =AG126+AH126
B127: % Variance Vs Base | U127: =IFERROR((U126-U114)/U114,0) | V127: =IFERROR((V126-V114)/V114,0) | W127: =IFERROR((W126-W114)/W114,0) | X127: =IFERROR((X126-X114)/X114,0) | Y127: =IFERROR((Y126-Y114)/Y114,0) | Z127: =IFERROR((Z126-Z114)/Z114,0) | AA127: =IFERROR((AA126-AA114)/AA114,0) | AB127: =IFERROR((AB126-AB114)/AB114,0) | ... AI127: =IFERROR((AI126-AI114)/AI114,0)

Sheet DCF Model
B1: Anup Engineering Limited
B2: Fiscal year ending 31st Mar, 2026
B3: All amounts in ₹ crores except per share data
B5: WACC Calculation
B6: COST OF EQUITY
B7: Risk Free Rate (Rf) | C7: =Beta!AA6
B8: Equity Risk Premium (ERP) | C8: =Beta!AA7
B9: Beta (Weekly) | C9: =Beta!AA4
B10: Cost of Equity (Ke) | C10: =C7+C9*C8
B12: COST OF DEBT
B13: Debt Outstanding (closing Balance) | C13: =SUM('Balance Sheet'!T13,'Balance Sheet'!T19)
B14: Debt Outstanding (Opening Balance) | C14: =SUM('Balance Sheet'!T13,'Balance Sheet'!T19)
B15: Interest Expense for the year | C15: ='Income Statement'!T31
B16: Interest Rate | C16: =C15/C13
B17: Tax Rate | C17: =Guidance!C19
B18: Cost of Debt (Kd) | C18: =C16*(1-C17)
B20: No. of Outstanding Shares | C20: ='Income Statement'!T48
B21: MPS | C21: ='Income Statement'!T50
B22: Market Value of Equity (Rs crores) | C22: =C20*C21
B24: WACC
B25: Total Capital | C25: =C22+C13
B26: Debt (%) | C26: =C13/C25
B27: Equity (%) | C27: =1-C26
B28: WACC | C28: =(C10*C27)+(C18*C26)
B30: CASE SCENARIOS | C30: 0.05
B31: Conservative | C31: 0.04 | D31: Indian GDP Growth + Inflation
B32: Base | C32: 0.05 | D32: Capital Goods Sector Long Term Growth
B33: Aggressive | C33: 0.06 | D33: Premium for Nuclear & Hydrogen Expansion
B34: Terminal Growth Rate | C34: =C30
H35: Terminal Value
B36: Discounted Cash Flow | D36: FY2027 E | E36: FY2028 E | F36: FY2029 E | G36: FY2030 E | H36: FY2031 E
B37: Year Fraction | C37: =TODAY() | D37: =(DATE(2027,3,31)-$C$37)/365 | E37: =(DATE(2028,3,31)-$C$37)/365 | F37: =(DATE(2029,3,31)-$C$37)/365 | G37: =(DATE(2030,3,31)-$C$37)/365 | H37: =(DATE(2031,3,31)-$C$37)/365
B38: EBIT | D38: ='Income Statement'!W27 | E38: ='Income Statement'!Z27 | F38: ='Income Statement'!AC27 | G38: ='Income Statement'!AF27 | H38: ='Income Statement'!AI27
B39: Less:Cash Taxes | D39: =D38*$C$17 | E39: =E38*$C$17 | F39: =F38*$C$17 | G39: =G38*$C$17 | H39: =H38*$C$17
B40: NOPAT | D40: =D38-D39 | E40: =E38-E39 | F40: =F38-F39 | G40: =G38-G39 | H40: =H38-H39
B41: Add: D&A | D41: ='Balance Sheet'!W63 | E41: ='Balance Sheet'!Z63 | F41: ='Balance Sheet'!AC63 | G41: ='Balance Sheet'!AF63 | H41: ='Balance Sheet'!AI63
B42: Less: Capex | D42: =-'Balance Sheet'!W64 | E42: =-'Balance Sheet'!Z64 | F42: =-'Balance Sheet'!AC64 | G42: =-'Balance Sheet'!AF64 | H42: =-'Balance Sheet'!AI64
B43: Less: Changes in NWC | D43: =-('Balance Sheet'!W96) | E43: =-'Balance Sheet'!Z96 | F43: =-'Balance Sheet'!AC96 | G43: =-'Balance Sheet'!AF96 | H43: =-'Balance Sheet'!AI96
B44: FCF | D44: =SUM(D40:D43) | E44: =SUM(E40:E43) | F44: =SUM(F40:F43) | G44: =SUM(G40:G43) | H44: =SUM(H40:H43)
B45: Terminal value | H45: =(H44*(1+C34))/($C$28-C34)
B46: Total FCF | D46: =D44+D45 | E46: =E44+E45 | F46: =F44+F45 | G46: =G44+G45 | H46: =H44+H45
B47: Discounting Rate(%) | D47: =$C28 | E47: =$C28 | F47: =$C28 | G47: =$C28 | H47: =$C28
B48: Discounting Factor | D48: =1/(1+D47)^D37 | E48: =1/(1+E47)^E37 | F48: =1/(1+F47)^F37 | G48: =1/(1+G47)^G37 | H48: =1/(1+H47)^H37
B49: PV of FCF | D49: =D46*D48 | E49: =E46*E48 | F49: =F46*F48 | G49: =G46*G48 | H49: =H46*H48
B51: DCF Value of Firm/ Operating Business Enterprise Value | C51: =SUM(D49:H49) | E51: SENSITIVITY ANALYSIS
B52: Total Value of the Firm | C52: =SUM(C51) | E52: WACC
B53: Less: Gross Debt & Debt Equivalents | C53: =C13 | E53: LTGR | F53: =C56 | G53: =H53-1% | H53: =I53-1% | I53: 0.12337048 | J53: =I53+1% | K53: =J53+1%
B54: Add: Cash | C54: ='Balance Sheet'!T49+'Balance Sheet'!T50 | F54: =F55-1% | H54: 1360.6277 | I54: 1199.0916 | J54: 1069.189 | K54: 962.53323
B55: DCF Value of Common Equity | C55: =C52-C53+C54 | F55: =F56-1% | G55: 1779.0981 | H55: 1516.6973 | I55: 1317.7153 | J55: 1161.7561 | K55: 1036.3171
B56: DCF Value Per Share | C56: =C55/C20 | F56: =C30 | G56: 2071.0108 | H56: 1722.0231 | I56: 1468.6745 | J56: 1276.5294 | K56: 1125.9056
B57: Relative Value Per Share | C57: ='Peer Comps'!C17 | F57: =F56+1% | G57: 2497.5369 | H57: 2004.2925 | I57: 1667.2771 | J57: 1422.5886 | K57: 1236.9856
B58: Average Blended Target Price | C58: =AVERAGE(C56:C57) | F58: =F57+1% | G58: 3179.6939 | H58: 2416.7285 | I58: 1940.3038 | J58: 1614.7448 | K58: 1378.3449
B59: CMP a/o 16 October, 2026 | C59: 1488.5
B60: % Upside to current market price | C60: =C58/C59-1

Sheet Monte-Carlo
A1: Monte Carlo Simulation — DCF Value per Share
A2: Anup Engineering Limited | ₹ crores except per-share | Press F9 to run a new simulation
A4: DISTRIBUTION ASSUMPTIONS | H4: SIMULATION RESULTS (₹ / share)
A5: Variable | B5: Mean | C5: Std Dev | D5: Distribution | H5: Trials | I5: =COUNT($E$23:$E$1022)
A6: WACC | B6: ='DCF Model'!C28 | C6: 0.01 | D6: Normal | H6: Mean | I6: =AVERAGE($E$23:$E$1022)
A7: Terminal Growth Rate | B7: ='DCF Model'!C34 | C7: 0.0075 | D7: Normal | H7: Median | I7: =MEDIAN($E$23:$E$1022)
A8: FCF Performance Multiplier | B8: 1 | C8: 0.1 | D8: Normal | H8: Std Dev | I8: =_xlfn.STDEV.S($E$23:$E$1022)
A9: Number of Trials | B9: 1000 | H9: Minimum | I9: =MIN($E$23:$E$1022)
H10: Maximum | I10: =MAX($E$23:$E$1022)
A11: BASE CASE (linked from DCF Model) | H11: P5 (5th pctile) | I11: =_xlfn.PERCENTILE.INC($E$23:$E$1022,0.05)
B12: FY2027E | C12: FY2028E | D12: FY2029E | E12: FY2030E | F12: FY2031E | H12: P25 | I12: =_xlfn.PERCENTILE.INC($E$23:$E$1022,0.25)
A13: FCF (₹ cr) | B13: ='DCF Model'!D44 | C13: ='DCF Model'!E44 | D13: ='DCF Model'!F44 | E13: ='DCF Model'!G44 | F13: ='DCF Model'!H44 | H13: P75 | I13: =_xlfn.PERCENTILE.INC($E$23:$E$1022,0.75)
A14: Year Fraction | B14: ='DCF Model'!D37 | C14: ='DCF Model'!E37 | D14: ='DCF Model'!F37 | E14: ='DCF Model'!G37 | F14: ='DCF Model'!H37 | H14: P95 (95th pctile) | I14: =_xlfn.PERCENTILE.INC($E$23:$E$1022,0.95)
A15: Gross Debt (₹ cr) | B15: ='DCF Model'!C53 | H15: Base Value / Share | I15: =B18
A16: Cash (₹ cr) | B16: ='DCF Model'!C54 | H16: CMP | I16: =B19
A17: Shares Outstanding (cr) | B17: ='DCF Model'!C20 | H17: P(Value > CMP) | I17: =COUNTIF($E$23:$E$1022,">"&B19)/I5
A18: Base Value / Share (₹) | B18: ='DCF Model'!C56 | H18: Mean Upside vs CMP | I18: =I6/I16-1
A19: CMP (5 Jun 26, ₹) | B19: ='DCF Model'!C59
A21: SIMULATION TRIALS | H21: HISTOGRAM
A22: Trial | B22: WACC | C22: Term. Growth | D22: FCF Mult. | E22: Value / Share (₹) | H22: Value ≤ (₹) | I22: Frequency
A23: =ROW()-22 | B23: =_xlfn.NORM.INV(RAND(),$B$6,$C$6) | C23: =MIN(_xlfn.NORM.INV(RAND(),$B$7,$C$7),B23-0.005) | D23: =_xlfn.NORM.INV(RAND(),$B$8,$C$8) | E23: {=(SUMPRODUCT($B$13:$F$13*D23/(1+B23)^$B$14:$F$14)+($F$13*D23*(1+C23))/(B23-C23)/(1+B23)^$F$14-$B$15+$B$16)/$B$17} | H23: =$I$9+($I$10-$I$9)/12*(ROW()-22) | I23: {=FREQUENCY($E$23:$E$1022,$H$23:$H$34)}
A24: =ROW()-22 | B24: =_xlfn.NORM.INV(RAND(),$B$6,$C$6) | C24: =MIN(_xlfn.NORM.INV(RAND(),$B$7,$C$7),B24-0.005) | D24: =_xlfn.NORM.INV(RAND(),$B$8,$C$8) | E24: {=(SUMPRODUCT($B$13:$F$13*D24/(1+B24)^$B$14:$F$14)+($F$13*D24*(1+C24))/(B24-C24)/(1+B24)^$F$14-$B$15+$B$16)/$B$17} | H24: =$I$9+($I$10-$I$9)/12*(ROW()-22)
A25: =ROW()-22 | B25: =_xlfn.NORM.INV(RAND(),$B$6,$C$6) | C25: =MIN(_xlfn.NORM.INV(RAND(),$B$7,$C$7),B25-0.005) | D25: =_xlfn.NORM.INV(RAND(),$B$8,$C$8) | E25: {=(SUMPRODUCT($B$13:$F$13*D25/(1+B25)^$B$14:$F$14)+($F$13*D25*(1+C25))/(B25-C25)/(1+B25)^$F$14-$B$15+$B$16)/$B$17} | H25: =$I$9+($I$10-$I$9)/12*(ROW()-22)
A26: =ROW()-22 | B26: =_xlfn.NORM.INV(RAND(),$B$6,$C$6) | C26: =MIN(_xlfn.NORM.INV(RAND(),$B$7,$C$7),B26-0.005) | D26: =_xlfn.NORM.INV(RAND(),$B$8,$C$8) | E26: {=(SUMPRODUCT($B$13:$F$13*D26/(1+B26)^$B$14:$F$14)+($F$13*D26*(1+C26))/(B26-C26)/(1+B26)^$F$14-$B$15+$B$16)/$B$17} | H26: =$I$9+($I$10-$I$9)/12*(ROW()-22)
A27: =ROW()-22 | B27: =_xlfn.NORM.INV(RAND(),$B$6,$C$6) | C27: =MIN(_xlfn.NORM.INV(RAND(),$B$7,$C$7),B27-0.005) | D27: =_xlfn.NORM.INV(RAND(),$B$8,$C$8) | E27: {=(SUMPRODUCT($B$13:$F$13*D27/(1+B27)^$B$14:$F$14)+($F$13*D27*(1+C27))/(B27-C27)/(1+B27)^$F$14-$B$15+$B$16)/$B$17} | H27: =$I$9+($I$10-$I$9)/12*(ROW()-22)
A28: =ROW()-22 | B28: =_xlfn.NORM.INV(RAND(),$B$6,$C$6) | C28: =MIN(_xlfn.NORM.INV(RAND(),$B$7,$C$7),B28-0.005) | D28: =_xlfn.NORM.INV(RAND(),$B$8,$C$8) | E28: {=(SUMPRODUCT($B$13:$F$13*D28/(1+B28)^$B$14:$F$14)+($F$13*D28*(1+C28))/(B28-C28)/(1+B28)^$F$14-$B$15+$B$16)/$B$17} | H28: =$I$9+($I$10-$I$9)/12*(ROW()-22)
A29: =ROW()-22 | B29: =_xlfn.NORM.INV(RAND(),$B$6,$C$6) | C29: =MIN(_xlfn.NORM.INV(RAND(),$B$7,$C$7),B29-0.005) | D29: =_xlfn.NORM.INV(RAND(),$B$8,$C$8) | E29: {=(SUMPRODUCT($B$13:$F$13*D29/(1+B29)^$B$14:$F$14)+($F$13*D29*(1+C29))/(B29-C29)/(1+B29)^$F$14-$B$15+$B$16)/$B$17} | H29: =$I$9+($I$10-$I$9)/12*(ROW()-22)
A30: =ROW()-22 | B30: =_xlfn.NORM.INV(RAND(),$B$6,$C$6) | C30: =MIN(_xlfn.NORM.INV(RAND(),$B$7,$C$7),B30-0.005) | D30: =_xlfn.NORM.INV(RAND(),$B$8,$C$8) | E30: {=(SUMPRODUCT($B$13:$F$13*D30/(1+B30)^$B$14:$F$14)+($F$13*D30*(1+C30))/(B30-C30)/(1+B30)^$F$14-$B$15+$B$16)/$B$17} | H30: =$I$9+($I$10-$I$9)/12*(ROW()-22)
A31: =ROW()-22 | B31: =_xlfn.NORM.INV(RAND(),$B$6,$C$6) | C31: =MIN(_xlfn.NORM.INV(RAND(),$B$7,$C$7),B31-0.005) | D31: =_xlfn.NORM.INV(RAND(),$B$8,$C$8) | E31: {=(SUMPRODUCT($B$13:$F$13*D31/(1+B31)^$B$14:$F$14)+($F$13*D31*(1+C31))/(B31-C31)/(1+B31)^$F$14-$B$15+$B$16)/$B$17} | H31: =$I$9+($I$10-$I$9)/12*(ROW()-22)
A32: =ROW()-22 | B32: =_xlfn.NORM.INV(RAND(),$B$6,$C$6) | C32: =MIN(_xlfn.NORM.INV(RAND(),$B$7,$C$7),B32-0.005) | D32: =_xlfn.NORM.INV(RAND(),$B$8,$C$8) | E32: {=(SUMPRODUCT($B$13:$F$13*D32/(1+B32)^$B$14:$F$14)+($F$13*D32*(1+C32))/(B32-C32)/(1+B32)^$F$14-$B$15+$B$16)/$B$17} | H32: =$I$9+($I$10-$I$9)/12*(ROW()-22)
A33: =ROW()-22 | B33: =_xlfn.NORM.INV(RAND(),$B$6,$C$6) | C33: =MIN(_xlfn.NORM.INV(RAND(),$B$7,$C$7),B33-0.005) | D33: =_xlfn.NORM.INV(RAND(),$B$8,$C$8) | E33: {=(SUMPRODUCT($B$13:$F$13*D33/(1+B33)^$B$14:$F$14)+($F$13*D33*(1+C33))/(B33-C33)/(1+B33)^$F$14-$B$15+$B$16)/$B$17} | H33: =$I$9+($I$10-$I$9)/12*(ROW()-22)
A34: =ROW()-22 | B34: =_xlfn.NORM.INV(RAND(),$B$6,$C$6) | C34: =MIN(_xlfn.NORM.INV(RAND(),$B$7,$C$7),B34-0.005) | D34: =_xlfn.NORM.INV(RAND(),$B$8,$C$8) | E34: {=(SUMPRODUCT($B$13:$F$13*D34/(1+B34)^$B$14:$F$14)+($F$13*D34*(1+C34))/(B34-C34)/(1+B34)^$F$14-$B$15+$B$16)/$B$17} | H34: =$I$9+($I$10-$I$9)/12*(ROW()-22)
A35: =ROW()-22 | B35: =_xlfn.NORM.INV(RAND(),$B$6,$C$6) | C35: =MIN(_xlfn.NORM.INV(RAND(),$B$7,$C$7),B35-0.005) | D35: =_xlfn.NORM.INV(RAND(),$B$8,$C$8) | E35: {=(SUMPRODUCT($B$13:$F$13*D35/(1+B35)^$B$14:$F$14)+($F$13*D35*(1+C35))/(B35-C35)/(1+B35)^$F$14-$B$15+$B$16)/$B$17}
A36: =ROW()-22 | B36: =_xlfn.NORM.INV(RAND(),$B$6,$C$6) | C36: =MIN(_xlfn.NORM.INV(RAND(),$B$7,$C$7),B36-0.005) | D36: =_xlfn.NORM.INV(RAND(),$B$8,$C$8) | E36: {=(SUMPRODUCT($B$13:$F$13*D36/(1+B36)^$B$14:$F$14)+($F$13*D36*(1+C36))/(B36-C36)/(1+B36)^$F$14-$B$15+$B$16)/$B$17}
A37: =ROW()-22 | B37: =_xlfn.NORM.INV(RAND(),$B$6,$C$6) | C37: =MIN(_xlfn.NORM.INV(RAND(),$B$7,$C$7),B37-0.005) | D37: =_xlfn.NORM.INV(RAND(),$B$8,$C$8) | E37: {=(SUMPRODUCT($B$13:$F$13*D37/(1+B37)^$B$14:$F$14)+($F$13*D37*(1+C37))/(B37-C37)/(1+B37)^$F$14-$B$15+$B$16)/$B$17}
A38: =ROW()-22 | B38: =_xlfn.NORM.INV(RAND(),$B$6,$C$6) | C38: =MIN(_xlfn.NORM.INV(RAND(),$B$7,$C$7),B38-0.005) | D38: =_xlfn.NORM.INV(RAND(),$B$8,$C$8) | E38: {=(SUMPRODUCT($B$13:$F$13*D38/(1+B38)^$B$14:$F$14)+($F$13*D38*(1+C38))/(B38-C38)/(1+B38)^$F$14-$B$15+$B$16)/$B$17}
A39: =ROW()-22 | B39: =_xlfn.NORM.INV(RAND(),$B$6,$C$6) | C39: =MIN(_xlfn.NORM.INV(RAND(),$B$7,$C$7),B39-0.005) | D39: =_xlfn.NORM.INV(RAND(),$B$8,$C$8) | E39: {=(SUMPRODUCT($B$13:$F$13*D39/(1+B39)^$B$14:$F$14)+($F$13*D39*(1+C39))/(B39-C39)/(1+B39)^$F$14-$B$15+$B$16)/$B$17}
A40: =ROW()-22 | B40: =_xlfn.NORM.INV(RAND(),$B$6,$C$6) | C40: =MIN(_xlfn.NORM.INV(RAND(),$B$7,$C$7),B40-0.005) | D40: =_xlfn.NORM.INV(RAND(),$B$8,$C$8) | E40: {=(SUMPRODUCT($B$13:$F$13*D40/(1+B40)^$B$14:$F$14)+($F$13*D40*(1+C40))/(B40-C40)/(1+B40)^$F$14-$B$15+$B$16)/$B$17}
A41: =ROW()-22 | B41: =_xlfn.NORM.INV(RAND(),$B$6,$C$6) | C41: =MIN(_xlfn.NORM.INV(RAND(),$B$7,$C$7),B41-0.005) | D41: =_xlfn.NORM.INV(RAND(),$B$8,$C$8) | E41: {=(SUMPRODUCT($B$13:$F$13*D41/(1+B41)^$B$14:$F$14)+($F$13*D41*(1+C41))/(B41-C41)/(1+B41)^$F$14-$B$15+$B$16)/$B$17}
A42: =ROW()-22 | B42: =_xlfn.NORM.INV(RAND(),$B$6,$C$6) | C42: =MIN(_xlfn.NORM.INV(RAND(),$B$7,$C$7),B42-0.005) | D42: =_xlfn.NORM.INV(RAND(),$B$8,$C$8) | E42: {=(SUMPRODUCT($B$13:$F$13*D42/(1+B42)^$B$14:$F$14)+($F$13*D42*(1+C42))/(B42-C42)/(1+B42)^$F$14-$B$15+$B$16)/$B$17}
A43: =ROW()-22 | B43: =_xlfn.NORM.INV(RAND(),$B$6,$C$6) | C43: =MIN(_xlfn.NORM.INV(RAND(),$B$7,$C$7),B43-0.005) | D43: =_xlfn.NORM.INV(RAND(),$B$8,$C$8) | E43: {=(SUMPRODUCT($B$13:$F$13*D43/(1+B43)^$B$14:$F$14)+($F$13*D43*(1+C43))/(B43-C43)/(1+B43)^$F$14-$B$15+$B$16)/$B$17}
A44: =ROW()-22 | B44: =_xlfn.NORM.INV(RAND(),$B$6,$C$6) | C44: =MIN(_xlfn.NORM.INV(RAND(),$B$7,$C$7),B44-0.005) | D44: =_xlfn.NORM.INV(RAND(),$B$8,$C$8) | E44: {=(SUMPRODUCT($B$13:$F$13*D44/(1+B44)^$B$14:$F$14)+($F$13*D44*(1+C44))/(B44-C44)/(1+B44)^$F$14-$B$15+$B$16)/$B$17}
A45: =ROW()-22 | B45: =_xlfn.NORM.INV(RAND(),$B$6,$C$6) | C45: =MIN(_xlfn.NORM.INV(RAND(),$B$7,$C$7),B45-0.005) | D45: =_xlfn.NORM.INV(RAND(),$B$8,$C$8) | E45: {=(SUMPRODUCT($B$13:$F$13*D45/(1+B45)^$B$14:$F$14)+($F$13*D45*(1+C45))/(B45-C45)/(1+B45)^$F$14-$B$15+$B$16)/$B$17}
A46: =ROW()-22 | B46: =_xlfn.NORM.INV(RAND(),$B$6,$C$6) | C46: =MIN(_xlfn.NORM.INV(RAND(),$B$7,$C$7),B46-0.005) | D46: =_xlfn.NORM.INV(RAND(),$B$8,$C$8) | E46: {=(SUMPRODUCT($B$13:$F$13*D46/(1+B46)^$B$14:$F$14)+($F$13*D46*(1+C46))/(B46-C46)/(1+B46)^$F$14-$B$15+$B$16)/$B$17}
... A1022: =ROW()-22 | B1022: =_xlfn.NORM.INV(RAND(),$B$6,$C$6) | C1022: =MIN(_xlfn.NORM.INV(RAND(),$B$7,$C$7),B1022-0.005) | D1022: =_xlfn.NORM.INV(RAND(),$B$8,$C$8) | E1022: {=(SUMPRODUCT($B$13:$F$13*D1022/(1+B1022)^$B$14:$F$14)+($F$13*D1022*(1+C1022))/(B1022-C1022)/(1+B1022)^$F$14-$B$15+$B$16)/$B$17}

Sheet Estimate Sheet
B1: Anup Engineering Limited
B2: Fiscal year ending 31st Mar, 2026
B3: All amounts in ₹ crores except per share data
B5: PREVIEW TABLE
B6: Particulars | C6: FY26 E | D6: FY26 Consensus | E6: FY25 (PY) | F6: FY26 Actual | G6: YoY% | H6: Vs Estimate % | I6: Vs Consensus %
B7: FINANCIAL METRICS
B8: Revenue | C8: 847.93139 | D8: 858.3333 | E8: ='Income Statement'!Q8 | F8: ='Income Statement'!T8 | G8: =(F8/E8)-1 | H8: =(F8/C8)-1 | I8: =(F8/D8)-1
B9: Gross Profit | C9: 427.15231 | D9: 424.4458 | E9: ='Income Statement'!Q17 | F9: ='Income Statement'!T17 | G9: =(F9/E9)-1 | H9: =(F9/C9)-1 | I9: =(F9/D9)-1
B10: Gross Margin % | C10: =C9/C8 | D10: =D9/D8 | E10: =E9/E8 | F10: =F9/F8 | G10: =(F10/E10)-1 | H10: =(F10/C10)-1 | I10: =(F10/D10)-1
B12: EBITDA | C12: 191.755 | D12: 190.0667 | E12: ='Income Statement'!Q23 | F12: ='Income Statement'!T23 | G12: =(F12/E12)-1 | H12: =(F12/C12)-1 | I12: =(F12/D12)-1
B13: EBITDA Margin % | C13: =C12/C8 | D13: =D12/D8 | E13: =E12/E8 | F13: =F12/F8 | G13: =(F13/E13)-1 | H13: =(F13/C13)-1 | I13: =(F13/D13)-1
B15: EBIT | C15: 165.94381 | D15: 153.3 | E15: ='Income Statement'!Q27 | F15: ='Income Statement'!T27 | G15: =(F15/E15)-1 | H15: =(F15/C15)-1 | I15: =(F15/D15)-1
B16: EBIT Margin % | C16: =C15/C8 | D16: =D15/D8 | E16: =E15/E8 | F16: =F15/F8 | G16: =(F16/E16)-1 | H16: =(F16/C16)-1 | I16: =(F16/D16)-1
B18: PBT | C18: 157.83448 | D18: 163.6 | E18: ='Income Statement'!Q32 | F18: ='Income Statement'!T32 | G18: =(F18/E18)-1 | H18: =(F18/C18)-1 | I18: =(F18/D18)-1
B19: PBT Margin % | C19: =C18/C8 | D19: =D18/D8 | E19: =E18/E8 | F19: =F18/F8 | G19: =(F19/E19)-1 | H19: =(F19/C19)-1 | I19: =(F19/D19)-1
B21: PAT | C21: 117.83181 | D21: 124.0333 | E21: ='Income Statement'!Q43 | F21: ='Income Statement'!T43 | G21: =(F21/E21)-1 | H21: =(F21/C21)-1 | I21: =(F21/D21)-1
B22: PAT Margin % | C22: =C21/C8 | D22: =D21/D8 | E22: =E21/E8 | F22: =F21/F8 | G22: =(F22/E22)-1 | H22: =(F22/C22)-1 | I22: =(F22/D22)-1
B24: EPS | C24: 58.837946 | D24: 61.9 | E24: ='Income Statement'!Q49 | F24: ='Income Statement'!T49 | G24: =(F24/E24)-1 | H24: =(F24/C24)-1 | I24: =(F24/D24)-1
B25: Dividend per share | C25: 17 | D25: 17.42 | E25: ='Income Statement'!Q53 | F25: ='Income Statement'!T53 | G25: =(F25/E25)-1 | H25: =(F25/C25)-1 | I25: =(F25/D25)-1
B27: Capex | C27: 66 | D27: 60 | E27: ='Balance Sheet'!Q64 | F27: ='Balance Sheet'!T64 | G27: =(F27/E27)-1 | H27: =(F27/C27)-1 | I27: =(F27/D27)-1
B29: OPERATIONAL METRICS
B30: Closing Order Book:
B31: Heat Exchangers | C31: 412.83106 | E31: ='Revenue Segments'!Q17 | F31: ='Revenue Segments'!T17 | G31: =(F31/E31)-1 | H31: =(F31/C31)-1
B32: Vessels | C32: 121.1 | E32: ='Revenue Segments'!Q29 | F32: ='Revenue Segments'!T29 | G32: =(F32/E32)-1 | H32: =(F32/C32)-1
B33: Towers & Reactors | C33: 26.35139 | E33: ='Revenue Segments'!Q41 | F33: ='Revenue Segments'!T41 | G33: =(F33/E33)-1 | H33: =(F33/C33)-1
B34: Tank & Silos | C34: 54.068 | E34: ='Revenue Segments'!Q53 | F34: ='Revenue Segments'!T53 | G34: =(F34/E34)-1 | H34: =(F34/C34)-1
B35: Centrifuge & Others | C35: 16.586272 | E35: ='Revenue Segments'!Q65 | F35: ='Revenue Segments'!T65 | G35: =(F35/E35)-1 | H35: =(F35/C35)-1
B36: Total Order Book (Clg) | C36: =SUM(C31:C35) | E36: =SUM(E31:E35) | F36: =SUM(F31:F35) | G36: =(F36/E36)-1 | H36: =(F36/C36)-1
B38: Order Inflows:
B39: Heat Exchangers | C39: 567.19832 | E39: ='Revenue Segments'!Q11 | F39: ='Revenue Segments'!T11 | G39: =(F39/E39)-1 | H39: =(F39/C39)-1
B40: Vessels | C40: 96.333333 | E40: ='Revenue Segments'!Q23 | F40: ='Revenue Segments'!T23 | G40: =(F40/E40)-1 | H40: =(F40/C40)-1
B41: Towers & Reactors | C41: 12.418984 | E41: ='Revenue Segments'!Q35 | F41: ='Revenue Segments'!T35 | G41: =(F41/E41)-1 | H41: =(F41/C41)-1
B42: Tank & Silos | C42: 53.94 | E42: ='Revenue Segments'!Q47 | F42: ='Revenue Segments'!T47 | G42: =(F42/E42)-1 | H42: =(F42/C42)-1
B43: Centrifuge & Others | C43: 34.658333 | E43: ='Revenue Segments'!Q59 | F43: ='Revenue Segments'!T59 | G43: =(F43/E43)-1 | H43: =(F43/C43)-1
B44: Total Order Inflows | C44: =SUM(C39:C43) | E44: =SUM(E39:E43) | F44: =SUM(F39:F43) | G44: =(F44/E44)-1 | H44: =(F44/C44)-1

Sheet Peer Comps
B1: Anup Engineering Limited
B2: Fiscal year ending 31st Mar, 2026
B3: All amounts in ₹ crores except per share data
B5: Relative Valuation
C6: Income Statement Wise | L6: Balance Sheet Wise | S6: Market Data
B7: Peer Set | C7: Revenue | D7: Gross profit | E7: Gross margin | F7: EBITDA | G7: EBITDA margin | H7: Net Earnings | I7: Net margin | J7: EPS | K7: Debt | L7: Cash | M7: Total Equity | N7: Total Assets | O7: Debt/Equity | P7: ROE | Q7: ROCE=EBIT/ TA-CL | R7: ROA | S7: CMP | T7: No. of o/s Shares | U7: Market Cap | V7: EV | W7: P/E Ratio | X7: EV/EBITDA | Y7: P/B Ratio
B8: ISGEC Heavy Engineering | C8: ='Peer Data'!I9 | D8: ='Peer Data'!J9 | E8: =D8/C8 | F8: ='Peer Data'!K9 | G8: =F8/C8 | H8: ='Peer Data'!M9 | I8: =H8/C8 | J8: =H8/T8 | K8: ='Peer Data'!D46 | L8: ='Peer Data'!D47 | M8: ='Peer Data'!D48 | N8: ='Peer Data'!D49 | O8: =K8/M8 | P8: =H8/M8 | Q8: ='Peer Data'!D30/('Peer Data'!D49-'Peer Data'!D51) | R8: =H8/N8 | S8: ='Peer Data'!D9 | T8: ='Peer Data'!C9 | U8: ='Peer Data'!E9 | V8: ='Peer Data'!H9 | W8: =S8/J8 | X8: =V8/F8 | Y8: =U8/M8
B9: Praj Industries | C9: ='Peer Data'!I10 | D9: ='Peer Data'!J10 | E9: =D9/C9 | F9: ='Peer Data'!K10 | G9: =F9/C9 | H9: ='Peer Data'!M10 | I9: =H9/C9 | J9: =H9/T9 | K9: ='Peer Data'!E46 | L9: ='Peer Data'!E47 | M9: ='Peer Data'!E48 | N9: ='Peer Data'!E49 | O9: =K9/M9 | P9: =H9/M9 | Q9: ='Peer Data'!E30/('Peer Data'!E49-'Peer Data'!E51) | R9: =H9/N9 | S9: ='Peer Data'!D10 | T9: ='Peer Data'!C10 | U9: ='Peer Data'!E10 | V9: ='Peer Data'!H10 | W9: =S9/J9 | X9: =V9/F9 | Y9: =U9/M9
B10: GMM Pfaudler | C10: ='Peer Data'!I11 | D10: ='Peer Data'!J11 | E10: =D10/C10 | F10: ='Peer Data'!K11 | G10: =F10/C10 | H10: ='Peer Data'!M11 | I10: =H10/C10 | J10: =H10/T10 | K10: ='Peer Data'!F46 | L10: ='Peer Data'!F47 | M10: ='Peer Data'!F48 | N10: ='Peer Data'!F48 | O10: =K10/M10 | P10: =H10/M10 | Q10: ='Peer Data'!F30/('Peer Data'!F49-'Peer Data'!F51) | R10: =H10/N10 | S10: ='Peer Data'!D11 | T10: ='Peer Data'!C11 | U10: ='Peer Data'!E11 | V10: ='Peer Data'!H11 | W10: =S10/J10 | X10: =V10/F10 | Y10: =U10/M10
B11: Anup Engineering Ltd | C11: ='Peer Data'!I14 | D11: ='Peer Data'!J14 | E11: =D11/C11 | F11: ='Peer Data'!K14 | G11: =F11/C11 | H11: ='Peer Data'!M14 | I11: =H11/C11 | J11: =H11/T11 | K11: ='Peer Data'!C46 | L11: ='Peer Data'!C47 | M11: ='Peer Data'!C48 | N11: ='Peer Data'!C48 | O11: =K11/M11 | P11: =H11/M11 | Q11: ='Peer Data'!C30/('Peer Data'!C49-'Peer Data'!C51) | R11: =H11/N11 | S11: ='Peer Data'!D14 | T11: ='Peer Data'!C14 | U11: ='Peer Data'!E14 | V11: ='Peer Data'!H14 | W11: =S11/J11 | X11: =V11/F11 | Y11: =U11/M11
B12: Average | C12: =AVERAGE(C8:C11) | D12: =AVERAGE(D8:D11) | E12: =AVERAGE(E8:E11) | F12: =AVERAGE(F8:F11) | G12: =AVERAGE(G8:G11) | H12: =AVERAGE(H8:H11) | I12: =AVERAGE(I8:I11) | J12: =AVERAGE(J8:J11) | ... V12: =AVERAGE(V8:V11) | W12: =SUMPRODUCT(W8:W10,U8:U10)/SUM(U8:U10) | X12: =SUMPRODUCT(X8:X10,V8:V10)/SUM(V8:V10) | Y12: =AVERAGE(Y8:Y11)
B15: Relative Valuation a/o 5th June, 2026 | C15: EV/EBITDA
B16: Weighted Average Value | C16: =X12
B17: Implied Price | C17: =((C16*F11)-K11+L11)/T11

Sheet Peer Data
B1: Anup Engineering Limited
B2: Fiscal year ending 31st Mar, 2026
B3: All amounts in ₹ crores except per share data
B5: Comparable Company Analysis
B6: Particulars | C6: Market Data | F6: Financial Data | M6: Valuation
C7: Shares O/s | D7: MPS | E7: Market Cap | F7: Cash | G7: Debt | H7: EV | I7: Sales | J7: Gross Profit | K7: EBITDA | L7: EBIT | M7: Net Earnings | N7: Price/ Sales | O7: EV/EBITDA | P7: EV/EBIT
B8: Peer Company | D8: a/o 16 October, 2026 | E8: a/o 16 October, 2026
B9: ISGEC Heavy Engineering | C9: =D53 | D9: 899.75 | E9: =C9*D9 | F9: =D47 | G9: =D46 | H9: =E9+G9-F9 | I9: =D$20 | J9: =D25 | K9: =D28 | L9: =D30 | M9: =D40 | N9: =E9/I9 | O9: =H9/K9 | P9: =H9/L9
B10: Praj Industries | C10: =E53 | D10: 287.15 | E10: =C10*D10 | F10: =E47 | G10: =E46 | H10: =E10+G10-F10 | I10: =E20 | J10: =E25 | K10: =E28 | L10: =E30 | M10: =E40 | N10: =E10/I10 | O10: =H10/K10 | P10: =H10/L10
B11: GMM Pfaudler | C11: =F53 | D11: 1312.1 | E11: =C11*D11 | F11: =F47 | G11: =F46 | H11: =E11+G11-F11 | I11: =F20 | J11: =F25 | K11: =F28 | L11: =F30 | M11: =F40 | N11: =E11/I11 | O11: =H11/K11 | P11: =H11/L11
B12: Thermax | C12: =G53 | D12: 3326.8 | E12: =C12*D12 | F12: =G47 | G12: =G46 | H12: =E12+G12-F12 | I12: =G20 | J12: =G25 | K12: =G28 | L12: =G30 | M12: =G40 | N12: =E12/I12 | O12: =H12/K12 | P12: =H12/L12
B13: Patels Airtemp India | C13: =H53 | D13: 360.8 | E13: =C13*D13 | F13: =H47 | G13: =H46 | H13: =E13+G13-F13 | I13: =H20 | J13: =H25 | K13: =H28 | L13: =H30 | M13: =H40 | N13: =E13/I13 | O13: =H13/K13 | P13: =H13/L13
B14: Anup Engineering Ltd | C14: =C53 | D14: 1488.5 | E14: =C14*D14 | F14: =C47 | G14: =C46 | H14: =E14+G14-F14 | I14: =C20 | J14: =C25 | K14: =C28 | L14: =C30 | M14: =C40 | N14: =E14/I14 | O14: =H14/K14 | P14: =H14/L14
B17: Income Statement
B18: Particulars | C18: FY26
C19: Anup Engineering Ltd | D19: ISGEC Heavy Engineering | E19: Praj Industries | F19: GMM Pfaudler | G19: Thermax | H19: Patels Airtemp India
B20: Revenue from Operations | C20: ='Income Statement'!T8 | D20: 6789.26 | E20: 3167.8828 | F20: 3523.94 | G20: 10694.15 | H20: 252.9347
B21: Cost of Materials Consumed | C21: ='Income Statement'!T12 | D21: 1994.86 | E21: 1476.1768 | F21: 1463.15 | G21: 5424.02 | H21: 116.3751
B22: Purchase of Stock-in-Trade | C22: 0 | D22: =1770.22+665.46 | E22: 139.2647 | F22: 0 | G22: 184.67 | H22: 0.6479
B23: Changes in Inventories | C23: ='Income Statement'!T13 | D23: -40.89 | E23: 4.5967 | F23: -68 | G23: -49.08 | H23: 33.4626
B24: Cost of Goods Sold | C24: =SUM(C21:C23) | D24: =SUM(D21:D23) | E24: =SUM(E21:E23) | F24: =SUM(F21:F23) | G24: =SUM(G21:G23) | H24: =SUM(H21:H23)
B25: Gross Profit | C25: =C20-C24 | D25: =D20-D24 | E25: =E20-E24 | F25: =F20-F24 | G25: =G20-G24 | H25: =H20-H24
B26: Employee Benefits Expenses | C26: ='Income Statement'!T20 | D26: 666.42 | E26: 345.7596 | F26: =1006.97+120.28 | G26: 1421.2 | H26: 17.3398
B27: Other Expenses | C27: ='Income Statement'!T22 | D27: 1178.46 | E27: 1050.3115 | F27: 598.92 | G27: =1396.11+42.82+1248.15+0.41 | H27: 61.7889
B28: EBITDA | C28: =C25-(C26+C27) | D28: =D25-(D26+D27) | E28: =E25-(E26+E27) | F28: =F25-(F26+F27) | G28: =G25-(G26+G27) | H28: =H25-(H26+H27)
B29: D&A Expenses | C29: ='Income Statement'!T26 | D29: 278.34 | E29: 105.5645 | F29: 157.61 | G29: 207.64 | H29: 3.5144
B30: EBIT/ Operating Income | C30: =C28-C29 | D30: =D28-D29 | E30: =E28-E29 | F30: =F28-F29 | G30: =G28-G29 | H30: =H28-H29
B31: Other Income | C31: ='Income Statement'!T30 | D31: 133.02 | E31: 50.3549 | F31: 45.07 | G31: 267.48 | H31: 4.043
B32: Finance Costs | C32: ='Income Statement'!T31 | D32: =85.1-0.08 | E32: 20.2652 | F32: 122.8 | G32: 138.96 | H32: 9.9503
B33: PBT | C33: =C30+C31-C32 | D33: =D30+D31-D32 | E33: =E30+E31-E32 | F33: =F30+F31-F32 | G33: =G30+G31-G32 | H33: =H30+H31-H32
B34: Current Tax | C34: ='Income Statement'!T38 | D34: 150.7 | E34: 58.358 | F34: 72.93 | G34: 268.05 | H34: 3.5573
B35: Earlier Years tax | C35: ='Income Statement'!T39 | D35: 0.22 | E35: 0 | F35: 0 | G35: 0 | H35: 0
B36: Deferred Tax | C36: ='Income Statement'!T40 | D36: 2.94 | E36: -32.2881 | F36: -22.78 | G36: 19.63 | H36: 0.0671
B37: Total Tax Expense | C37: =SUM(C34:C36) | D37: =SUM(D34:D36) | E37: =SUM(E34:E36) | F37: =SUM(F34:F36) | G37: =SUM(G34:G36) | H37: =SUM(H34:H36)
B38: PAT | C38: =C33-C37 | D38: =D33-D37 | E38: =E33-E37 | F38: =F33-F37 | G38: =G33-G37 | H38: =H33-H37
B39: Exceptional Items | C39: 0 | D39: -16.49 | E39: -26.3821 | F39: -65.31 | G39: 61.21 | H39: 0
B40: Net Profit | C40: =SUM(C38:C39) | D40: =SUM(D38:D39) | E40: =SUM(E38:E39) | F40: =SUM(F38:F39) | G40: =SUM(G38:G39) | H40: =SUM(H38:H39)
B43: Balance Sheet Items
B44: Particulars | C44: FY26
C45: Anup Engineering Ltd | D45: ISGEC Heavy Engineering | E45: Praj Industries | F45: GMM Pfaudler | G45: Thermax | H45: Patels Airtemp India
B46: Debt | C46: ='Balance Sheet'!T13+'Balance Sheet'!T19 | D46: =517.42+400.65 | E46: 0 | F46: =544.6+290.46 | G46: =672.18+1615.83 | H46: =83.1394
B47: Cash | C47: ='Balance Sheet'!T49+'Balance Sheet'!T50 | D47: =324.22+72.94 | E47: =142.3696+61.3724 | F47: =635.38+52.26 | G47: =674.45+516.21 | H47: =33.6562+0.1417
B48: Equity | C48: ='Balance Sheet'!T11 | D48: 2887.67 | E48: 1309.2537 | F48: 1232.99 | G48: 5579.19 | H48: 166.1066
B49: Total Assets | C49: ='Balance Sheet'!T55 | D49: 8077.14 | E49: 3055.8943 | F49: 4023.55 | G49: 13282.11 | H49: 297.3674
B50: Total Liabilities | C50: ='Balance Sheet'!T28+'Balance Sheet'!T17 | D50: =D49-D48 | E50: =E49-E48 | F50: =F49-F48 | G50: =G49-G48 | H50: =H49-H48
B51: Current Liabilities | C51: ='Balance Sheet'!T28 | D51: 4347.45 | E51: 1618.9786 | F51: 1515.46 | G51: 5820.36 | H51: 15.5746
B52: EPS | C52: ='Income Statement'!T49 | D52: ='Income Statement'!U49 | E52: =E40/E53 | F52: =F40/F53 | G52: 21.68 | H52: 18.78
B53: No of o/s shares | C53: 2.00315 | D53: 7.353 | E53: =36.7626/2 | F53: =8.99/2 | G53: =22.53/2 | H53: =5.4702/10

Sheet Beta
B1: Date | C1: Anup | E1: BSE Capital Goods Index | G1: Nifty 50 | J1: Date | K1: Anup | M1: BSE Capital Goods Index | O1: Nifty 50 | R1: Date | S1: Anup | U1: BSE Capital Goods Index | W1: Nifty 50
C2: Daily Closing Price | D2: Returns | E2: Daily Closing Price | F2: Returns | G2: Daily Closing Price | H2: Returns | K2: Weekly Closing Price | L2: Returns | M2: Weekly Closing Price | N2: Returns | O2: Weekly Closing Price | P2: Returns | S2: Monthly Closing Price | T2: Returns | U2: Monthly Closing Price | V2: Returns | W2: Monthly Closing Price | X2: Returns
B3: 46176 | C3: 1934.7 | D3: =C3/C4-1 | E3: 79354.73 | F3: =E3/E4-1 | G3: 23405.6 | H3: =G3/G4-1 | J3: 46176 | K3: 1934.7 | L3: =K3/K4-1 | M3: 79354.73 | N3: =M3/M4-1 | O3: 23405.6 | P3: =O3/O4-1 | R3: 46176 | S3: 1934.7 | T3: =S3/S4-1 | U3: 79354.73 | V3: =U3/U4-1 | W3: 23405.6 | X3: =W3/W4-1 | Z3: Beta (Monthly) | AA3: =SLOPE(T3:T62,V3:V62)
B4: 46175 | C4: 1870.3 | D4: =C4/C5-1 | E4: 79301.15 | F4: =E4/E5-1 | G4: 23483.55 | H4: =G4/G5-1 | J4: 46173 | K4: 1840.4 | L4: =K4/K5-1 | M4: 80818.74 | N4: =M4/M5-1 | O4: 23547.75 | P4: =O4/O5-1 | R4: 46173 | S4: 1840.4 | T4: =S4/S5-1 | U4: 80818.74 | V4: =U4/U5-1 | W4: 23547.75 | X4: =W4/W5-1 | Z4: Beta (Weekly) | AA4: =SLOPE(L3:L263,N3:N263)
B5: 46174 | C5: 1840.1 | D5: =C5/C6-1 | E5: 78848.83 | F5: =E5/E6-1 | G5: 23382.6 | H5: =G5/G6-1 | J5: 46166 | K5: 1977.6 | L5: =K5/K6-1 | M5: 78316.91 | N5: =M5/M6-1 | O5: 23719.3 | P5: =O5/O6-1 | R5: 46142 | S5: 2062.2 | T5: =S5/S6-1 | U5: 77210.23 | V5: =U5/U6-1 | W5: 23997.55 | X5: =W5/W6-1 | Z5: Beta (Daily) | AA5: =SLOPE(D3:D1240,F3:F1240)
B6: 46171 | C6: 1840.4 | D6: =C6/C7-1 | E6: 80818.74 | F6: =E6/E7-1 | G6: 23547.75 | H6: =G6/G7-1 | J6: 46159 | K6: 1966.5 | L6: =K6/K7-1 | M6: 76826.42 | N6: =M6/M7-1 | O6: 23643.5 | P6: =O6/O7-1 | R6: 46112 | S6: 1603.7 | T6: =S6/S7-1 | U6: 64243.38 | V6: =U6/U7-1 | W6: 22331.4 | X6: =W6/W7-1 | Z6: Rf | AA6: 0.0696 | AB6: https://www.rbi.org.in/Scripts/BS_NSDPDisplay.aspx?param=4
B7: 46169 | C7: 1947 | D7: =C7/C8-1 | E7: 81647.91 | F7: =E7/E8-1 | G7: 23907.15 | H7: =G7/G8-1 | J7: 46152 | K7: 2161.9 | L7: =K7/K8-1 | M7: 80125.2 | N7: =M7/M8-1 | O7: 24176.15 | P7: =O7/O8-1 | R7: 46081 | S7: 1571.2 | T7: =S7/S8-1 | U7: 70454.47 | V7: =U7/U8-1 | W7: 25178.65 | X7: =W7/W8-1 | Z7: ERP | AA7: 0.0708 | AB7: https://pages.stern.nyu.edu/~adamodar/New_Home_Page/datafile/ctryprem.html
B8: 46168 | C8: 1981.2 | D8: =C8/C9-1 | E8: 79107.54 | F8: =E8/E9-1 | G8: 23913.7 | H8: =G8/G9-1 | J8: 46145 | K8: 2062.2 | L8: =K8/K9-1 | M8: 77210.23 | N8: =M8/M9-1 | O8: 23997.55 | P8: =O8/O9-1 | R8: 46053 | S8: 1771.2 | T8: =S8/S9-1 | U8: 66666.73 | V8: =U8/U9-1 | W8: 25320.65 | X8: =W8/W9-1 | Z8: Ke | AA8: =AA6+AA4*AA7
B9: 46167 | C9: 1977.7 | D9: =C9/C10-1 | E9: 78698.01 | F9: =E9/E10-1 | G9: 24031.7 | H9: =G9/G10-1 | J9: 46138 | K9: 2108.8 | L9: =K9/K10-1 | M9: 77089.06 | N9: =M9/M10-1 | O9: 23897.95 | P9: =O9/O10-1 | R9: 46022 | S9: 2243.1 | T9: =S9/S10-1 | U9: 67112 | V9: =U9/U10-1 | W9: 26129.6 | X9: =W9/W10-1
B10: 46164 | C10: 1977.6 | D10: =C10/C11-1 | E10: 78316.91 | F10: =E10/E11-1 | G10: 23719.3 | H10: =G10/G11-1 | J10: 46131 | K10: 2022.3 | L10: =K10/K11-1 | M10: 76112.21 | N10: =M10/M11-1 | O10: 24353.55 | P10: =O10/O11-1 | R10: 45991 | S10: 2259.8 | T10: =S10/S11-1 | U10: 69208.59 | V10: =U10/U11-1 | W10: 26202.95 | X10: =W10/W11-1
B11: 46163 | C11: 1978.4 | D11: =C11/C12-1 | E11: 78274.9 | F11: =E11/E12-1 | G11: 23654.7 | H11: =G11/G12-1 | J11: 46124 | K11: 1911.8 | L11: =K11/K12-1 | M11: 72180.77 | N11: =M11/M12-1 | O11: 24050.6 | P11: =O11/O12-1 | R11: 45961 | S11: 2307.2 | T11: =S11/S12-1 | U11: 70404.39 | V11: =U11/U12-1 | W11: 25722.1 | X11: =W11/W12-1
B12: 46162 | C12: 1952 | D12: =C12/C13-1 | E12: 77278.48 | F12: =E12/E13-1 | G12: 23659 | H12: =G12/G13-1 | J12: 46117 | K12: 1748.8 | L12: =K12/K13-1 | M12: 66360.28 | N12: =M12/M13-1 | O12: 22713.1 | P12: =O12/O13-1 | R12: 45930 | S12: 2347.1 | T12: =S12/S13-1 | U12: 68289.99 | V12: =U12/U13-1 | W12: 24611.1 | X12: =W12/W13-1
B13: 46161 | C13: 1955.5 | D13: =C13/C14-1 | E13: 76118.17 | F13: =E13/E14-1 | G13: 23618 | H13: =G13/G14-1 | J13: 46110 | K13: 1672.8 | L13: =K13/K14-1 | M13: 65702.59 | N13: =M13/M14-1 | O13: 22819.6 | P13: =O13/O14-1 | R13: 45900 | S13: 2214.7 | T13: =S13/S14-1 | U13: 65417.08 | V13: =U13/U14-1 | W13: 24426.85 | X13: =W13/W14-1
B14: 46160 | C14: 1929.6 | D14: =C14/C15-1 | E14: 76219.01 | F14: =E14/E15-1 | G14: 23649.95 | H14: =G14/G15-1 | J14: 46103 | K14: 1588.2 | L14: =K14/K15-1 | M14: 67344.39 | N14: =M14/M15-1 | O14: 23114.5 | P14: =O14/O15-1 | R14: 45869 | S14: 2645.3 | T14: =S14/S15-1 | U14: 68236.66 | V14: =U14/U15-1 | W14: 24768.35 | X14: =W14/W15-1
B15: 46157 | C15: 1966.5 | D15: =C15/C16-1 | E15: 76826.42 | F15: =E15/E16-1 | G15: 23643.5 | H15: =G15/G16-1 | J15: 46096 | K15: 1521.8 | L15: =K15/K16-1 | M15: 67620.2 | N15: =M15/M16-1 | O15: 23151.1 | P15: =O15/O16-1 | R15: 45838 | S15: 2769.1 | T15: =S15/S16-1 | U15: 72332.77 | V15: =U15/U16-1 | W15: 25517.05 | X15: =W15/W16-1
B16: 46156 | C16: 1961.4 | D16: =C16/C17-1 | E16: 77604.31 | F16: =E16/E17-1 | G16: 23689.6 | H16: =G16/G17-1 | J16: 46089 | K16: 1479.2 | L16: =K16/K17-1 | M16: 70618.46 | N16: =M16/M17-1 | O16: 24450.45 | P16: =O16/O17-1 | R16: 45808 | S16: 2778.2 | T16: =S16/S17-1 | U16: 71089.64 | V16: =U16/U17-1 | W16: 24750.7 | X16: =W16/W17-1
B17: 46155 | C17: 1979.2 | D17: =C17/C18-1 | E17: 77073.96 | F17: =E17/E18-1 | G17: 23412.6 | H17: =G17/G18-1 | J17: 46082 | K17: 1571.2 | L17: =K17/K18-1 | M17: 70454.47 | N17: =M17/M18-1 | O17: 25178.65 | P17: =O17/O18-1 | R17: 45777 | S17: 2989.4 | T17: =S17/S18-1 | U17: 62780.39 | V17: =U17/U18-1 | W17: 24334.2 | X17: =W17/W18-1
B18: 46154 | C18: 1970.4 | D18: =C18/C19-1 | E18: 76216.88 | F18: =E18/E19-1 | G18: 23379.55 | H18: =G18/G19-1 | J18: 46075 | K18: 1700.5 | L18: =K18/K19-1 | M18: 69612.86 | N18: =M18/M19-1 | O18: 25571.25 | P18: =O18/O19-1 | R18: 45747 | S18: 3475.5 | T18: =S18/S19-1 | U18: 62724.28 | V18: =U18/U19-1 | W18: 23519.35 | X18: =W18/W19-1
B19: 46153 | C19: 2067.6 | D19: =C19/C20-1 | E19: 78453.03 | F19: =E19/E20-1 | G19: 23815.85 | H19: =G19/G20-1 | J19: 46068 | K19: 1984.5 | L19: =K19/K20-1 | M19: 68243.17 | N19: =M19/M20-1 | O19: 25471.1 | P19: =O19/O20-1 | R19: 45716 | S19: 2798.15 | T19: =S19/S20-1 | U19: 55241.12 | V19: =U19/U20-1 | W19: 22124.7 | X19: =W19/W20-1
B20: 46150 | C20: 2161.9 | D20: =C20/C21-1 | E20: 80125.2 | F20: =E20/E21-1 | G20: 24176.15 | H20: =G20/G21-1 | J20: 46061 | K20: 1933.7 | L20: =K20/K21-1 | M20: 67752.3 | N20: =M20/M21-1 | O20: 25693.7 | P20: =O20/O21-1 | R20: 45688 | S20: 2824.6 | T20: =S20/S21-1 | U20: 64529.77 | V20: =U20/U21-1 | W20: 23508.4 | X20: =W20/W21-1
... B62: 46085 | C62: 1490.2 | D62: =C62/C63-1 | E62: 68146.84 | F62: =E62/E63-1 | G62: 24480.5 | H62: =G62/G63-1 | J62: 45767 | K62: 3167.1 | L62: =K62/K63-1 | M62: 61111.69 | N62: =M62/M63-1 | O62: 23851.65 | P62: =O62/O63-1 | R62: 44408 | S62: 513.88 | T62: =S62/S63-1 | U62: 23671.73 | V62: =U62/U63-1 | W62: 15763.05 | X62: =W62/W63-1
B63: 46083 | C63: 1557.8 | D63: =C63/C64-1 | E63: 69993.72 | F63: =E63/E64-1 | G63: 24865.7 | H63: =G63/G64-1 | J63: 45760 | K63: 3064.45 | L63: =K63/K64-1 | M63: 58545.93 | N63: =M63/M64-1 | O63: 22828.55 | P63: =O63/O64-1 | R63: 44377 | S63: 432.5 | U63: 22948.98 | W63: 15721.5
B64: 46080 | C64: 1571.2 | D64: =C64/C65-1 | E64: 70454.47 | F64: =E64/E65-1 | G64: 25178.65 | H64: =G64/G65-1 | J64: 45753 | K64: 3178 | L64: =K64/K65-1 | M64: 59643.57 | N64: =M64/M65-1 | O64: 22904.45 | P64: =O64/O65-1
B65: 46079 | C65: 1613.3 | D65: =C65/C66-1 | E65: 70804.27 | F65: =E65/E66-1 | G65: 25496.55 | H65: =G65/G66-1 | J65: 45746 | K65: 3475.5 | L65: =K65/K66-1 | M65: 62724.28 | N65: =M65/M66-1 | O65: 23519.35 | P65: =O65/O66-1
B66: 46078 | C66: 1586.2 | D66: =C66/C67-1 | E66: 70188.31 | F66: =E66/E67-1 | G66: 25482.5 | H66: =G66/G67-1 | J66: 45739 | K66: 3266.55 | L66: =K66/K67-1 | M66: 61901.78 | N66: =M66/M67-1 | O66: 23350.4 | P66: =O66/O67-1
B67: 46077 | C67: 1630.6 | D67: =C67/C68-1 | E67: 69999.43 | F67: =E67/E68-1 | G67: 25424.65 | H67: =G67/G68-1 | J67: 45732 | K67: 2886.4 | L67: =K67/K68-1 | M67: 57756.79 | N67: =M67/M68-1 | O67: 22397.2 | P67: =O67/O68-1
B68: 46076 | C68: 1729.5 | D68: =C68/C69-1 | E68: 69774.05 | F68: =E68/E69-1 | G68: 25713 | H68: =G68/G69-1 | J68: 45725 | K68: 3057.95 | L68: =K68/K69-1 | M68: 58911.86 | N68: =M68/M69-1 | O68: 22552.5 | P68: =O68/O69-1
B69: 46073 | C69: 1700.5 | D69: =C69/C70-1 | E69: 69612.86 | F69: =E69/E70-1 | G69: 25571.25 | H69: =G69/G70-1 | J69: 45718 | K69: 2798.15 | L69: =K69/K70-1 | M69: 55241.12 | N69: =M69/M70-1 | O69: 22124.7 | P69: =O69/O70-1
B70: 46072 | C70: 1728.4 | D70: =C70/C71-1 | E70: 68578.35 | F70: =E70/E71-1 | G70: 25454.35 | H70: =G70/G71-1 | J70: 45711 | K70: 3179.85 | L70: =K70/K71-1 | M70: 58398.81 | N70: =M70/M71-1 | O70: 22795.9 | P70: =O70/O71-1
B71: 46071 | C71: 1798.3 | D71: =C71/C72-1 | E71: 70104.62 | F71: =E71/E72-1 | G71: 25819.35 | H71: =G71/G72-1 | J71: 45704 | K71: 2732.1 | L71: =K71/K72-1 | M71: 57349.1 | N71: =M71/M72-1 | O71: 22929.25 | P71: =O71/O72-1
B72: 46070 | C72: 1796.4 | D72: =C72/C73-1 | E72: 69483.84 | F72: =E72/E73-1 | G72: 25725.4 | H72: =G72/G73-1 | J72: 45697 | K72: 2798.7 | L72: =K72/K73-1 | M72: 61074.9 | N72: =M72/M73-1 | O72: 23559.95 | P72: =O72/O73-1
B73: 46069 | C73: 1883.5 | D73: =C73/C74-1 | E73: 68957.07 | F73: =E73/E74-1 | G73: 25682.75 | H73: =G73/G74-1 | J73: 45690 | K73: 3027.8 | L73: =K73/K74-1 | M73: 62581.73 | N73: =M73/M74-1 | O73: 23482.15 | P73: =O73/O74-1
B74: 46066 | C74: 1984.5 | D74: =C74/C75-1 | E74: 68243.17 | F74: =E74/E75-1 | G74: 25471.1 | H74: =G74/G75-1 | J74: 45683 | K74: 2950.9 | L74: =K74/K75-1 | M74: 62231.16 | N74: =M74/M75-1 | O74: 23092.2 | P74: =O74/O75-1
B75: 46065 | C75: 2046.4 | D75: =C75/C76-1 | E75: 69045.33 | F75: =E75/E76-1 | G75: 25807.2 | H75: =G75/G76-1 | J75: 45676 | K75: 3100.4 | L75: =K75/K76-1 | M75: 65179.63 | N75: =M75/M76-1 | O75: 23203.2 | P75: =O75/O76-1
... B263: 45792 | C263: 2979.8 | D263: =C263/C264-1 | E263: 67802.23 | F263: =E263/E264-1 | G263: 25062.1 | H263: =G263/G264-1 | J263: 44360 | K263: 444.35 | L263: =K263/K264-1 | M263: 22917.69 | N263: =M263/M264-1 | O263: 15799.35 | P263: =O263/O264-1
B264: 45791 | C264: 2993.8 | D264: =C264/C265-1 | E264: 66938.23 | F264: =E264/E265-1 | G264: 24666.9 | H264: =G264/G265-1 | J264: 44353 | K264: 446.1 | M264: 23279.53 | O264: 15670.25
B265: 45790 | C265: 3025.2 | D265: =C265/C266-1 | E265: 65952.78 | F265: =E265/E266-1 | G265: 24578.35 | H265: =G265/G266-1
B266: 45789 | C266: 3301.8 | D266: =C266/C267-1 | E266: 65274.44 | F266: =E266/E267-1 | G266: 24924.7 | H266: =G266/G267-1
B267: 45786 | C267: 3158 | D267: =C267/C268-1 | E267: 62852.21 | F267: =E267/E268-1 | G267: 24008 | H267: =G267/G268-1
B268: 45785 | C268: 3093.6 | D268: =C268/C269-1 | E268: 61820.63 | F268: =E268/E269-1 | G268: 24273.8 | H268: =G268/G269-1
B269: 45784 | C269: 3119.5 | D269: =C269/C270-1 | E269: 62384 | F269: =E269/E270-1 | G269: 24414.4 | H269: =G269/G270-1
B270: 45783 | C270: 3041.4 | D270: =C270/C271-1 | E270: 62117.06 | F270: =E270/E271-1 | G270: 24379.6 | H270: =G270/G271-1
B271: 45782 | C271: 3115.8 | D271: =C271/C272-1 | E271: 63200.61 | F271: =E271/E272-1 | G271: 24461.15 | H271: =G271/G272-1
B272: 45779 | C272: 2914.1 | D272: =C272/C273-1 | E272: 62668.31 | F272: =E272/E273-1 | G272: 24346.7 | H272: =G272/G273-1
B273: 45777 | C273: 2989.4 | D273: =C273/C274-1 | E273: 62780.39 | F273: =E273/E274-1 | G273: 24334.2 | H273: =G273/G274-1
B274: 45776 | C274: 3089.4 | D274: =C274/C275-1 | E274: 63289.87 | F274: =E274/E275-1 | G274: 24335.95 | H274: =G274/G275-1
B275: 45775 | C275: 3018 | D275: =C275/C276-1 | E275: 62698.43 | F275: =E275/E276-1 | G275: 24328.5 | H275: =G275/G276-1
B276: 45772 | C276: 3035.3 | D276: =C276/C277-1 | E276: 61508.96 | F276: =E276/E277-1 | G276: 24039.35 | H276: =G276/G277-1
... B1240: 44354 | C1240: 449.2 | D1240: =C1240/C1241-1 | E1240: 23434.58 | F1240: =E1240/E1241-1 | G1240: 15751.65 | H1240: =G1240/G1241-1
B1241: 44351 | C1241: 446.1 | E1241: 23279.53 | G1241: 15670.25

Sheet Risk Data
A1: USD/INR Volatility | E1: Brent-Crude Volatility | H1: Steel Price Volatility
A2: Date | B2: Daily USD/INR Rates | C2: Daily Log Return | D2: Brent-Crude log return (Days matched) | E2: Date | F2: Value ($) | G2: Daily Log Return | H2: Date | I2: Price | J2: Daily Log Return | L2: Risk Type | M2: Sigma
A3: 2/4/2026 | B3: 93.2088 | C3: =LN(B4/B3) | D3: =IFERROR(VLOOKUP(A3,E:G,3,FALSE)," ") | E3: 1/4/2026 | F3: 119.56 | G3: =LN(F4/F3) | H3: 1/4/2026 | I3: 45980 | J3: =LN(I4/I3) | L3: Currency Risk (USD/INR) | M3: =STDEV(C3:C243)*SQRT(252) | N3: RBI Website
A4: 30/3/2026 | B4: 94.6543 | C4: =LN(B5/B4) | D4: =IFERROR(VLOOKUP(A4,E:G,3,FALSE)," ") | E4: 31/3/2026 | F4: 126.69 | G4: =LN(F5/F4) | H4: 31/3/2026 | I4: 45190 | J4: =LN(I5/I4) | L4: Geoplitical Risk (Brent-Crude) | M4: =STDEV(G3:G255)*SQRT(260) | N4: Brent Crude Data
